Workbook

Sheet Observation
A6: Row Labels | B6: Sum of Accumulated Balance
A7: Assets | B7: 3.2091825e+09 | D7: =BS!F55 -> 2.9976385e+09 | E7: =D7-B7 -> -2.1154393e+08
A8: Liablities | B8: -3.4906291e+09 | C8: =B8+B9 -> -3.2091825e+09 | D8: =BS!F32 -> 2.9976385e+09 | E8: =D8+C8 -> -2.1154393e+08 | F8: =E8-E7 -> -0.46000004
A9: PNL | B9: 2.8144664e+08 | D9: =PL!G33 -> 1.2032169e+08 | E9: =D9+B9 -> 4.0176833e+08
A10: Grand Total | B10: -1.1920929e-07

Sheet BS
A2: Moonstone Realinfra Private Limited
A3: CIN :- U45201PN2022PTC207521
A4: A 102 ICC TRADE TOWER 403/A SENAPATI BAPAT ROAD PUNE , MH 411016
A5: Balance Sheet as at 31.03.2026
A6: Particulars | C6: Note No | D6: HO | F6: Construction Division | H6: Total
D7: =H7 -> Figures as at the end of 31.03.2026 | E7: Figures as at the end of 31.03.2025 | F7: =H7 -> Figures as at the end of 31.03.2026 | G7: Figures as at the end of 31.03.2025 | H7: Figures as at the end of 31.03.2026 | I7: Figures as at the end of 31.03.2025
A9: I. EQUITY AND LIABILITIES
A11: (1) Shareholder's Funds
A12: (a) Share Capital | C12: Note 1A | D12: 0 | E12: 0 | F12: =ESC!C18 -> 100000 | G12: 100000 | H12: =ESC!C18 -> 100000 | I12: =ESC!E18 -> 100000
A13: (b) Reserves and Surplus | C13: Note-1B | D13: =+Notes!B10 -> -30616.78 | E13: =Notes!C10 -> -30616.78 | F13: =Notes!D10 -> 87831217 | G13: =Notes!E10 -> -83426.209 | H13: =Notes!F10 -> 87800601 | I13: =Notes!G10 -> -114042.99
A14: (c) Money Received Against Share Warrants | G14: 0 | H14: =D14+F14 -> 0 | I14: =E14+G14 -> 0
A16: (2) Share Application Money Pending Allotment | E16: =Notes!C23 -> 0 | G16: 0 | H16: =D16+F16 -> 0 | I16: =E16+G16 -> 0
A18: (3) Non-Current Liabilities
A19: (a) Long-Term Borrowings | D19: 0 | E19: 0 | F19: =Notes!F19 -> 3.853325e+08 | G19: =Notes!G19 -> 0 | H19: =Notes!F19 -> 3.853325e+08 | I19: =Notes!G19 -> 0
A20: (b) Deferred Tax Liabilities (Net) | D20: 0 | E20: 0 | F20: 0 | G20: 0 | H20: =D20+F20 -> 0 | I20: =E20+G20 -> 0
A21: (c) Other Long Term Liabilities | D21: 0 | E21: 0 | F21: 0 | G21: 0 | H21: =D21+F21 -> 0 | I21: =E21+G21 -> 0
A22: (d) Long-Term Provision | D22: 0 | E22: 0 | F22: 0 | G22: 0 | H22: =D22+F22 -> 0 | I22: =E22+G22 -> 0
A24: (4) Current Liabilities
A25: (a) Short-Term Borrowings | C25: Note-3 | D25: =Notes!B42 -> 258260000 | E25: =Notes!C42 -> 552110000 | F25: =Notes!D42 -> 4.0433683e+08 | G25: =Notes!E42 -> -15907480 | H25: =Notes!F42 -> 6.6259683e+08 | I25: =Notes!G42 -> 536202520
A26: (b) Trade Payable | C26: Note 4
A27: (i) Total Outstanding Dues of Micro Enterprises and Small Enterprises; and | D27: 0 | E27: 0 | F27: ='Note-4'!F8 -> 16500 | G27: ='Note-4'!F17 -> 543846.53 | H27: ='Note-4'!F8 -> 16500 | I27: ='Note-4'!F17 -> 543846.53
A28: (ii) Total Outstanding Dues of Creditors Other Than Micro Enterprises and Small Enterprises | D28: 0 | E28: 0 | F28: ='Note-4'!F9 -> 3.386677e+08 | G28: ='Note-4'!F18 -> 5.7107583e+08 | H28: ='Note-4'!F9 -> 3.386677e+08 | I28: ='Note-4'!F18 -> 5.7107583e+08
A29: (c) Other Current Liabilities | C29: Note-5 | D29: =+Notes!B61 -> -2.7320444e+08 | E29: =Notes!C61 -> -5.6174239e+08 | F29: =Notes!D61 -> 1.7366311e+09 | G29: =Notes!E61 -> 2287780375 | H29: =Notes!F61 -> 1.4634267e+09 | I29: =Notes!G61 -> 1.726038e+09
A30: (d) Short-Term Provisions | C30: Note-6 | D30: =+Notes!B102 -> 21789349 | E30: =Notes!C102 -> 16919070 | F30: =Notes!D102 -> 44722692 | G30: =Notes!E102 -> 1854156.9 | H30: =Notes!F102 -> 66512041 | I30: =Notes!G102 -> 18773227
G31: 0
B32: Total | D32: =SUM(D12:D30) -> 6814293.4 | E32: =SUM(E12:E30) -> 7256064.1 | F32: =SUM(F12:F30) -> 2.9976385e+09 | G32: =SUM(G12:G30) -> 2.8453633e+09 | H32: =SUM(H12:H30) -> 3.0044528e+09 | I32: =SUM(I12:I30) -> 2.8526194e+09
A34: II. Assets
A36: (1) Non-Current Assets
A37: (a) Property, Plant and Equipment
A38: (i) Property, Plant and Equipment | C38: Note-7 | D38: 0 | E38: 0 | F38: ='Dep & DTA DTL'!M9 -> 17765.345 | G38: ='Dep & DTA DTL'!D9 -> 32341.13 | H38: ='Dep & DTA DTL'!M12 -> 17765.345 | I38: ='Dep & DTA DTL'!D12 -> 32341.13
A39: (ii) Intangible Assets | D39: 0 | E39: 0 | F39: 0 | G39: 0 | H39: =D39+F39 -> 0 | I39: =E39+G39 -> 0
A40: (iii) Capital Work-In-Progress | D40: 0 | E40: 0 | F40: 0 | G40: 0 | H40: =D40+F40 -> 0 | I40: =E40+G40 -> 0
A41: (iv) Intangible Assets Under Development | D41: 0 | E41: 0 | F41: 0 | G41: 0 | H41: =D41+F41 -> 0 | I41: =E41+G41 -> 0
A42: (b) Non- Current Investment | H42: =D42+F42 -> 0 | I42: =E42+G42 -> 0
A43: (c) Deferred Tax Assets (Net) | C43: ='Dep & DTA DTL'!B17 -> Note 8 | D43: 0 | E43: 0 | F43: ='Dep & DTA DTL'!C35+G43 -> 5495.5925 | G43: 3586 | H43: =G43+'Dep & DTA DTL'!C35 -> 5495.5925 | I43: ='Dep & DTA DTL'!C36 -> 3586
A44: (d) Long Term Loans And Advances | H44: =D44+F44 -> 0 | I44: =E44+G44 -> 0
A45: (e) Other Non-Current Assets | H45: =D45+F45 -> 0 | I45: =E45+G45 -> 0
A47: (2) Current Assets
A48: (a) Current Investment | C48: Note-9 | D48: 0 | E48: 0 | F48: =Notes!D111 -> 37338046 | G48: =Notes!E111 -> 1055980 | H48: =Notes!F111 -> 37338046 | I48: =Notes!G111 -> 1055980
A49: (b) Inventories | C49: Note-10 | D49: =Notes!B120 -> 0 | E49: =Notes!C120 -> 0 | F49: =Notes!D120 -> 2.9139761e+09 | G49: =Notes!E120 -> 2.8127656e+09 | H49: =Notes!F120 -> 2.9139761e+09 | I49: =Notes!G120 -> 2.8127656e+09
A50: (c) Trade Receivables | D50: 0 | E50: 0 | F50: 0 | G50: 0 | H50: =D50+F50 -> 0 | I50: =E50+G50 -> 0
A51: (d) Cash And Cash Equivalents | C51: Note-11 | D51: =+Notes!B140 -> 4359293.4 | E51: =Notes!C140 -> 4815080.1 | F51: =Notes!D140 -> 6525891 | G51: =Notes!E140 -> 2075181.9 | H51: =Notes!F140 -> 10885184 | I51: =Notes!G140 -> 6890262
A52: (e) Short Term Loans And Advances | C52: Note-12 | D52: =+Notes!B157 -> 2440000 | E52: =Notes!C157 -> 2440000 | F52: =Notes!D157 -> 218082 | G52: =Notes!E157 -> 41467 | H52: =Notes!F157 -> 2658082 | I52: =Notes!G157 -> 2481467
A53: (f) Other Current Assets | C53: Note-13 | D53: =+Notes!B173 -> 15000 | E53: =Notes!C173 -> 984 | F53: =Notes!D173 -> 39557162 | G53: =Notes!E173 -> 29389097 | H53: =Notes!F173 -> 39572162 | I53: =Notes!G173 -> 29390081
B55: Total | D55: =SUM(D47:D53) -> 6814293.4 | E55: =SUM(E47:E53) -> 7256064.1 | F55: =SUM(F38:F53) -> 2.9976385e+09 | G55: =SUM(G38:G53) -> 2.8453633e+09 | H55: =SUM(H38:H53) -> 3.0044528e+09 | I55: =SUM(I38:I53) -> 2.8526194e+09 | J55: =H55-H32 -> 0.46000004 | K55: =I55-I32 -> -0.050998688
A56: Significant Accounting Policies & Notes on Accounts | D56: =D55-D32 -> 2.2351742e-08 | E56: =E55-E32 -> -3.3527613e-08 | F56: =F55-F32 -> 0.46000004 | G56: =G55-G32 -> -0.050998688
A58: As per our report of even date
A59: Bhandari S A A J & Associates | G59: For & on behalf of the Board of
A60: Chartered Accountants | G60: Moonstone Realinfra Pvt Ltd
A61: FRN :- 108155W
A64: CA. Pravin B. Bhandari | G64: Rajesh K. Goyal | H64: Rajesh K. Goyal | I64: Vineet K. Goyal
A65: Partner | G65: Director | H65: Director | I65: Director
A66: MRN :- 032548 | G66: DIN :- 00516086 | H66: DIN :- 00516086 | I66: DIN :- 02305167
A67: UDIN:-
A68: Date:-
A69: Place :- Pune

Sheet PL
A2: Moonstone Realinfra Private Limited
A3: CIN :- U45201PN2022PTC207521
A4: A 102 ICC TRADE TOWER 403/A SENAPATI BAPAT ROAD PUNE , MH 411016
A5: Statement of Profit & Loss for the year ended 31.03.2026
A6: Particulars | D6: Note No | E6: HO | G6: Construction Division | I6: Total
E7: =I7 -> Figures as at the end of 31.03.2026 | F7: Figures as at the end of 31.03.2025 | G7: =I7 -> Figures as at the end of 31.03.2026 | H7: Figures as at the end of 31.03.2025 | I7: Figures as at the end of 31.03.2026 | J7: Figures as at the end of 31.03.2025
A9: I. Revenue From Operations | D9: =Notes!A175 -> Note-14 | F9: =Notes!C179 -> 0 | G9: =Notes!D182 -> 3.6329722e+08 | H9: =Notes!E182 -> 534581.34 | I9: =Notes!F182 -> 3.6329722e+08 | J9: =Notes!G182 -> 534581.34
A10: II. Other Income | D10: =Notes!A184 -> Note-15 | F10: =Notes!C193 -> 0 | G10: =Notes!D193 -> 2874429.8 | H10: =Notes!E193 -> 98037.001 | I10: =Notes!F193 -> 2874429.8 | J10: =Notes!G193 -> 98037.001
A12: III. Total Revenue (I +II) | G12: =SUM(G9:G10) -> 3.6617165e+08 | H12: =SUM(H9:H10) -> 632618.34 | I12: =SUM(I9:I10) -> 3.6617165e+08 | J12: =SUM(J9:J10) -> 632618.34
A14: IV. Expenses:
A15: (a) Cost of Construction | D15: =Notes!A195 -> Note-16 | F15: =Notes!C240 -> 5834 | G15: =Notes!D240 -> 2.6738234e+08 | H15: =Notes!E240 -> 9.0679174e+08 | I15: =Notes!F240 -> 2.6738234e+08 | J15: =Notes!G240 -> 9.0679758e+08
A16: (b) Purchase of Stock-in-Trade | G16: 0 | H16: 0 | I16: =E16+G16 -> 0 | J16: =F16+H16 -> 0
A17: (c) Changes in Inventories of Finished Goods, work-In Progress and Stock-in-Trade | D17: =Notes!A242 -> Note-17 | F17: =Notes!C254 -> 0 | G17: =Notes!D254 -> -1.0121044e+08 | H17: =Notes!E254 -> -9.2434364e+08 | I17: =Notes!F254 -> -1.0121044e+08 | J17: =Notes!G254 -> -9.2434364e+08
A18: (d) Employee Benefits Expense | F18: =Notes!C255 -> 0 | G18: =Notes!D255 -> 0 | H18: =Notes!E255 -> 0 | I18: =E18+G18 -> 0 | J18: =F18+H18 -> 0
A19: (e) Finance Cost | D19: =Notes!A256 -> Note-18 | F19: =Notes!C264 -> 0 | G19: =Notes!D264 -> 62874802 | H19: =Notes!E264 -> 16021317 | I19: =Notes!F264 -> 62874802 | J19: =Notes!G264 -> 16021317
A20: (f) Depreciation and Amortization Expense | D20: ='Dep & DTA DTL'!B4 -> Note-7 | F20: =Notes!C265 -> 0 | G20: ='Dep & DTA DTL'!L12 -> 14575.785 | H20: 22469.87 | I20: ='Dep & DTA DTL'!L12 -> 14575.785 | J20: =F20+H20 -> 22469.87
A21: (g) Other Expenses | D21: =Notes!A266 -> Note-19 | F21: =Notes!C297 -> 24782.78 | G21: =Notes!D297 -> 16788678 | H21: =Notes!E297 -> 2224845.1 | I21: =Notes!F297 -> 16788678 | J21: =Notes!G297 -> 2249627.9
A23: IV. Total Expenses | F23: =SUM(F15:F21) -> 30616.78 | G23: =SUM(G15:G21) -> 2.4584996e+08 | H23: =SUM(H15:H21) -> 716740 | I23: =SUM(I15:I21) -> 2.4584996e+08 | J23: =SUM(J15:J21) -> 747356.78
A24: V. Profit Before Exceptional and Extraordinary Items And Tax (III - IV)
F25: =F12-F23 -> -30616.78 | G25: =+G12-G23 -> 1.2032169e+08 | H25: =+H12-H23 -> -84121.659 | I25: =+I12-I23 -> 1.2032169e+08 | J25: =+J12-J23 -> -114738.44
A27: VI. Exceptional Items | F27: 0 | G27: 0 | H27: 0 | I27: =E27+G27 -> 0 | J27: =F27+H27 -> 0
A29: VII. Profit Before Extraordinary Items and Tax (V - VI) | F29: =F25-F27 -> -30616.78 | G29: =G25-G27 -> 1.2032169e+08 | H29: =H25-H27 -> -84121.659 | I29: =I25-I27 -> 1.2032169e+08 | J29: =J25-J27 -> -114738.44
A31: VIII. Extraordinary Items | F31: 0 | G31: 0 | H31: 0 | I31: =E31+G31 -> 0 | J31: =F31+H31 -> 0
A33: IX. Profit Before Tax (VII- VIII) | F33: =F29-F31 -> -30616.78 | G33: =G29-G31 -> 1.2032169e+08 | H33: =H29-H31 -> -84121.659 | I33: =I29-I31 -> 1.2032169e+08 | J33: =J29-J31 -> -114738.44
A35: X. Tax Expense:
A36: (1) Current Tax | F36: 0 | I36: =30532486+1876474 -> 32408960 | J36: =F36+H36 -> 0
A37: (2) Deferred Tax | D37: ='Dep & DTA DTL'!B17 -> Note 8 | F37: 0 | G37: =-'Dep & DTA DTL'!C35 -> -1909.5925 | H37: -3586 | I37: =-'Dep & DTA DTL'!C35 -> -1909.5925 | J37: =F37+H37 -> -3586
A38: (3) Taxation For Earlier Years | F38: 0 | H38: 0 | I38: =E38+G38 -> 0 | J38: =F38+H38 -> 0
A40: XI. Profit (Loss) For The Period From Continuing Operations | F40: =F33-F36-F37-F38 -> -30616.78 | G40: =G33-G36-G37-G38 -> 1.203236e+08 | H40: =H33-H36-H37-H38 -> -80535.659 | I40: =I33-I36-I37-I38 -> 87914644 | J40: =J33-J36-J37-J38 -> -111152.44
A42: XII. Profit/(Loss) From Discontinuing Operations | F42: 0 | H42: 0 | I42: =E42+G42 -> 0 | J42: =F42+H42 -> 0
A43: XIII. Tax Expense Of Discontinuing Operations | F43: 0 | H43: 0 | I43: =E43+G43 -> 0 | J43: =F43+H43 -> 0
A45: XIV. Profit/(Loss) From Discontinuing Operations (After Tax) | F45: 0 | H45: =H42-H43 -> 0 | I45: =E45+G45 -> 0 | J45: =F45+H45 -> 0
A47: XV. Profit (Loss) For The Period | F47: =F40+F45 -> -30616.78 | G47: =G40+G45 -> 1.203236e+08 | H47: =H40+H45 -> -80535.659 | I47: =I40+I45 -> 87914644 | J47: =J40+J45 -> -111152.44
A49: XVI. Earning Per Equity Share:
A50: (1) Basic | E50: =E47/10000 -> 0 | F50: =F47/10000 -> -3.061678 | G50: =G47/10000 -> 12032.36 | H50: =H47/10000 -> -8.0535659 | I50: =I47/10000 -> 8791.4644 | J50: =J47/10000 -> -11.115244
A51: (2) Diluted | E51: =E47/10000 -> 0 | F51: =F47/10000 -> -3.061678 | G51: =G47/10000 -> 12032.36 | H51: =H47/10000 -> -8.0535659 | I51: =I47/10000 -> 8791.4644 | J51: =J47/10000 -> -11.115244
A52: Significant Accounting Policies & Notes on Accounts
A54: As per our report of even date
A55: Bhandari S A A J & Associates | I55: For & on behalf of the Board of
A56: Chartered Accountants | I56: Moonstone Realinfra Pvt. Ltd.
A57: FRN :- 108155W
A61: CA Pravin B. Bhandari | I61: Rajesh K. Goyal | J61: Vineet K. Goyal
A62: Partner | I62: Director | J62: Director
A63: MRN :- 032548 | I63: DIN :- 00516086 | J63: DIN :- 02305167
A64: UDIN
A65: Date:
A66: Place :- Pune

Sheet Cashflow
A1: Moonstone Realinfra Pvt Ltd
A2: =[1]Balancesheet!A3 -> CIN :- U45201PN2022PTC207521
A3: CASH FLOW STATEMENT
A4: Sr.No. | B4: Particulars | C4: For the year ended 31.03.2026 | D4: For the year ended 31.03.2025
A5: A | B5: Cash Flow From Operating Activities
B6: Net Profit Before Tax | C6: =PL!I33 -> 1.2032169e+08 | D6: =PL!J33 -> -114738.44
B7: Adjustments For
B8: Depreciation | C8: =PL!I20 -> 14575.785 | D8: =PL!J20 -> 22469.87
B9: Finance Cost | C9: =PL!I19 -> 62874802 | D9: =PL!J19 -> 16021317
B10: Operating Profit Before Working Capital Changes | C10: =SUM(C6:C9) -> 1.8321107e+08 | D10: =SUM(D6:D9) -> 15929048
B12: Adjustments For
B13: (Increase) / Decrease In Trade Receivables | C13: =BS!H50-BS!I50 -> 0 | D13: =BS!I50 -> 0
B14: (Increase) /Decrease In Other Current Assets | C14: =-(BS!H53-BS!I53) -> -10182081 | D14: =-BS!I53 -> -29390081
B15: (Increase) /Decrease In Other Non-Current Assets | C15: =BS!H45-BS!I45 -> 0 | D15: =BS!I45 -> 0
B16: Increase / (Decrease) In Other Long Term Liabilities | C16: =BS!H21-BS!I21 -> 0 | D16: =BS!I21 -> 0
B17: Increase / (Decrease) In Trade Payables | C17: =BS!H27+BS!H28-BS!I27-BS!I28 -> -2.3293548e+08 | D17: 5.1885005e+08
B18: Increase/ (Decrease) In Other Current Liabilities | C18: =BS!H29-BS!I29 -> -2.6261133e+08 | D18: 1.0626831e+09
B19: Increase/ (Decrease) In Long Term Provisions | C19: =BS!H22-BS!I22 -> 0 | D19: =[1]Balancesheet!I21-[1]Balancesheet!J21 -> 0
B20: Increase/ (Decrease) In Short Term Provisions | C20: =BS!H30-BS!I30 -> 47738815 | D20: 767510
B21: (Increase) / Decrease In Inventories | C21: =-(BS!H49-BS!I49) -> -1.0121044e+08 | D21: -9.2434364e+08
B23: Cash Generated From Operations | C23: =C10+SUM(C13:C22) -> -3.7598944e+08 | D23: =D10+SUM(D13:D22) -> 6.4449603e+08
B24: Less: Taxes Paid / (Refund) - Net | C24: =PL!I36+PL!I38 -> 32408960 | D24: =[1]PL!I35 -> 0
B25: Net Cash Inflow / (Outflow) From Operating Activities | C25: =C23-C24 -> -4.083984e+08 | D25: =D23-D24 -> 6.4449603e+08
A27: B | B27: Cash Flow From Investing Activities
B28: (Purchase) / Sale Of Fixed Assets | C28: =SUM(BS!H38:H41)+PL!I20-BS!I38 -> 0 | D28: -54811
B29: (Increase) / Decrease In Short Term Loans & Advances | C29: =-(BS!H52-BS!I52) -> -176615 | D29: -41467
B30: (Increase) / Decrease In Long Term Loans & Advances | C30: =BS!H44-BS!I44 -> 0 | D30: 0
B31: (Increase) / Decrease In Non- Current Investment | C31: =BS!H45-BS!I45 -> 0 | D31: 0
B32: (Increase) / Decrease In Current Investment | C32: =-(BS!H48-BS!I48) -> -36282066 | D32: -1055980
B33: Net Cash Flows From Investing Activities | C33: =SUM(C28:C32) -> -36458681 | D33: =SUM(D28:D32) -> -1152258
A35: C | B35: Cash Flow From Financing Activities
B36: Increase/ (Decrease) In Long-Term Borrowings | C36: =BS!H19-BS!I19 -> 3.853325e+08
B37: Increase/ (Decrease) In Short-Term Borrowings | C37: =(BS!H25-BS!I25) -> 1.2639431e+08 | D37: -649291480
B38: Issue of Shares For Cash | C38: =[1]Balancesheet!F11-[1]Balancesheet!G11 -> 0 | D38: =[1]Balancesheet!G11-[1]Balancesheet!H11 -> 0
B39: Finance Costs Paid | C39: =(C9)*-1 -> -62874802 | D39: =(D9)*-1 -> -16021317
B40: Increase/ (Decrease) In Reserve and Surplus | D40: =([1]Balancesheet!I12-[1]Balancesheet!J12)-[1]PL!I46 -> 0
B41: Net Cash Flows From Financing Activities | C41: =SUM(C36:C40) -> 4.48852e+08 | D41: =SUM(D36:D40) -> -665312797
A43: D | B43: Net Changes In Cash & Cash Equivalents (A+B+C) | C43: =C25+C33+C41 -> 3994922 | D43: =D25+D33+D41 -> -21969021
B44: Cash & Cash Equivalents At The Beginning Of The Year | C44: =BS!I51 -> 6890262 | D44: 28859284
B46: Cash & Cash Equivalents At The End Of The Year | C46: =SUM(C43:C44) -> 10885184 | D46: =SUM(D43:D44) -> 6890262.3
B48: Components Of Cash And Cash Equivalents
B49: Cash on hand
B50: Balances with banks
B51: Total of Cash & Cash Equivalents | C51: =BS!H51 -> 10885184 | D51: =BS!I51 -> 6890262
A54: As per our report of even date
A55: =[1]Balancesheet!A59 -> As per our report of even date | C55: For & on behalf of the Board of
A56: Chartered Accountants | C56: Moonstone Realinfra Pvt Ltd
A57: FRN :- 108155W
A59: CA Pravin B. Bhandari | C59: Rajesh K. Goyal | D59: Vineet K. Goyal
A60: Partner | C60: Director | D60: Director
A61: MRN :- 032548 | C61: =BS!H66 -> DIN :- 00516086 | D61: =BS!I66 -> DIN :- 02305167
A62: UDIN
A64: Date:
A65: Place :- Pune

Sheet Sheet1 (2)

Sheet WIP Final
A1: Moonstone Realinfra Pvt Ltd
A3: Punawale Land
A4: S.No | B4: Area in hectre as per index II | C4: Area in hectre converted to Sq mt as per index II | D4: Land Consideration | E4: Stamp Duty | F4: Commission | G4: Total Cost of Land | H4: Development expenses | I4: Purchased in FY | J4: Land | K4: Project | N4: Stamp Duty & Registration Expenses - on Land Purch
A5: 32/6 | B5: 0.49 | C5: =+B5*10000 -> 4900 | D5: =88673100 -> 88673100 | E5: =5352923.6 -> 5352923.6 | F5: 0 | G5: =+SUM(D5:F5) -> 94026024 | H5: 273000 | I5: 21-22 | J5: =+G5*$C$145 -> 13261266 | K5: =G5*$C$146 -> 80764758 | N5: Out of Pocket Expences
A6: 31/1,31/1/1A.. | B6: =+(0.28+0.6+0.29+0.28) -> 1.45 | C6: =+B6*10000 -> 14500 | D6: =205595682 -> 205595682 | E6: 14424800 | F6: 0 | G6: =+SUM(D6:F6) -> 220020482 | I6: 22-23 | J6: =+G6*$C$145 -> 31031304 | K6: =G6*$C$146 -> 1.8898918e+08 | N6: Conveyance Expenses
A7: 32/1,32/7, 32/3 | B7: =+(1.65+0.895+1) -> 3.545 | C7: =+B7*10000 -> 35450 | D7: =473340000 -> 473340000 | E7: 33170900 | F7: 0 | G7: =+SUM(D7:F7) -> 506510900 | I7: 22-23 | J7: =+G7*$C$145 -> 71437411 | K7: =G7*$C$146 -> 4.3507349e+08 | N7: PF Employer Contribution
A8: 32/3 | B8: 0.895 | C8: =+B8*10000 -> 8950 | D8: =135000000 -> 135000000 | E8: 9480000 | F8: 0 | G8: =+SUM(D8:F8) -> 144480000 | I8: 22-23 | J8: =+G8*$C$145 -> 20377206 | K8: =G8*$C$146 -> 1.2410279e+08 | N8: EDLI Contribution
A9: 34/2/2/2 | B9: 0.8553 | C9: =+B9*10000 -> 8553 | D9: =225000000 -> 225000000 | E9: =15750000+30000 -> 15780000 | F9: 2500000 | G9: =+SUM(D9:F9) -> 243280000 | H9: 3250257.4 | I9: 23-24 | J9: =+G9*$C$145 -> 34311786 | K9: =G9*$C$146 -> 2.0896821e+08 | N9: PF Admin Charges
A10: 34/2/2/3 | B10: =0.8533+0.002 -> 0.8553 | C10: =+B10*10000 -> 8553 | D10: =225000000 -> 225000000 | E10: =15750000+30000 -> 15780000 | F10: 2500000 | G10: =+SUM(D10:F10) -> 243280000 | H10: 3250257 | I10: 23-24 | J10: =+G10*$C$145 -> 34311786 | K10: =G10*$C$146 -> 2.0896821e+08 | N10: Other Deduction related to Personnel Cost
A11: Total area Purchase in Co | B11: =SUM(B5:B10) -> 8.0906 | C11: =SUBTOTAL(9,C5:C10) -> 80906 | D11: =SUBTOTAL(9,D5:D10) -> 1352608782 | E11: =SUBTOTAL(9,E5:E10) -> 93988624 | F11: =SUBTOTAL(9,F5:F10) -> 5000000 | G11: =SUBTOTAL(9,G5:G10) -> 1.4515974e+09 | H11: =SUBTOTAL(9,H5:H10) -> 6773514.4 | J11: =SUBTOTAL(9,J5:J10) -> 2.0473076e+08 | K11: =SUBTOTAL(9,K5:K10) -> 1.2468666e+09 | N11: Employer Contribution at ESIC
N12: Profession Tax (PTEC)
N13: MLWF Employer Contribution
A14: FY 21-22 | N14: Insurance Charges
A15: Expenses | N15: Printing & Stationery
A16: Particulars | B16: Amount | C16: Land | D16: Project | E16: Expense Type | N16: Professional Fees
A17: Land | B17: =+G5 -> 94026024 | C17: =+B17*$C$145 -> 13261266 | D17: =+B17*$C$146 -> 80764758 | E17: Direct cost (Common) | N17: Repair & Maintenance
A18: Development Expenses (Punawale) | B18: 273000 | C18: =+B18*$C$145 -> 38503.442 | D18: =+B18*$C$146 -> 234496.56 | E18: Direct cost (Common) | N18: Round Off Expense
A19: Bank Charges | B19: 29.5 | C19: =+B19*$C$145 -> 4.1606284 | D19: =+B19*$C$146 -> 25.339372 | E19: Direct cost (Common) | N19: Audit Fees
A20: Total | B20: =SUM(B17:B19) -> 94299053 | C20: =SUM(C17:C19) -> 13299773 | D20: =SUM(D17:D19) -> 80999280 | F20: =+B20-C20-D20 -> 0 | N20: Interest on Late Payment of GST
N21: Bank Charges
N22: Registration and Filing Fees
A23: FY 22-23 | N23: Depreciation - Office Equipments
A24: Expenses | N24: Penalty/Fine/Damages
A25: Particulars | B25: Amount | C25: Land | D25: Project | E25: Expense Type | N25: Deffered Tax - P&L
A26: Opening WIP | B26: =+B20 -> 94299053 | C26: =+C20 -> 13299773 | D26: =+D20 -> 80999280 | N26: Interest On Late Payment of TDS
A27: Land | B27: =+SUM(G6:G8) -> 871011382 | C27: =+B27*$C$145 -> 1.2284592e+08 | D27: =+B27*$C$146 -> 7.4816546e+08 | E27: Direct cost (Common) | N27: Salary - Indirect
A28: Development Expenses (Punawale - S.No. 31) | B28: 11075368 | C28: =+B28*$C$145 -> 1562050.5 | D28: =+B28*$C$146 -> 9513317.5 | E28: Direct cost (Common)
A29: Development Expenses (Punawale - S.No. 32) | B29: 27153746 | C29: =+B29*$C$145 -> 3829716.8 | D29: =+B29*$C$146 -> 23324029 | E29: Direct cost (Common)
A30: Development Expenses (Punawale - S.No 32/3) | B30: 16639975 | C30: =+B30*$C$145 -> 2346873 | D30: =+B30*$C$146 -> 14293102 | E30: Direct cost (Common)
A31: Development Expenses (Punawale-S.No. 32/6) | B31: 8030711 | C31: =+B31*$C$145 -> 1132637.4 | D31: =+B31*$C$146 -> 6898073.6 | E31: Direct cost (Common)
A32: Electrical Work (Punawale-S.No.31) | B32: 2696074 | C32: =+B32*$C$145 -> 380249.56 | D32: =+B32*$C$146 -> 2315824.4 | E32: Direct cost (Common)
A33: Electrical Work (Punawale - S.No. 32) | B33: 6610029 | C33: =+B33*$C$145 -> 932266.92 | D33: =+B33*$C$146 -> 5677762.1 | E33: Direct cost (Common)
A34: Electrical Work (Punawale-S.No. 32/3) | B34: 1664128 | C34: =+B34*$C$145 -> 234705.7 | D34: =+B34*$C$146 -> 1429422.3 | E34: Direct cost (Common)
A35: Electrical Work (Punawale-S.No. 32/6) | B35: 911086 | C35: =+B35*$C$145 -> 128497.98 | D35: =+B35*$C$146 -> 782588.02 | E35: Direct cost (Common)
A36: Fencing Work Expenses (Punawale-S.No. 31) | B36: 772100 | C36: =+B36*$C$145 -> 108895.63 | D36: =+B36*$C$146 -> 663204.37 | E36: Direct cost (Common)
A37: Fencing Work Expenses (Punawale-S.No. 32) | B37: 772100 | C37: =+B37*$C$145 -> 108895.63 | D37: =+B37*$C$146 -> 663204.37 | E37: Direct cost (Common)
A38: Liasoning Expenses (Punawale - S.No. 31) | B38: 4737500 | C38: =+B38*$C$145 -> 668168.71 | D38: =+B38*$C$146 -> 4069331.3 | E38: Direct cost (Common)
A39: Liasoning Expenses (Punawale - S.No. 32) | B39: 16800 | C39: =+B39*$C$145 -> 2369.4426 | D39: =+B39*$C$146 -> 14430.557 | E39: Direct cost (Common)
... A47: Professional Expenses (Punawale -S.No. 32/6) | B47: 14992 | C47: =+B47*$C$145 -> 2114.4454 | D47: =+B47*$C$146 -> 12877.555 | E47: Direct cost (Common)
A48: Total | B48: =SUM(B26:B47) -> 1.0469266e+09 | C48: =SUM(C26:C47) -> 1.476567e+08 | D48: =SUM(D26:D47) -> 8.9926994e+08 | F48: =+B48-C48-D48 -> 0
A50: FY 23-24
A51: Expenses
A52: Particulars | B52: Amount | C52: Land | D52: Project | E52: Expense Type
A53: Opening WIP | B53: =+B48 -> 1.0469266e+09 | C53: =+C48 -> 1.476567e+08 | D53: =+D48 -> 8.9926994e+08
A54: Land | B54: =+SUM(G9:G10) -> 486560000 | C54: =+B54*$C$145 -> 68623571 | D54: =+B54*$C$146 -> 4.1793643e+08 | E54: Direct cost (Common)
A55: TDR at Chikhali (S.No 41 Part | B55: =8800000+206700+88005 -> 9094705 | D55: =+B55 -> 9094705 | E55: Direct Cost (Project)
A56: TDR at Chikhali (S.No. 93 Part | B56: =8000000+270600 -> 8270600 | D56: =+B56 -> 8270600 | E56: Direct Cost (Project)
A57: TDR at Ravet (S.No. 75/1A/1A/1A/1 Part | B57: =4800000+174600 -> 4974600 | D57: =+B57 -> 4974600 | E57: Direct Cost (Project)
A58: TDR at Tathwade (S.No. 91/2 Part | B58: 7381500 | D58: =+B58 -> 7381500 | E58: Direct Cost (Project)
A59: TDR at Thergaon (S.No 37/6P | B59: =4000000+252100+150600+600 -> 4403300 | D59: =+B59 -> 4403300 | E59: Direct Cost (Project)
A60: TDR at Wakad (12/1 Part | B60: =28500000+885600 -> 29385600 | D60: =+B60 -> 29385600 | E60: Direct Cost (Project)
A61: TDR Purchase | B61: =82848400+2517100 -> 85365500 | D61: =+B61 -> 85365500 | E61: Direct Cost (Project)
A62: Building Permission Development Charges | B62: 100477300 | D62: =+B62 -> 100477300 | E62: Direct Cost (Project)
A63: CONSULTANCY & ARCHITECH EXPENSE | B63: 2973000 | D63: =+B63 -> 2973000 | E63: Direct Cost (Project)
A64: Development Expenses | B64: 40413100 | D64: =+B64 -> 40413100 | E64: Direct Cost (Project)
A65: Electrical Expenses | B65: 10000 | D65: =+B65 -> 10000 | E65: Direct Cost (Project)
A66: LABOUR CHARGES -CONSULTANT | B66: 1394080 | D66: =+B66 -> 1394080 | E66: Direct Cost (Project)
A67: LABOUR CHARGES -Development | B67: 23683672 | D67: =+B67 -> 23683672 | E67: Direct Cost (Project)
A68: MIning Application | B68: 5020 | D68: =+B68 -> 5020 | E68: Direct Cost (Project)
A69: RERA Expenses | B69: 320860.9 | D69: =+B69 -> 320860.9 | E69: Direct Cost (Project)
A70: Royalty Paid | B70: 3403100 | D70: =+B70 -> 3403100 | E70: Direct Cost (Project)
A71: TCS on Royalty | B71: 60000 | D71: =+B71 -> 60000 | E71: Direct Cost (Project)
A72: SECURITY CHARGES | B72: 138000 | D72: =+B72 -> 138000 | E72: Direct Cost (Project)
A73: CGST (Direct Expenses) | B73: 2672203 | D73: =+B73 -> 2672203 | E73: Direct Cost (Project)
... A76: SAMPLE FLAT EXPENSES | B76: 4173392 | D76: =+B76 -> 4173392 | E76: Indirect Cost (Project)
A77: BROKERAGE & COMMISSION | B77: =6062000-F9-F10 -> 1062000 | D77: =+B77 -> 1062000 | E77: Indirect Cost (Project)
A78: COLLATERALS | B78: 61250 | D78: =+B78 -> 61250 | E78: Indirect Cost (Project)
A79: EVENT AND ACTIVATION | B79: 687855 | D79: =+B79 -> 687855 | E79: Indirect Cost (Project)
A80: OTHER MARKETING EXPENSE | B80: 316248 | D80: =+B80 -> 316248 | E80: Indirect Cost (Project)
A81: OUTDOOR | B81: 6782775 | D81: =+B81 -> 6782775 | E81: Indirect Cost (Project)
A82: CGST (Indirect Expenses) | B82: 2396201 | D82: =+B82 -> 2396201 | E82: Indirect Cost (Project)
A83: SGST (Indirect Expenses) | B83: 2396201 | D83: =+B83 -> 2396201 | E83: Indirect Cost (Project)
A84: Advertisement Expenses | B84: 28800 | D84: =+B84 -> 28800 | E84: Indirect Cost (Project)
A85: Audit Fees | B85: 50000 | C85: =+B85*$C$145 -> 7051.9125 | D85: =+B85*$C$146 -> 42948.087 | E85: Indirect cost (Common)
A86: Bank Charges | B86: 363094.96 | C86: =+B86*$C$145 -> 51210.278 | D86: =+B86*$C$146 -> 311884.68 | E86: Indirect cost (Common)
A87: Interest on GST | B87: 3996 | C87: =+B87*$C$145 -> 563.58885 | D87: =+B87*$C$146 -> 3432.4112 | E87: Indirect cost (Common)
A88: Interest paid on Loan | B88: 7391079 | C88: =+B88*$C$145 -> 1042424.8 | D88: =+B88*$C$146 -> 6348654.2 | E88: Indirect cost (Common)
A89: LEGAL & PROFESSIONAL FEES | B89: 1871000 | C89: =+B89*$C$145 -> 263882.57 | D89: =+B89*$C$146 -> 1607117.4 | E89: Indirect cost (Common)
A90: PRINT | B90: 20000 | C90: =+B90*$C$145 -> 2820.765 | D90: =+B90*$C$146 -> 17179.235 | E90: Indirect cost (Common)
A91: Professional Fees | B91: 162000 | C91: =+B91*$C$145 -> 22848.197 | D91: =+B91*$C$146 -> 139151.8 | E91: Indirect cost (Common)
A92: ROC Filing Expenses | B92: 1304 | C92: =+B92*$C$145 -> 183.91388 | D92: =+B92*$C$146 -> 1120.0861 | E92: Indirect cost (Common)
A93: ROUND OFF EXPENSE | B93: -167.98 | C93: =+B93*$C$145 -> -23.691605 | D93: =+B93*$C$146 -> -144.28839 | E93: Indirect cost (Common)
A94: Tax Audit Fees | B94: 50000 | C94: =+B94*$C$145 -> 7051.9125 | D94: =+B94*$C$146 -> 42948.087 | E94: Indirect cost (Common)
A95: Total | B95: =SUBTOTAL(9,B53:B94) -> 1.888422e+09 | C95: =SUBTOTAL(9,C53:C94) -> 2.1767829e+08 | D95: =SUBTOTAL(9,D53:D94) -> 1.6707437e+09 | F95: =+B95-C95-D95 -> 0
A97: FY 24-25
A98: Expenses
A99: Particulars | B99: Amount | C99: Land | D99: Project | E99: Expense Type
A100: Opening WIP | B100: =+B95 -> 1.888422e+09 | C100: =+C95 -> 2.1767829e+08 | D100: =+D95 -> 1.6707437e+09
A101: TDR Purchase (F.Y 24-25) | B101: 32026700 | D101: =+B101 -> 32026700 | E101: Direct Cost (Project)
A102: Subcon-Engg&Civil Wo | B102: 4.0013855e+08 | D102: =+B102 -> 4.0013855e+08 | E102: Direct Cost (Project)
A103: Subcon-Electric Work | B103: 30032191 | D103: =+B103 -> 30032191 | E103: Direct Cost (Project)
A104: Consultancy &archi | B104: 11628000 | D104: =+B104 -> 11628000 | E104: Direct Cost (Project)
A105: Cons-Civil Material | B105: 60441166 | D105: =+B105 -> 60441166 | E105: Direct Cost (Project)
A106: Site housekeep | B106: 2326406.1 | D106: =+B106 -> 2326406.1 | E106: Direct Cost (Project)
A107: Site security | B107: 2086848 | D107: =+B107 -> 2086848 | E107: Direct Cost (Project)
A108: Site fuel | B108: 2930492 | D108: =+B108 -> 2930492 | E108: Direct Cost (Project)
A109: Property Tax | B109: 1479902 | D109: =+B109 -> 1479902 | E109: Direct Cost (Project)
A110: Develp expen | B110: 938100 | D110: =+B110 -> 938100 | E110: Direct Cost (Project)
A111: Subcon-Plumbing Work | B111: 46641.05 | D111: =+B111 -> 46641.05 | E111: Direct Cost (Project)
A112: CGWA NOC | B112: 43215 | D112: =+B112 -> 43215 | E112: Direct Cost (Project)
...

Sheet Notes
A1: Note-1B
A2: Reserves and Surplus
A3: Particulars | B3: HO | D3: Construction Division | F3: Total
B4: =F4 -> Figures as at the end of 31.03.2026 | C4: Figures as at the end of 31.03.2025 | D4: =F4 -> Figures as at the end of 31.03.2026 | E4: Figures as at the end of 31.03.2025 | F4: Figures as at the end of 31.03.2026 | G4: Figures as at the end of 31.03.2025
A6: Profit and Loss A/c
A7: Opening Balance | B7: =+C10 -> -30616.78 | C7: 0 | D7: =-'TB_31.03.2026 (Links)'!E67-'TB_31.03.2026 (Links)'!E66+30617 -> -83426.27 | E7: =-'TB_31.03.2026 (Links)'!H67 -> -2890.55 | F7: =B7+D7 -> -114043.05 | G7: =C7+E7 -> -2890.55
A8: Add :- Surplus / (Deficit) in Statement of Profit and Loss | B8: 0 | C8: =PL!F47 -> -30616.78 | D8: =PL!I40 -> 87914644 | E8: =PL!H47 -> -80535.659 | F8: =B8+D8 -> 87914644 | G8: =C8+E8 -> -111152.44
A10: Grand Total | B10: =SUM(B7:B8) -> -30616.78 | C10: =SUM(C7:C8) -> -30616.78 | D10: =SUM(D7:D8) -> 87831217 | E10: =SUM(E7:E8) -> -83426.209 | F10: =SUM(F7:F8) -> 87800601 | G10: =SUM(G7:G8) -> -114042.99
A12: Note-2
A13: Long-Term Borrowings
A14: Particulars | B14: HO | D14: Construction Division | F14: Total
B15: =B25 -> Figures as at the end of 31.03.2026 | C15: =C25 -> Figures as at the end of 31.03.2025 | D15: =D25 -> Figures as at the end of 31.03.2026 | E15: =E25 -> Figures as at the end of 31.03.2025 | F15: =F25 -> Figures as at the end of 31.03.2026 | G15: =G25 -> Figures as at the end of 31.03.2025
A17: ='TB_31.03.2026 (Links)'!D72 -> Aditya Birla Capital Loan- 935318 | B17: 0 | C17: 0 | D17: =-'TB_31.03.2026 (Links)'!H72-'TB_31.03.2026 (Links)'!M193 -> 3.853325e+08 | E17: 0 | F17: =B17+D17 -> 3.853325e+08 | G17: =C17+E17 -> 0
A18: (Secured against Unsold Units and Land of sapphire 3 project ,developers share )
A19: Grand Total | B19: =SUM(B16:B18) -> 0 | C19: =SUM(C16:C18) -> 0 | D19: =SUM(D16:D18) -> 3.853325e+08 | E19: =SUM(E16:E18) -> 0 | F19: =SUM(F16:F18) -> 3.853325e+08 | G19: =SUM(G16:G18) -> 0
A22: Note-3
A23: Short Term Borrowings
A24: Particulars | B24: HO | D24: Construction Division | F24: Total
B25: =B4 -> Figures as at the end of 31.03.2026 | C25: =C4 -> Figures as at the end of 31.03.2025 | D25: =D4 -> Figures as at the end of 31.03.2026 | E25: =E4 -> Figures as at the end of 31.03.2025 | F25: =F4 -> Figures as at the end of 31.03.2026 | G25: =G4 -> Figures as at the end of 31.03.2025
A27: Bank Overdraft
A28: HDFC-99919917012022-Expenses A/c | B28: 0 | C28: 0 | D28: =-SUM('TB_31.03.2026 (Links)'!H33:H35) -> 27962349 | E28: 0 | F28: =B28+D28 -> 27962349 | G28: =C28+E28 -> 0
A29: (Secured Against Fixed Deposit)
A31: Loans and Advances From Related Parties
A33: Loan from Directors & Relatives (Unsecured & considered good)
A34: Rajesh Goyal | B34: -15550000 | C34: 84450000 | D34: =-'TB_31.03.2026 (Links)'!H70+0.16 -> 2.0563452e+08 | E34: =-'TB_31.03.2026 (Links)'!E70 -> 172634520 | F34: =B34+D34 -> 1.9008452e+08 | G34: =C34+E34 -> 257084520
A35: Vineet Goyal | B35: 152050000 | C35: 327900000 | D35: =-'TB_31.03.2026 (Links)'!H71 -> 49381956 | E35: =-'TB_31.03.2026 (Links)'!E71 -> -218300000 | F35: =B35+D35 -> 201431956 | G35: =C35+E35 -> 109600000
A36: Krishnakumar Goyal | B36: 0 | C36: 55150000 | D36: =-'TB_31.03.2026 (Links)'!H69 -> 121358000 | E36: =-'TB_31.03.2026 (Links)'!E69 -> 29758000 | F36: =B36+D36 -> 121358000 | G36: =C36+E36 -> 84908000
A37: Rehaan Vineet Goyal | B37: 15400000 | C37: 15400000 | D37: 0 | E37: 0 | F37: =B37+D37 -> 15400000 | G37: =C37+E37 -> 15400000
A38: Saesha Goyal | B38: 17000000 | C38: 0 | D38: 0 | E38: 0 | F38: =B38+D38 -> 17000000 | G38: =C38+E38 -> 0
A39: Sheetal Manoj Gupta | B39: 44350000 | C39: 38900000 | D39: 0 | E39: 0 | F39: =B39+D39 -> 44350000 | G39: =C39+E39 -> 38900000
A40: Shilpa Sachin Garg | B40: 45010000 | C40: 30310000 | D40: 0 | E40: 0 | F40: =B40+D40 -> 45010000 | G40: =C40+E40 -> 30310000
A42: Grand Total | B42: =SUM(B26:B41) -> 258260000 | C42: =SUM(C26:C41) -> 552110000 | D42: =SUM(D26:D41) -> 4.0433683e+08 | E42: =SUM(E26:E41) -> -15907480 | F42: =SUM(F26:F41) -> 6.6259683e+08 | G42: =SUM(G26:G41) -> 536202520
A45: Note-5
A46: Other Current Liabilities
A47: Particulars | B47: HO | D47: Construction Division | F47: Total
B48: =B4 -> Figures as at the end of 31.03.2026 | C48: =C4 -> Figures as at the end of 31.03.2025 | D48: =D4 -> Figures as at the end of 31.03.2026 | E48: =E4 -> Figures as at the end of 31.03.2025 | F48: =F4 -> Figures as at the end of 31.03.2026 | G48: =G4 -> Figures as at the end of 31.03.2025
L49: =30532486+1876474-293010 -> 32115950 | N49: =30532486+1876474 -> 32408960
A50: Contractual Deposit Received From Customer | B50: 0 | C50: 0 | D50: =-Customer!I17+-'TB_31.03.2026 (Links)'!H111 -> 1.3634267e+09 | E50: =-Customer!F17+-Customer!F18 -> 1.369242e+09 | F50: =B50+D50 -> 1.3634267e+09 | G50: =C50+E50 -> 1.369242e+09
A52: Branch/Division
A53: Interbranch Transaction | B53: -3.7320444e+08 | C53: =-911972112.13-6566277 -> -9.1853839e+08 | D53: =-'TB_31.03.2026 (Links)'!H59 -> 3.6663816e+08 | E53: =-'TB_31.03.2026 (Links)'!E59 -> 9.1197211e+08 | F53: =B53+D53 -> -6566277 | G53: =C53+E53 -> -6566277
A54: ='TB_31.03.2026 (Links)'!D64 -> Branch Ho-Liablities | D54: 6566277 | E54: 6566277 | F54: =B54+D54 -> 6566277 | G54: =C54+E54 -> 6566277
A55: ='TB_31.03.2026 (Links)'!D60 -> Branch-Ho-Assets | F55: =B55+D55 -> 0
A57: Advance Received Against Land
A58: Punawale | B58: 0 | C58: 356796000 | E58: 0 | F58: =B58+D58 -> 0 | G58: =C58+E58 -> 356796000
A59: Livience lifespaces Private Limited | B59: 100000000 | C59: 0 | D59: 0 | E59: 0 | F59: =B59+D59 -> 100000000 | G59: =C59+E59 -> 0
A61: Grand Total | B61: =SUM(B49:B60) -> -2.7320444e+08 | C61: =SUM(C49:C60) -> -5.6174239e+08 | D61: =SUM(D49:D60) -> 1.7366311e+09 | E61: =SUM(E49:E60) -> 2287780375 | F61: =SUM(F49:F60) -> 1.4634267e+09 | G61: =SUM(G49:G60) -> 1.726038e+09
A63: Note-6
A64: Short Term Provision
A65: Particulars | B65: HO | D65: Construction Division | F65: Total
B66: =B4 -> Figures as at the end of 31.03.2026 | C66: =C4 -> Figures as at the end of 31.03.2025 | D66: =D4 -> Figures as at the end of 31.03.2026 | E66: =E4 -> Figures as at the end of 31.03.2025 | F66: =F4 -> Figures as at the end of 31.03.2026 | G66: =G4 -> Figures as at the end of 31.03.2025
A68: Expense Payable
A69: Interest Payable | B69: 20549943 | C69: 9406089 | D69: ='TB_31.03.2026 (Links)'!M193 -> 1551002 | E69: 0 | F69: =B69+D69 -> 22100945 | G69: =C69+E69 -> 9406089 | H69: Others | J69: =F69+F71+F72+SUM(F79:F94) -> 28390022 | K69: Other
A70: ='TB_31.03.2026 (Links)'!D178 -> PTEC Payable | B70: 0 | C70: 0 | D70: =-'TB_31.03.2026 (Links)'!H178 -> 2500 | E70: 0 | F70: =B70+D70 -> 2500 | G70: =C70+E70 -> 0 | H70: Provision for employee benefit | J70: =F70+F73+SUM(F95:F100) -> 6006069 | K70: Provision for employee benefit
A71: Audit Fees Payable | B71: 0 | C71: 0 | D71: =-'TB_31.03.2026 (Links)'!H98 -> 180000 | E71: 180000 | F71: =B71+D71 -> 180000 | G71: =C71+E71 -> 180000 | H71: Others | J71: =F74 -> 32115950 | K71: Provision for Income-tax
A72: Interest Payable to Rajesh Goyal | B72: 0 | C72: 5909649 | E72: 0 | F72: =B72+D72 -> 0 | G72: =C72+E72 -> 5909649 | H72: Others | J72: =SUM(J69:J71) -> 66512041
A73: ='TB_31.03.2026 (Links)'!D93 -> Salary Payable | D73: =-'TB_31.03.2026 (Links)'!H93 -> 5674973 | E73: 0 | F73: =B73+D73 -> 5674973 | G73: =C73+E73 -> 0 | H73: Provision for employee benefit
A74: Income Tax Payable | D74: =PL!I36-293010 -> 32115950 | E74: 0 | F74: =B74+D74 -> 32115950 | G74: =C74+E74 -> 0 | H74: Provision for Income-tax
A76: Duties and Taxes
A78: GST Payable
A79: CGST Customer Payable | B79: 0 | C79: 0 | D79: =-'TB_31.03.2026 (Links)'!H74 -> 0 | E79: 1214 | F79: =B79+D79 -> 0 | G79: =C79+E79 -> 1214
A80: SGST Customer Payable | B80: 0 | C80: 0 | D80: =-'TB_31.03.2026 (Links)'!H75 -> 0 | E80: 1214 | F80: =B80+D80 -> 0 | G80: =C80+E80 -> 1214
A81: Output CGST 2.5% Payable | B81: 0 | C81: 0 | D81: =-'TB_31.03.2026 (Links)'!H77 -> 0 | E81: 262826.35 | F81: =B81+D81 -> 0 | G81: =C81+E81 -> 262826.35
A82: Output SGST 2.5% Payable | B82: 0 | C82: 0 | D82: =-'TB_31.03.2026 (Links)'!H78 -> 0 | E82: 234180.38 | F82: =B82+D82 -> 0 | G82: =C82+E82 -> 234180.38
A83: Output CGST 9% Payable | B83: 0 | C83: 0 | D83: 0 | E83: 48112.32 | F83: =B83+D83 -> 0 | G83: =C83+E83 -> 48112.32
A84: Output SGST 9% Payable | B84: 0 | C84: 0 | D84: 0 | E84: 48112.32 | F84: =B84+D84 -> 0 | G84: =C84+E84 -> 48112.32
A85: CGST RCM Payable | B85: 0 | C85: 0 | D85: =-'TB_31.03.2026 (Links)'!H81 -> 8992.78 | E85: 43663.32 | F85: =B85+D85 -> 8992.78 | G85: =C85+E85 -> 43663.32 | H85: Others
A86: SGST RCM Payable | B86: 0 | C86: 0 | D86: =-'TB_31.03.2026 (Links)'!H82 -> 8992.78 | E86: 43663.32 | F86: =B86+D86 -> 8992.78 | G86: =C86+E86 -> 43663.32 | H86: Others
A88: TDS Payable
A89: TDS Payable on Purchase (194Q) | B89: 0 | C89: 0 | D89: 0 | E89: 60276.89 | F89: =B89+D89 -> 0 | G89: =C89+E89 -> 60276.89 | H89: Others
A90: TDS Payable on Brokerage (194H) | B90: 0 | C90: 0 | D90: =-'TB_31.03.2026 (Links)'!H84 -> 25247 | E90: -20886 | F90: =B90+D90 -> 25247 | G90: =C90+E90 -> -20886 | H90: Others
A91: TDS Payable on Interest (194A) | B91: 1238206 | C91: =1602132 -> 1602132 | D91: =-'TB_31.03.2026 (Links)'!H177 -> 4407857.9 | E91: 0 | F91: =B91+D91 -> 5646063.9 | G91: =C91+E91 -> 1602132 | H91: Others
A92: TDS Payable on Professional Fees (194J) | B92: 0 | C92: 0 | D92: =-'TB_31.03.2026 (Links)'!H86 -> 56177 | E92: 106899 | F92: =B92+D92 -> 56177 | G92: =C92+E92 -> 106899 | H92: Others
A93: TDS Payable on Contractor (194C) | B93: 1200 | C93: 1200 | D93: =-'TB_31.03.2026 (Links)'!H87 -> 9480 | E93: 844881 | F93: =B93+D93 -> 10680 | G93: =C93+E93 -> 846081 | H93: Others
A94: ='TB_31.03.2026 (Links)'!D88 -> TDS on Salary | B94: 0 | C94: 0 | D94: =-'TB_31.03.2026 (Links)'!H88 -> 352924 | E94: 0 | F94: =B94+D94 -> 352924 | G94: =C94+E94 -> 0 | H94: Others
A95: ='TB_31.03.2026 (Links)'!D89 -> EDLI Contribution Payable | B95: 0 | C95: 0 | D95: =-'TB_31.03.2026 (Links)'!H89 -> 6337 | E95: 0 | F95: =B95+D95 -> 6337 | G95: =C95+E95 -> 0 | H95: Provision for employee benefit
A96: ='TB_31.03.2026 (Links)'!D91 -> PF Admin Charges Payable | B96: 0 | C96: 0 | D96: =-'TB_31.03.2026 (Links)'!H91 -> 6337 | E96: 0 | F96: =B96+D96 -> 6337 | G96: =C96+E96 -> 0 | H96: Provision for employee benefit
A97: ='TB_31.03.2026 (Links)'!D92 -> PF Employer Contribution Payable | B97: 0 | C97: 0 | D97: =-'TB_31.03.2026 (Links)'!H92 -> 152086 | E97: 0 | F97: =B97+D97 -> 152086 | G97: =C97+E97 -> 0 | H97: Provision for employee benefit
A98: ='TB_31.03.2026 (Links)'!D94 -> P.F. Employee Contribution Payable | B98: 0 | C98: 0 | D98: =-'TB_31.03.2026 (Links)'!H94 -> 152086 | E98: 0 | F98: =B98+D98 -> 152086 | G98: =C98+E98 -> 0 | H98: Provision for employee benefit
A99: ='TB_31.03.2026 (Links)'!D95 -> Profession Tax Payable | B99: 0 | C99: 0 | D99: =-'TB_31.03.2026 (Links)'!H95 -> 4250 | E99: 0 | F99: =B99+D99 -> 4250 | G99: =C99+E99 -> 0 | H99: Provision for employee benefit
A100: Professional Fees Payable | B100: 0 | C100: 0 | D100: =-'TB_31.03.2026 (Links)'!H99 -> 7500 | E100: 0 | F100: =B100+D100 -> 7500 | G100: =C100+E100 -> 0 | H100: Provision for employee benefit
A102: Grand Total | B102: =SUM(B69:B101) -> 21789349 | C102: =SUM(C69:C101) -> 16919070 | D102: =SUM(D69:D101) -> 44722692 | E102: =SUM(E69:E101) -> 1854156.9 | F102: =SUM(F69:F101) -> 66512041 | G102: =SUM(G69:G101) -> 18773227
A104: Note-9
A105: Current Investment
A106: Particulars | B106: HO | D106: Construction Division | F106: Total
B107: =B4 -> Figures as at the end of 31.03.2026 | C107: =C4 -> Figures as at the end of 31.03.2025 | D107: =D4 -> Figures as at the end of 31.03.2026 | E107: =E4 -> Figures as at the end of 31.03.2025 | F107: =F4 -> Figures as at the end of 31.03.2026 | G107: =G4 -> Figures as at the end of 31.03.2025
A108: Investment in Fixed Deposit | B108: 0 | C108: 0 | D108: ='TB_31.03.2026 (Links)'!H7 -> 35000000 | E108: 1000000 | F108: =B108+D108 -> 35000000 | G108: =C108+E108 -> 1000000
A109: Interest on Fixed Deposit Accrued but Not Due | B109: 0 | C109: 0 | D109: ='TB_31.03.2026 (Links)'!H47 -> 2338046.2 | E109: 55980 | F109: =B109+D109 -> 2338046.2 | G109: =C109+E109 -> 55980
A111: Grand Total | C111: =SUM(C108:C110) -> 0 | D111: =SUM(D108:D110) -> 37338046 | E111: =SUM(E108:E110) -> 1055980 | F111: =SUM(F108:F110) -> 37338046 | G111: =SUM(G108:G110) -> 1055980
A113: Note-10
A114: Inventories
A115: Particulars | B115: HO | D115: Construction Division | F115: Total
B116: =B4 -> Figures as at the end of 31.03.2026 | C116: =C4 -> Figures as at the end of 31.03.2025 | D116: =D4 -> Figures as at the end of 31.03.2026 | E116: =E4 -> Figures as at the end of 31.03.2025 | F116: =F4 -> Figures as at the end of 31.03.2026 | G116: =G4 -> Figures as at the end of 31.03.2025
A117: Inventories at the end of the year:
A118: Work in Progress | B118: 0 | C118: 0 | D118: ='WIP Final'!B197 -> 2.9139761e+09 | E118: =2812765648.83-C118 -> 2.8127656e+09 | F118: =B118+D118 -> 2.9139761e+09 | G118: =C118+E118 -> 2.8127656e+09
A120: Grand Total | C120: =SUM(C117:C119) -> 0 | D120: =SUM(D117:D119) -> 2.9139761e+09 | E120: =SUM(E117:E119) -> 2.8127656e+09 | F120: =SUM(F117:F119) -> 2.9139761e+09 | G120: =SUM(G117:G119) -> 2.8127656e+09
A122: Note-11
A123: Cash and cash Equivalents
A124: Particulars | B124: HO | D124: Construction Division | F124: Total
B125: =B4 -> Figures as at the end of 31.03.2026 | C125: =C4 -> Figures as at the end of 31.03.2025 | D125: =D4 -> Figures as at the end of 31.03.2026 | E125: =E4 -> Figures as at the end of 31.03.2025 | F125: =F4 -> Figures as at the end of 31.03.2026 | G125: =G4 -> Figures as at the end of 31.03.2025
A126: Cash on hand | B126: 0 | C126: 0 | D126: ='TB_31.03.2026 (Links)'!H18 -> 8105 | E126: 8605 | F126: =B126+D126 -> 8105 | G126: =C126+E126 -> 8605
...

Sheet ESC
A1: Moonstone Realinfra Private Limited
A2: CIN :- U45201PN2022PTC207521
A3: A 102 ICC TRADE TOWER 403/A SENAPATI BAPAT ROAD PUNE , MH 411016
A4: NOTES ANNEXED TO AND FORMING PART OF THE BALANCE SHEET AS ON 31ST March 2026
A6: Note 1A
A7: Share Capital
A8: Particulars | B8: Figures as at the end of current reporting Period 31-03-2026 | D8: Figures as at the end of current reporting Period 31-03-2025
B9: Number of shares | C9: Amount | D9: Number of shares | E9: Amount
A10: (a) Authorised
A11: 50,000 Equity shares of Rs.10/- each with voting rights | B11: 50000 | C11: =+B11*10 -> 500000 | D11: 50000 | E11: =+D11*10 -> 500000
A13: (b) Issued, Subscribed and Paid up
A14: At the Beginning of the year
A15: 10,000 Equity shares of Rs.10/- each with voting rights | B15: 10000 | C15: =+B15*10 -> 100000 | D15: 10000 | E15: =+D15*10 -> 100000
A16: Issued During the Year | B16: 0 | C16: 0 | D16: 0 | E16: 0
A17: Shares bought back during the year | B17: 0 | C17: 0 | D17: 0 | E17: 0
A18: At the End of the Year 10,000 Equity Shares of Rs.10 Each with voting Rights | B18: =SUM(B15:B16) -> 10000 | C18: =-'TB_31.03.2026 (Links)'!H65 -> 100000 | D18: =SUM(D15:D16) -> 10000 | E18: =SUM(E15:E16) -> 100000
A21: Shares in the company held by its holding company or its ultimate holding company including shares held by or by subsidiaries or associates of the holding company or the ultimate holding company
A22: Particulars | B22: Figures as at the end of current reporting Period 31-03-2026 | D22: Figures as at the end of current reporting Period 31-03-2025
B23: Number of shares | C23: Amount | D23: Number of shares | E23: Amount
A25: Shares held by Holding Company
A26: Intofinity Promotors Private Limited | B26: 9800 | C26: =+B26*10 -> 98000 | D26: 9800 | E26: =+D26*10 -> 98000
A29: List of Shareholders holding more than 5% share capital
A30: Particulars | B30: Figures as at the end of current reporting Period 31-03-2026 | D30: Figures as at the end of current reporting Period 31-03-2025
B31: Number of shares | C31: % of total shares | D31: Number of shares | E31: % of total shares
A33: Intofinity Promotors Private Limited | B33: 9800 | C33: 98 | D33: 9800 | E33: 98
A34: Total | B34: =SUM(B33:B33) -> 9800 | C34: =SUM(C33:C33) -> 98 | D34: =SUM(D33:D33) -> 9800 | E34: =SUM(E33:E33) -> 98
A36: NOTE 1A. Shares held by Promoter's
A37: For Current Reporting Period
A38: Promotor's Name | B38: No of shares | C38: % of total shares | D38: % Change during the year
A39: Intofinity Promotors Private Limited | B39: 9800 | C39: 98 | D39: 0
A41: Total | B41: =SUM(B39) -> 9800 | C41: =SUM(C39) -> 98
A43: For Previous reporting Period
A44: Promotor's Name | B44: No of shares | C44: % of total shares | D44: % Change during the year
A45: Intofinity Promotors Private Limited | B45: 9800 | C45: 98 | D45: 0
A47: Total | B47: =SUM(B45:B46) -> 9800 | C47: =SUM(C45:C46) -> 98
A49: In terms of our report attached.
A50: For Bhandari S A A J & Associates | C50: For, Kothari Cars Private Limited
A51: Chartered Accountants
A52: FRN : 108155W
A55: CA. Pravin B. Bhandari | C55: Rajendra B. Kothari | E55: Ashish R. Kothari | G55: Ashish R. Kothari
A56: (Partner) | C56: =#REF! -> #REF! | E56: Director | G56: Director
A57: M No. : 032548 | C57: DIN : 00477141 | E57: DIN : 01923933 | G57: DIN : 01923933
A58: Place : Pune
A59: Date : 30-08-2022

Sheet Note-4
A2: Note 4 | J2: Vendor Account: Name 1 | K2: MSME Status | L2: Sum of Company Code Currency Value | M2: Count of Count of Outstanding More than 3 Years | N2: Count of Count of Outstanding since 2 to 3 Year | O2: Sum of Sum of Outstanding since 1 to 2 Year | P2: Sum of Sum of Outstanding less Than 1 Year | Q2: MSME | R2: Other
A3: Trade Payables | J3: 360 Realtors LLP | K3: Other | L3: 99945.8 | M3: 0 | N3: 0 | O3: 0 | P3: 99945.8 | R3: =P3 -> 99945.8
J4: LANDROOF & CO | K4: Other | L4: 2716.02 | M4: 0 | N4: 0 | O4: 0 | P4: 2716.02 | R4: =P4 -> 2716.02
A5: Figures as at the end of 31.03.2026 | J5: Mahesh Tulashiram Golawar | K5: Other | L5: 19600 | M5: 0 | N5: 0 | O5: 0 | P5: 19600 | R5: =P5 -> 19600
A6: Particulars | B6: Outstanding for following periods from due date of payment | F6: Total | J6: Prajkta Rajendra Dhanokar | K6: Other | L6: 9800 | M6: 0 | N6: 0 | O6: 9800 | P6: 0 | R6: =P6 -> 0
B7: Less than 1 Year | C7: 1-2 Years | D7: 2-3 Years | E7: More than 3 Years | J7: PropTiger Marketing Services Pvt. L | K7: Other | L7: 1364447.5 | M7: 0 | N7: 0 | O7: 0 | P7: 1364447.5 | R7: =P7 -> 1364447.5
A8: MSME | B8: =Q18 -> 16500 | C8: 0 | D8: 0 | E8: 0 | F8: =SUM(B8:E8) -> 16500 | J8: RENUKA ENTERPRISES | K8: Other | L8: 19800 | M8: 0 | N8: 0 | O8: 19800 | P8: 0 | R8: =P8 -> 0
A9: Others | B9: =R18 -> 1.8497197e+08 | C9: =O18 -> 1.5369573e+08 | D9: 0 | E9: 0 | F9: =SUM(B9:E9) -> 3.386677e+08 | J9: SAI ENTERPRISES | K9: Other | L9: 98954 | M9: 0 | N9: 0 | O9: 0 | P9: 98954 | R9: =P9 -> 98954
A10: Dispute dues-MSME | B10: 0 | C10: 0 | D10: 0 | E10: 0 | F10: =SUM(B10:E10) -> 0 | J10: THANISH CONSTRUCTION LLP | K10: Other | L10: 3.3475597e+08 | M10: 0 | N10: 0 | O10: 1.5366613e+08 | P10: 1.8108984e+08 | R10: =P10 -> 1.8108984e+08
A11: Dispute dues others | B11: 0 | C11: 0 | D11: 0 | E11: 0 | F11: =SUM(B11:E11) -> 0 | J11: BHANDARI SAAJ & ASSOCIATES | K11: Other | L11: 0 | M11: 0 | N11: 0 | O11: 0 | P11: 0 | R11: =P11 -> 0
A12: Total | B12: =SUM(B8:B11) -> 1.8498847e+08 | C12: =SUM(C8:C11) -> 1.5369573e+08 | D12: =SUM(D8:D11) -> 0 | E12: =SUM(E8:E11) -> 0 | F12: =SUM(F8:F11) -> 3.386842e+08 | J12: FAST FACILITY SERVICES | K12: Other | L12: 145019.34 | M12: 0 | N12: 0 | O12: 0 | P12: 145019.34 | R12: =P12 -> 145019.34
J13: NIKISHA CONSULTANCY SERVICES | K13: Other | L13: 7350 | M13: 0 | N13: 0 | O13: 0 | P13: 7350 | R13: =P13 -> 7350
A14: Figures as at the end of 31.03.2025 | J14: Sadguru Enterprises | K14: MSME | L14: 16500 | M14: 0 | N14: 0 | O14: 0 | P14: 16500 | Q14: =P14 -> 16500
A15: Particulars | B15: Outstanding for following periods from due date of payment | F15: Total | J15: VK DESIGN AND PROJECTS PRIVATE LIMI | K15: Other | L15: 2093040 | M15: 0 | N15: 0 | O15: 0 | P15: 2093040 | R15: =P15 -> 2093040
B16: Less than 1 Year | C16: 1-2 Years | D16: 2-3 Years | E16: More than 3 Years | J16: TEJAS SUDAM THAKUR PATIL | K16: Other | L16: 27828 | M16: 0 | N16: 0 | O16: 0 | P16: 27828 | R16: =P16 -> 27828
A17: MSME | B17: 543846.53 | C17: 0 | D17: 0 | E17: 0 | F17: =SUM(B17:E17) -> 543846.53 | J17: MANOJ KUMAR VARMA | K17: Other | L17: 23230 | P17: =L17 -> 23230 | R17: =P17 -> 23230
A18: Others | B18: 5.7107583e+08 | C18: 0 | D18: 0 | E18: 0 | F18: =SUM(B18:E18) -> 5.7107583e+08 | J18: Total | L18: =SUM(L3:L17) -> 3.386842e+08 | O18: =SUM(O3:O17) -> 1.5369573e+08 | P18: =SUM(P3:P17) -> 1.8498847e+08 | Q18: =SUM(Q3:Q17) -> 16500 | R18: =SUM(R3:R17) -> 1.8497197e+08
A19: Dispute dues-MSME | B19: 0 | C19: 0 | D19: 0 | E19: 0 | F19: =SUM(B19:E19) -> 0
A20: Dispute dues Others | B20: 0 | C20: 0 | D20: 0 | E20: 0 | F20: =SUM(B20:E20) -> 0
A21: Total | B21: =SUM(B17:B20) -> 5.7161968e+08 | C21: =SUM(C17:C20) -> 0 | D21: =SUM(D17:D20) -> 0 | E21: =SUM(E17:E20) -> 0 | F21: =SUM(F17:F20) -> 5.7161968e+08

Sheet Dep & DTA DTL
B4: Note-7
B5: Property, Plant and Equipment
B7: Block of Assets | C7: Name of Assets | D7: Opening WDV | E7: Date of Acquisition/ Put to Use | F7: Residual Value | G7: Useful Life | H7: No. Days Used till Last Period | I7: Balance Life | J7: No. Days Used in Current Year | K7: Depreciation Rate | L7: Depreciation Amount | M7: Closing WDV
B9: Plant & Machinery | C9: Office Equipment | D9: =SUM('TB_31.03.2026 (Links)'!E5:E6) -> 32341.13 | E9: 45415 | F9: =D9*0.05 -> 1617.0565 | G9: 5 | H9: 0 | I9: =(5*365-J9)/365 -> 4 | J9: 365 | K9: =1-((F9/D9)^(1/G9)) -> 0.45071973 | L9: =D9*K9/365*J9-1 -> 14575.785 | M9: =D9-L9 -> 17765.345
B12: Grand Total | D12: =SUM(D9:D11) -> 32341.13 | F12: =SUM(F9:F11) -> 1617.0565 | L12: =SUM(L9:L11) -> 14575.785 | M12: =SUM(M9:M11) -> 17765.345
B17: Note 8
B18: Deferred Tax Assets (Net)
B20: Block of Asset | C20: Name of Asset | D20: Rate | E20: Opening WDV | F20: Addition | H20: Deletion | J20: Depreciation | K20: Closing WDV
F21: More Than 180 Days | G21: Less Than 180 Days | H21: More Than 180 Days | I21: Less Than 180 Days
B23: Plant & Machinery | C23: Office Equipment | D23: 0.15 | E23: 46589.35 | F23: 0 | G23: 0 | H23: 0 | I23: 0 | J23: =(E23*D23)+(F23*D23)+(G23*D23/2) -> 6988.4025 | K23: =SUM(E23:G23)-SUM(H23:J23) -> 39600.948
B25: Grand Total | E25: =SUM(E23) -> 46589.35 | F25: =SUM(F23) -> 0 | G25: =SUM(G23) -> 0 | H25: =SUM(H23) -> 0 | I25: 0 | J25: =SUM(J23) -> 6988.4025 | K25: =SUM(K23) -> 39600.948
B28: Deffered Tax Assets/Deffered Tax Liability
B30: Particular | C30: Amount
B31: Depreciation as per books | C31: =L9 -> 14575.785
B32: Depreciation as per Income Tax | C32: =J23 -> 6988.4025
B33: Deductiable Temporary Difference | C33: =C31-C32 -> 7587.3828
B34: Tax Rate | C34: 0.25168
B35: Deffered Tax Assets should be created | C35: =C33*C34 -> 1909.5925
B36: Opening DTA | C36: 3586
B37: Closing DTA | C37: =C35+C36 -> 5495.5925

Sheet Customer Reco details
A1: Customer details
AG2: =SUBTOTAL(9,AG4:AG948) -> -1.3634267e+09
A3: Sr.No. | B3: Project Name | C3: Flat No | D3: Tower | E3: Unit No | F3: Unit Type | G3: Saleable Area Sq.Ft | H3: RERA Carpet Area Sq.Ft | I3: Total Carpet Area Sq.Ft | J3: Title | K3: Customer Code | L3: Customer Name | M3: Customer Pan | N3: Registration No | O3: Registration Date | P3: Total Agreement Value | Q3: Booking Status | R3: Opening - Maintenance | S3: Opening - SDR | T3: Opening Receipt | U3: Total Opening (As per TB 31-3-25) | V3: Receipts Including GST | W3: Receipt- TDS | X3: Due-Maintenance | Y3: Receipt - Maintenance | Z3: Payment-SDR | AA3: Receipt-SDR | AB3: Due-Interest (Including GST) | AC3: GST | AD3: Payment Including GST (Refund) | AE3: Due Booking Cancellation (Including GST) | AF3: Sales | AG3: Closing Balance (As per TB 31-3-26) | AH3: Remark | AI3: As per GST payable Ledger of books 25-26 | AJ3: Net receipt against Flat (Basic) | AL3: Diff
A4: 1 | B4: KOHINOOR UPTOWN AVENUE | C4: Tower 8-608 | D4: Tower 8 | E4: 608 | F4: 2BHK | G4: 1012 | H4: 653.59 | I4: 723.02 | J4: Mr. | K4: 2002502 | L4: ABHIJEET BALASAHEB LONDHE | M4: AVQPL7206G | N4: 2134/2024 | O4: 45441 | P4: 5683644 | Q4: SOLD | R4: 0 | S4: 0 | T4: -1697949.3 | U4: =SUM(R4:T4) -> -1697949.3 | V4: 0 | W4: 0 | X4: 0 | Y4: 0 | Z4: 0 | AA4: 0 | AB4: 0 | AC4: -7142.9 | AD4: 0 | AG4: =SUM(U4:AF4) -> -1705092.2 | AI4: 7142.9 | AJ4: =SUM(U4:AE4) -> -1705092.2 | AL4: =+AC4+AI4 -> 0 | AO4: 2002502 | AP4: 20412001
A5: =A4+1 -> 2 | B5: KOHINOOR UPTOWN AVENUE | C5: Tower 1-1107 | D5: Tower 1 | E5: 1107 | F5: 2BHK | G5: 1114 | H5: 683.3 | I5: 795.57 | J5: Mr. | K5: 2020808 | L5: ABHIJEET KUSURKAR | M5: BCSPK1165K | P5: 6928571 | Q5: CANCELLED | R5: 0 | S5: 0 | T5: -75000 | U5: =SUM(R5:T5) -> -75000 | V5: 75000 | W5: 0 | X5: 0 | Y5: 0 | Z5: 0 | AA5: 0 | AB5: 0 | AC5: 0 | AD5: 0 | AG5: =SUM(U5:AF5) -> 0 | AI5: 0 | AJ5: =SUM(U5:AE5) -> 0 | AL5: =+AC5-AI5 -> 0 | AO5: 2020808 | AP5: 20412016
A6: =A5+1 -> 3 | B6: KOHINOOR UPTOWN AVENUE | C6: Tower 7-901 | D6: Tower 7 | E6: 901 | F6: 2BHK | G6: 1012 | H6: 653.59 | I6: 723.02 | J6: Mr. | K6: 2002404 | L6: ABHIJEET NAMDEV PATIL | M6: BVNPP0532M | N6: 2627/2024 | O6: 45462 | P6: 5698827 | Q6: SOLD | R6: 0 | S6: 0 | T6: -1707263.6 | U6: =SUM(R6:T6) -> -1707263.6 | V6: 0 | W6: 0 | X6: 0 | Y6: 0 | Z6: 0 | AA6: 0 | AB6: 0 | AC6: -2380.9 | AD6: 0 | AG6: =SUM(U6:AF6) -> -1709644.5 | AI6: 2380.9 | AJ6: =SUM(U6:AE6) -> -1709644.5 | AL6: =+AC6+AI6 -> 0 | AO6: 2002404 | AP6: 20412009
A7: =A6+1 -> 4 | B7: KOHINOOR UPTOWN AVENUE | C7: Tower 4-1703 | D7: Tower 4 | E7: 1703 | F7: 3BHK | G7: 1787 | H7: 1138.51 | I7: 1276.29 | J7: Mr. | K7: 2018875 | L7: ABHIJEET PRAKASH SAMANT | M7: AZCPS1564J | N7: 4689/2024 | O7: 45629 | P7: 14080286 | Q7: SOLD | R7: 0 | S7: 0 | T7: -4322636.6 | U7: =SUM(R7:T7) -> -4322636.6 | V7: -95238 | W7: 0 | X7: 0 | Y7: 0 | Z7: 0 | AA7: 0 | AB7: 0 | AC7: 0 | AD7: 0 | AG7: =SUM(U7:AF7) -> -4417874.6 | AI7: 0 | AJ7: =SUM(U7:AE7) -> -4417874.6 | AL7: =+AC7-AI7 -> 0 | AO7: 2018875 | AP7: 20412003
A8: =A7+1 -> 5 | B8: KOHINOOR UPTOWN AVENUE | C8: Tower 2-1201 | D8: Tower 2 | E8: 1201 | F8: 2BHK | G8: 1012 | H8: 653.59 | I8: 723.02 | J8: Ms. | K8: 2020347 | L8: ABHIJIT ANIL SHRUNGARE | M8: ETMPS6757M | P8: 6134762 | Q8: SOLD | R8: 0 | S8: 0 | T8: -650905 | U8: =SUM(R8:T8) -> -650905 | V8: 0 | W8: 0 | X8: 0 | Y8: 0 | Z8: 0 | AA8: 0 | AB8: 0 | AC8: 0 | AD8: 0 | AG8: =SUM(U8:AF8) -> -650905 | AI8: 0 | AJ8: =SUM(U8:AE8) -> -650905 | AL8: =+AC8-AI8 -> 0 | AO8: 2020347 | AP8: 20412005
A9: =A8+1 -> 6 | B9: KOHINOOR UPTOWN AVENUE | C9: Tower 8-1805 | D9: Tower 8 | E9: 1805 | F9: Row House | G9: 1265 | H9: 813.33 | I9: 903.31 | J9: Mr. | K9: 2002464 | L9: ABHIJIT ARUNRAO KHANDAR | M9: BJYPK7780D | N9: 2904/2024 | O9: 45475 | P9: 7142857 | Q9: CANCELLED | R9: 0 | S9: 0 | T9: -1834244 | U9: =SUM(R9:T9) -> -1834244 | V9: 1834244 | W9: 0 | X9: 0 | Y9: 0 | Z9: 0 | AA9: 0 | AB9: 0 | AC9: 0 | AD9: 0 | AG9: =SUM(U9:AF9) -> 0 | AI9: 0 | AJ9: =SUM(U9:AE9) -> 0 | AL9: =+AC9-AI9 -> 0 | AO9: 2002464 | AP9: 20412007
A10: =A9+1 -> 7 | B10: KOHINOOR UPTOWN AVENUE | C10: Tower 2-301 | D10: Tower 2 | E10: 301 | F10: 2BHK | G10: 1012 | H10: 653.59 | I10: 723.02 | J10: Mr. | K10: 2019572 | L10: ABHIJIT ARUNRAO KULKARNI | M10: BNQPK0310M | P10: 6044643 | Q10: CANCELLED | R10: 0 | S10: 0 | T10: -758947 | U10: =SUM(R10:T10) -> -758947 | V10: 770544 | W10: 0 | X10: 0 | Y10: 0 | Z10: 0 | AA10: 0 | AB10: 0 | AC10: -23194 | AD10: 0 | AG10: =SUM(U10:AF10) -> -11597 | AI10: 23194 | AJ10: =SUM(U10:AE10) -> -11597 | AL10: =+AC10+AI10 -> 0 | AO10: 2019572 | AP10: 20412010
A11: =A10+1 -> 8 | B11: KOHINOOR UPTOWN AVENUE | C11: Tower 1-701 | D11: Tower 1 | E11: 701 | F11: 2BHK | G11: 1012 | H11: 653.59 | I11: 723.02 | J11: Mr. | K11: 2018482 | L11: ABHIJIT LAXMAN NALAWADE | M11: BGVPN4676D | P11: 6437429 | Q11: CANCELLED | R11: 0 | S11: 0 | T11: -778281 | U11: =SUM(R11:T11) -> -778281 | V11: 778281 | W11: 0 | X11: 0 | Y11: 0 | Z11: 0 | AA11: 0 | AB11: 0 | AC11: 0 | AD11: 0 | AG11: =SUM(U11:AF11) -> 0 | AI11: 0 | AJ11: =SUM(U11:AE11) -> 0 | AL11: =+AC11-AI11 -> 0 | AO11: 2018482 | AP11: 20412008
A12: =A11+1 -> 9 | B12: KOHINOOR UPTOWN AVENUE | C12: Tower 2-1902 | D12: Tower 2 | E12: 1902 | F12: 2BHK | G12: 1114 | H12: 683.3 | I12: 795.57 | J12: Mr. | K12: 2021311 | L12: ABHIJIT LAXMAN NALAWADE | M12: BGVPN4676D | P12: 7205357 | Q12: CANCELLED | R12: 0 | S12: 0 | T12: 0 | U12: =SUM(R12:T12) -> 0 | V12: 0 | W12: 0 | X12: 0 | Y12: 0 | Z12: 0 | AA12: 0 | AB12: 0 | AC12: 0 | AD12: 0 | AG12: =SUM(U12:AF12) -> 0 | AI12: 0 | AJ12: =SUM(U12:AE12) -> 0 | AL12: =+AC12-AI12 -> 0 | AO12: 2021311 | AP12: 20412002
A13: =A12+1 -> 10 | B13: KOHINOOR UPTOWN AVENUE | C13: Tower 6-1202 | D13: Tower 6 | E13: 1202 | F13: 2BHK | G13: 1114 | H13: 683.3 | I13: 795.57 | J13: Mr. | K13: 2017884 | L13: ABHIJIT PRAKASHRAO DATIR | M13: BYIPD4430L | N13: 2842/2024 | O13: 45470 | P13: 6401714 | Q13: SOLD | R13: 0 | S13: 0 | T13: -2083531.3 | U13: =SUM(R13:T13) -> -2083531.3 | V13: 0 | W13: 0 | X13: 0 | Y13: 0 | Z13: 0 | AA13: 0 | AB13: 0 | AC13: 0 | AD13: 0 | AG13: =SUM(U13:AF13) -> -2083531.3 | AI13: 0 | AJ13: =SUM(U13:AE13) -> -2083531.3 | AL13: =+AC13-AI13 -> 0 | AO13: 2017884 | AP13: 20412017
A14: =A13+1 -> 11 | B14: KOHINOOR UPTOWN AVENUE | C14: Tower 6-308 | D14: Tower 6 | E14: 308 | F14: 2BHK | G14: 1012 | H14: 653.59 | I14: 723.02 | J14: Mr. | K14: 2017703 | L14: ABHIJIT SHANKARRAO SALUNKHE | M14: IKFPS3114A | N14: 2550/2024 | O14: 45456 | P14: 5758858 | Q14: SOLD | R14: 0 | S14: 0 | T14: -1785245.1 | U14: =SUM(R14:T14) -> -1785245.1 | V14: 0 | W14: 0 | X14: 0 | Y14: 0 | Z14: 0 | AA14: 0 | AB14: 0 | AC14: 0 | AD14: 0 | AG14: =SUM(U14:AF14) -> -1785245.1 | AI14: 0 | AJ14: =SUM(U14:AE14) -> -1785245.1 | AL14: =+AC14-AI14 -> 0 | AO14: 2017703 | AP14: 20412004
A15: =A14+1 -> 12 | B15: KOHINOOR UPTOWN AVENUE | C15: Tower 7-1007 | D15: Tower 7 | E15: 1007 | F15: 2BHK | G15: 1114 | H15: 683.3 | I15: 795.57 | J15: Mr. | K15: 2018907 | L15: ABHIMANYU MARUTI GHARGINE | M15: ABQPG9733K | N15: 3349/2024 | O15: 45509 | P15: 6304075 | Q15: SOLD | R15: 0 | S15: 0 | T15: -484221.61 | U15: =SUM(R15:T15) -> -484221.61 | V15: -1407000 | W15: 0 | X15: 0 | Y15: 0 | Z15: 0 | AA15: 0 | AB15: 0 | AC15: -16667 | AD15: 0 | AG15: =SUM(U15:AF15) -> -1907888.6 | AI15: 16667 | AJ15: =SUM(U15:AE15) -> -1907888.6 | AL15: =+AC15+AI15 -> 0 | AO15: 2018907 | AP15: 20412006
A16: =A15+1 -> 13 | B16: KOHINOOR UPTOWN AVENUE | C16: Tower 1-707 | D16: Tower 1 | E16: 707 | F16: 2BHK | G16: 1114 | H16: 683.3 | I16: 795.57 | J16: Mr. | K16: 2018363 | L16: ABHISHEK CHANDRAKANT SURYAWANSHI | M16: LVJPS2992E | P16: 7155788 | Q16: CANCELLED | R16: 0 | S16: 0 | T16: -140253 | U16: =SUM(R16:T16) -> -140253 | V16: 151000 | W16: 0 | X16: 0 | Y16: 0 | Z16: 0 | AA16: 0 | AB16: 0 | AC16: -21493.57 | AD16: 0 | AG16: =SUM(U16:AF16) -> -10746.57 | AI16: 21494 | AJ16: =SUM(U16:AE16) -> -10746.57 | AL16: =+AC16+AI16 -> 0.43 | AO16: 2018363
A17: =A16+1 -> 14 | B17: KOHINOOR UPTOWN AVENUE | C17: Tower 7-1601 | D17: Tower 7 | E17: 1601 | F17: 2BHK | G17: 1012 | H17: 653.59 | I17: 723.02 | J17: Mr. | K17: 2021019 | L17: ABHISHEK CHOUHAN | M17: AJNPC6908P | N17: 2061/2025 | O17: 45737 | P17: 6151714 | Q17: SOLD | R17: 0 | S17: 0 | T17: -1845514.3 | U17: =SUM(R17:T17) -> -1845514.3 | V17: -61517.14 | W17: 0 | X17: 0 | Y17: 0 | Z17: 0 | AA17: 0 | AB17: 0 | AC17: 0 | AD17: 0 | AG17: =SUM(U17:AF17) -> -1907031.4 | AI17: 0 | AJ17: =SUM(U17:AE17) -> -1907031.4 | AL17: =+AC17-AI17 -> 0 | AO17: 2021019
A18: =A17+1 -> 15 | B18: KOHINOOR UPTOWN AVENUE | C18: Tower 8-1001 | D18: Tower 8 | E18: 1001 | F18: 2BHK | G18: 1012 | H18: 653.59 | I18: 723.02 | J18: Mr. | K18: 2002410 | L18: ABHISHEK DILIP BONDARDE | M18: BLDPB6997C | N18: 1713/2024 | O18: 45429 | P18: 5698827 | Q18: SOLD | R18: 0 | S18: 0 | T18: -1759492.7 | U18: =SUM(R18:T18) -> -1759492.7 | V18: -200000 | W18: 0 | X18: 0 | Y18: 0 | Z18: 0 | AA18: 0 | AB18: 0 | AC18: -7143 | AD18: 0 | AG18: =SUM(U18:AF18) -> -1966635.7 | AI18: 7143 | AJ18: =SUM(U18:AE18) -> -1966635.7 | AL18: =+AC18+AI18 -> 0 | AO18: 2002410
A19: =A18+1 -> 16 | B19: KOHINOOR UPTOWN AVENUE | C19: Tower 6-2208 | D19: Tower 6 | E19: 2208 | F19: 2BHK | G19: 1012 | H19: 653.59 | I19: 723.02 | J19: Mr. | K19: 2015482 | L19: ABHISHEK MODI | M19: BMOPM2291L | N19: 3036/2024 | O19: 45483 | P19: 5910666 | Q19: SOLD | R19: 0 | S19: 0 | T19: -1833196 | U19: =SUM(R19:T19) -> -1833196 | V19: 50000 | W19: 0 | X19: 0 | Y19: 0 | Z19: 0 | AA19: 0 | AB19: 0 | AC19: 0 | AD19: 0 | AG19: =SUM(U19:AF19) -> -1783196 | AI19: 0 | AJ19: =SUM(U19:AE19) -> -1783196 | AL19: =+AC19-AI19 -> 0 | AO19: 2015482
A20: =A19+1 -> 17 | B20: KOHINOOR UPTOWN AVENUE | C20: Tower 3-1407 | D20: Tower 3 | E20: 1407 | F20: 2BHK | G20: 1114 | H20: 683.3 | I20: 795.57 | J20: Mr. | K20: 2001892 | L20: ABHISHEK PRAVINKUMAR KODULE | M20: EPNPK9324H | N20: 2542/2024 | O20: 45456 | P20: 6339238 | Q20: SOLD | R20: 0 | S20: 0 | T20: -1844627.4 | U20: =SUM(R20:T20) -> -1844627.4 | V20: -50000 | W20: 0 | X20: 0 | Y20: 0 | Z20: 0 | AA20: 0 | AB20: 0 | AC20: 0 | AD20: 0 | AG20: =SUM(U20:AF20) -> -1894627.4 | AI20: 0 | AJ20: =SUM(U20:AE20) -> -1894627.4 | AL20: =+AC20-AI20 -> 0 | AO20: 2001892
A21: =A20+1 -> 18 | B21: KOHINOOR UPTOWN AVENUE | C21: Tower 3-1902 | D21: Tower 3 | E21: 1902 | F21: 2BHK | G21: 1114 | H21: 683.3 | I21: 795.57 | J21: Mr. | K21: 2002189 | L21: ABHISHEK RAJENDRA HINGE | M21: AXIPH5032N | N21: 2003/2024 | O21: 45434 | P21: 6337489 | Q21: SOLD | R21: 0 | S21: 0 | T21: -1711383.7 | U21: =SUM(R21:T21) -> -1711383.7 | V21: -182718 | W21: 0 | X21: 0 | Y21: 0 | Z21: 0 | AA21: 0 | AB21: 0 | AC21: 0 | AD21: 0 | AG21: =SUM(U21:AF21) -> -1894101.7 | AI21: 0 | AJ21: =SUM(U21:AE21) -> -1894101.7 | AL21: =+AC21+AI21 -> 0 | AO21: 2002189
A22: =A21+1 -> 19 | B22: KOHINOOR UPTOWN AVENUE | C22: Tower 3-1205 | D22: Tower 3 | E22: 1205 | F22: 3BHK | G22: 1498 | H22: 954.87 | I22: 1069.73 | J22: Mr. | K22: 2022124 | L22: ABHISHEK SONI | M22: BSPPS9925N | N22: 2888/2024 | O22: 45474 | P22: 8812477 | Q22: SOLD | R22: 0 | S22: 0 | T22: -2731866.6 | U22: =SUM(R22:T22) -> -2731866.6 | V22: 0 | W22: 0 | X22: 0 | Y22: 0 | Z22: 0 | AA22: 0 | AB22: 0 | AC22: 0 | AD22: 0 | AG22: =SUM(U22:AF22) -> -2731866.6 | AI22: 0 | AJ22: =SUM(U22:AE22) -> -2731866.6 | AL22: =+AC22-AI22 -> 0 | AO22: 2022124
A23: =A22+1 -> 20 | B23: KOHINOOR UPTOWN AVENUE | C23: Tower 4-306 | D23: Tower 4 | E23: 306 | F23: 3BHK | G23: 1787 | H23: 1138.51 | I23: 1276.29 | J23: Mr. | K23: 2002244 | L23: ABHISHEK UPADHYAY | M23: ABLPU5450C | N23: 2508/2024 | O23: 45455 | P23: 10776761 | Q23: SOLD | R23: 0 | S23: 0 | T23: -3308464.6 | U23: =SUM(R23:T23) -> -3308464.6 | V23: 0 | W23: 0 | X23: 0 | Y23: 0 | Z23: 0 | AA23: 0 | AB23: 0 | AC23: 0 | AD23: 0 | AG23: =SUM(U23:AF23) -> -3308464.6 | AI23: 0 | AJ23: =SUM(U23:AE23) -> -3308464.6 | AL23: =+AC23-AI23 -> 0 | AO23: 2002244
A24: =A23+1 -> 21 | B24: KOHINOOR UPTOWN AVENUE | C24: Tower 4-901 | D24: Tower 4 | E24: 901 | F24: 3BHK | G24: 1787 | H24: 1138.51 | I24: 1276.29 | J24: Mr. | K24: 2002256 | L24: ABINASH ACHARYA | M24: BKJPA0876Q | N24: 2087/2024 | O24: 45439 | P24: 11269682 | Q24: CANCELLED | R24: 0 | S24: 0 | T24: -2993782.9 | U24: =SUM(R24:T24) -> -2993782.9 | V24: 2958290 | W24: 0 | X24: 0 | Y24: 0 | Z24: 0 | AA24: 0 | AB24: 0 | AC24: 0 | AD24: 0 | AG24: =SUM(U24:AF24) -> -35492.9 | AI24: 0 | AJ24: =SUM(U24:AE24) -> -35492.9 | AL24: =+AC24-AI24 -> 0 | AO24: 2002256
A25: =A24+1 -> 22 | B25: KOHINOOR UPTOWN AVENUE | C25: Tower 8-1104 | D25: Tower 8 | E25: 1104 | F25: 3BHK | G25: 1498 | H25: 954.87 | I25: 1069.73 | J25: Ms. | K25: 2002418 | L25: ABOLI AVINASH PATHAK | M25: ECGPP5376E | N25: 2450/2024 | O25: 45454 | P25: 8492059 | Q25: SOLD | R25: 0 | S25: 0 | T25: -2509727.1 | U25: =SUM(R25:T25) -> -2509727.1 | V25: 0 | W25: 0 | X25: 0 | Y25: 0 | Z25: 0 | AA25: 0 | AB25: 0 | AC25: -25238.6 | AD25: 0 | AG25: =SUM(U25:AF25) -> -2534965.7 | AI25: 25238.6 | AJ25: =SUM(U25:AE25) -> -2534965.7 | AL25: =+AC25+AI25 -> 0 | AO25: 2002418
A26: =A25+1 -> 23 | B26: KOHINOOR UPTOWN AVENUE | C26: Tower 2-1007 | D26: Tower 2 | E26: 1007 | F26: 2BHK | G26: 1114 | H26: 683.3 | I26: 795.57 | J26: Mr. | K26: 2021515 | L26: ADITYA ABHAY GAIKWAD | M26: DFWPG8744D | P26: 7026762 | Q26: CANCELLED | R26: 0 | S26: 0 | T26: -75000 | U26: =SUM(R26:T26) -> -75000 | V26: 75000 | W26: 0 | X26: 0 | Y26: 0 | Z26: 0 | AA26: 0 | AB26: 0 | AC26: 0 | AD26: 0 | AG26: =SUM(U26:AF26) -> 0 | AI26: 0 | AJ26: =SUM(U26:AE26) -> 0 | AL26: =+AC26-AI26 -> 0 | AO26: 2021515
A27: =A26+1 -> 24 | B27: KOHINOOR UPTOWN AVENUE | C27: Tower 7-804 | D27: Tower 7 | E27: 804 | F27: 2.5BHK | G27: 1265 | H27: 813.33 | I27: 903.31 | J27: Mr. | K27: 2002399 | L27: ADITYA AJAY BIDKAR | M27: CTQPB9937G | N27: 1838/2024 | O27: 45428 | P27: 7164190 | Q27: SOLD | R27: 0 | S27: 0 | T27: -2216374 | U27: =SUM(R27:T27) -> -2216374 | V27: 0 | W27: 0 | X27: 0 | Y27: 0 | Z27: 0 | AA27: 0 | AB27: 0 | AC27: 0 | AD27: 0 | AG27: =SUM(U27:AF27) -> -2216374 | AI27: 0 | AJ27: =SUM(U27:AE27) -> -2216374 | AL27: =+AC27+AI27 -> 0 | AO27: 2002399
A28: =A27+1 -> 25 | B28: KOHINOOR UPTOWN AVENUE | C28: Tower 3-607 | D28: Tower 3 | E28: 607 | F28: 2BHK | G28: 1114 | H28: 683.3 | I28: 795.57 | J28: Mr. | K28: 2002220 | L28: ADITYA DEEPAK FUKE | M28: ACOPF6786C | N28: 2050/2024 | O28: 45440 | P28: 6287368 | Q28: SOLD | R28: 0 | S28: 0 | T28: -1879068.5 | U28: =SUM(R28:T28) -> -1879068.5 | V28: 0 | W28: 0 | X28: 0 | Y28: 0 | Z28: 0 | AA28: 0 | AB28: 0 | AC28: -7142 | AD28: 0 | AG28: =SUM(U28:AF28) -> -1886210.5 | AI28: 7142 | AJ28: =SUM(U28:AE28) -> -1886210.5 | AL28: =+AC28+AI28 -> 0 | AO28: 2002220
A29: =A28+1 -> 26 | B29: KOHINOOR UPTOWN AVENUE | C29: Tower 3-1001 | D29: Tower 3 | E29: 1001 | F29: 2BHK | G29: 1012 | H29: 653.59 | I29: 723.02 | J29: Mr. | K29: 2001869 | L29: ADITYA GAJANAN VEDPATHAK | M29: AYIPV8704G | N29: 1976/2024 | O29: 45435 | P29: 5698827 | Q29: SOLD | R29: 0 | S29: 0 | T29: -1759492.6 | U29: =SUM(R29:T29) -> -1759492.6 | V29: 0 | W29: 0 | X29: 0 | Y29: 0 | Z29: 0 | AA29: 0 | AB29: 0 | AC29: -7142 | AD29: 0 | AG29: =SUM(U29:AF29) -> -1766634.6 | AI29: 7142 | AJ29: =SUM(U29:AE29) -> -1766634.6 | AL29: =+AC29+AI29 -> 0 | AO29: 2001869
A30: =A29+1 -> 27 | B30: KOHINOOR UPTOWN AVENUE | C30: Tower 3-1203 | D30: Tower 3 | E30: 1203 | F30: 3BHK | G30: 1375 | H30: 876.73 | I30: 982.22 | J30: Mr. | K30: 2015843 | L30: ADITYA PATIL | M30: CNPPP3018R | N30: 2661/2024 | O30: 45463 | P30: 7678571 | Q30: SOLD | R30: 0 | S30: 0 | T30: -2303573.1 | U30: =SUM(R30:T30) -> -2303573.1 | V30: 0 | W30: 0 | X30: 0 | Y30: 0 | Z30: 0 | AA30: 0 | AB30: 0 | AC30: 0 | AD30: 0 | AG30: =SUM(U30:AF30) -> -2303573.1 | AI30: 0 | AJ30: =SUM(U30:AE30) -> -2303573.1 | AL30: =+AC30-AI30 -> 0 | AO30: 2015843
A31: =A30+1 -> 28 | B31: KOHINOOR UPTOWN AVENUE | C31: Tower 8-1904 | D31: Tower 8 | E31: 1904 | F31: 3BHK | G31: 1498 | H31: 954.87 | I31: 1069.73 | J31: Mrs. | K31: 2019424 | L31: AHIRE SEEMA SAHEBRAO | M31: AHHPA9667M | N31: 4088/2024 | O31: 45560 | P31: 8946381 | Q31: SOLD | R31: 0 | S31: 0 | T31: -2673378.1 | U31: =SUM(R31:T31) -> -2673378.1 | V31: 0 | W31: 0 | X31: 0 | Y31: 0 | Z31: 0 | AA31: 0 | AB31: 0 | AC31: 0 | AD31: 0 | AG31: =SUM(U31:AF31) -> -2673378.1 | AI31: 0 | AJ31: =SUM(U31:AE31) -> -2673378.1 | AL31: =+AC31-AI31 -> 0 | AO31: 2019424
A32: =A31+1 -> 29 | B32: KOHINOOR UPTOWN AVENUE | C32: Tower 3-1006 | D32: Tower 3 | E32: 1006 | F32: 3BHK | G32: 1375 | H32: 876.73 | I32: 982.22 | J32: Mr. | K32: 2001872 | L32: AJAY ANANDRAO BHANDARE | M32: NJHMK6793D | N32: 2868/2024 | O32: 45471 | P32: 7741048 | Q32: SOLD | R32: 0 | S32: 0 | T32: -2293825.8 | U32: =SUM(R32:T32) -> -2293825.8 | V32: 0 | W32: 0 | X32: 0 | Y32: 0 | Z32: 0 | AA32: 0 | AB32: 0 | AC32: 0 | AD32: 0 | AG32: =SUM(U32:AF32) -> -2293825.8 | AI32: 0 | AJ32: =SUM(U32:AE32) -> -2293825.8 | AL32: =+AC32-AI32 -> 0 | AO32: 2001872
A33: =A32+1 -> 30 | B33: KOHINOOR UPTOWN AVENUE | C33: Tower 8-1304 | D33: Tower 8 | E33: 1304 | F33: 2.5BHK | G33: 1265 | H33: 813.33 | I33: 903.31 | J33: Mr. | K33: 2002430 | L33: AJAY KUMAR SAH | M33: EPTPS7020J | N33: 3028/2024 | O33: 45483 | P33: 7160667 | Q33: SOLD | R33: 0 | S33: 0 | T33: -2219804 | U33: =SUM(R33:T33) -> -2219804 | V33: 0 | W33: 0 | X33: 0 | Y33: 0 | Z33: 0 | AA33: 0 | AB33: 0 | AC33: 0 | AD33: 0 | AG33: =SUM(U33:AF33) -> -2219804 | AI33: 0 | AJ33: =SUM(U33:AE33) -> -2219804 | AL33: =+AC33-AI33 -> 0 | AO33: 2002430
A34: =A33+1 -> 31 | B34: KOHINOOR UPTOWN AVENUE | C34: Tower 4-304 | D34: Tower 4 | E34: 304 | F34: 3BHK | G34: 1787 | H34: 1138.51 | I34: 1276.29 | J34: Mr. | K34: 2002242 | L34: AJAY SINGH | M34: AETPT3769G | N34: 2357/2024 | O34: 45448 | P34: 10866000 | Q34: SOLD | R34: 0 | S34: 0 | T34: -3368460 | U34: =SUM(R34:T34) -> -3368460 | V34: 0 | W34: 0 | X34: 0 | Y34: 0 | Z34: 0 | AA34: 0 | AB34: 0 | AC34: 0 | AD34: 0 | AG34: =SUM(U34:AF34) -> -3368460 | AI34: 0 | AJ34: =SUM(U34:AE34) -> -3368460 | AL34: =+AC34-AI34 -> 0 | AO34: 2002242
A35: =A34+1 -> 32 | B35: KOHINOOR UPTOWN AVENUE | C35: Tower 3-1005 | D35: Tower 3 | E35: 1005 | F35: 3BHK | G35: 1498 | H35: 954.87 | I35: 1069.73 | J35: Mrs. | K35: 2001871 | L35: AJITA PRASAD DESHPANDE | M35: AIPPU3226P | N35: 1905/2024 | O35: 45429 | P35: 8581345 | Q35: SOLD | R35: 0 | S35: 0 | T35: -2552951.8 | U35: =SUM(R35:T35) -> -2552951.8 | V35: 0 | W35: 0 | X35: 0 | Y35: 0 | Z35: 0 | AA35: 0 | AB35: 0 | AC35: -21454 | AD35: 0 | AG35: =SUM(U35:AF35) -> -2574405.8 | AI35: 21454 | AJ35: =SUM(U35:AE35) -> -2574405.8 | AL35: =+AC35+AI35 -> 0 | AO35: 2001871
A36: =A35+1 -> 33 | B36: KOHINOOR UPTOWN AVENUE | C36: Tower 8-408 | D36: Tower 8 | E36: 408 | F36: 2BHK | G36: 1012 | H36: 653.59 | I36: 723.02 | J36: Mr. | K36: 2002494 | L36: AKASH DEBASHISH CHATTERJI | M36: BDMPC9577Q | N36: 1826/2024 | O36: 45434 | P36: 5668460 | Q36: SOLD | R36: 0 | S36: 0 | T36: -1725222.7 | U36: =SUM(R36:T36) -> -1725222.7 | V36: 0 | W36: 0 | X36: 0 | Y36: 0 | Z36: 0 | AA36: 0 | AB36: 0 | AC36: -31999 | AD36: 0 | AG36: =SUM(U36:AF36) -> -1757221.7 | AI36: 31999 | AJ36: =SUM(U36:AE36) -> -1757221.7 | AL36: =+AC36+AI36 -> 0 | AO36: 2002494
A37: =A36+1 -> 34 | B37: KOHINOOR UPTOWN AVENUE | C37: Tower 4-902 | D37: Tower 4 | E37: 902 | F37: 3BHK | G37: 1787 | H37: 1138.51 | I37: 1276.29 | J37: Mr. | K37: 2019333 | L37: AKASH RAJENDRA TAWADE | M37: BJSPT4107R | N37: 3027/2024 | O37: 45483 | P37: 11580286 | Q37: SOLD | R37: 0 | S37: 0 | T37: -3383554.6 | U37: =SUM(R37:T37) -> -3383554.6 | V37: -50000 | W37: 0 | X37: 0 | Y37: 0 | Z37: 0 | AA37: 0 | AB37: 0 | AC37: -6596 | AD37: 0 | AG37: =SUM(U37:AF37) -> -3440150.6 | AI37: 6596 | AJ37: =SUM(U37:AE37) -> -3440150.6 | AL37: =+AC37+AI37 -> 0 | AO37: 2019333
A38: =A37+1 -> 35 | B38: KOHINOOR UPTOWN AVENUE | C38: Tower 1-2108 | D38: Tower 1 | E38: 2108 | F38: 2BHK | G38: 1012 | H38: 653.59 | I38: 723.02 | J38: Mr. | K38: 2017977 | L38: Akash Ramesh Naktode | M38: ATNPN5524E | P38: 6151714 | Q38: SOLD | R38: 0 | S38: 0 | T38: -1100478 | U38: =SUM(R38:T38) -> -1100478 | V38: 0 | W38: 0 | X38: 0 | Y38: 0 | Z38: 0 | AA38: 0 | AB38: 0 | AC38: 0 | AD38: 0 | AG38: =SUM(U38:AF38) -> -1100478 | AI38: 0 | AJ38: =SUM(U38:AE38) -> -1100478 | AL38: =+AC38-AI38 -> 0 | AO38: 2017977
A39: =A38+1 -> 36 | B39: KOHINOOR UPTOWN AVENUE | C39: Tower 6-702 | D39: Tower 6 | E39: 702 | F39: 2BHK | G39: 1114 | H39: 683.3 | I39: 795.57 | J39: Mr. | K39: 2002275 | L39: AKASH SAMBHE | M39: GFDPE7974P | N39: 2091/2024 | O39: 45439 | P39: 6401714 | Q39: SOLD | R39: 0 | S39: 0 | T39: -1984531.4 | U39: =SUM(R39:T39) -> -1984531.4 | V39: 0 | W39: 0 | X39: 0 | Y39: 0 | Z39: 0 | AA39: 0 | AB39: 0 | AC39: 0 | AD39: 0 | AG39: =SUM(U39:AF39) -> -1984531.4 | AI39: 0 | AJ39: =SUM(U39:AE39) -> -1984531.4 | AL39: =+AC39-AI39 -> 0 | AO39: 2002275
A40: =A39+1 -> 37 | B40: KOHINOOR UPTOWN AVENUE | C40: Tower 6-905 | D40: Tower 6 | E40: 905 | F40: 2BHK | G40: 1498 | H40: 954.87 | I40: 1069.73 | J40: Mr. | K40: 2018838 | L40: AKASH SHANTARAM DOKE | M40: CUNPD7096Q | N40: 4694/2024 | O40: 45629 | P40: 9491048 | Q40: SOLD | R40: 0 | S40: 0 | T40: -2847314.3 | U40: =SUM(R40:T40) -> -2847314.3 | V40: -264000 | W40: 0 | X40: 0 | Y40: 0 | Z40: 0 | AA40: 0 | AB40: 0 | AC40: 0 | AD40: 0 | AG40: =SUM(U40:AF40) -> -3111314.3 | AI40: 0 | AJ40: =SUM(U40:AE40) -> -3111314.3 | AL40: =+AC40-AI40 -> 0 | AO40: 2018838
A41: =A40+1 -> 38 | B41: KOHINOOR UPTOWN AVENUE | C41: Tower 7-707 | D41: Tower 7 | E41: 707 | F41: 2BHK | G41: 1114 | H41: 683.3 | I41: 795.57 | J41: Mr. | K41: 2002395 | L41: AKASH SUBHASHRAO NAGAPURE | M41: AVZPN3770E | N41: 2105/2024 | O41: 45440 | P41: 6305333 | Q41: SOLD | R41: 0 | S41: 0 | T41: -1742600.7 | U41: =SUM(R41:T41) -> -1742600.7 | V41: -149000 | W41: 0 | X41: 0 | Y41: 0 | Z41: 0 | AA41: 0 | AB41: 0 | AC41: 0 | AD41: 0 | AG41: =SUM(U41:AF41) -> -1891600.7 | AI41: 0 | AJ41: =SUM(U41:AE41) -> -1891600.7 | AL41: =+AC41+AI41 -> 0 | AO41: 2002395
A42: =A41+1 -> 39 | B42: KOHINOOR UPTOWN AVENUE | C42: Tower 6-1305 | D42: Tower 6 | E42: 1305 | F42: 2.5BHK | G42: 1265 | H42: 813.33 | I42: 903.31 | J42: Mr. | K42: 2017891 | L42: AKASH VISHWAS LONDHE | M42: AUPPL5382D | N42: 2415/2024 | O42: 45454 | P42: 7291415 | Q42: SOLD | R42: 0 | S42: 0 | T42: -2202007.6 | U42: =SUM(R42:T42) -> -2202007.6 | V42: 0 | W42: 0 | X42: 0 | Y42: 0 | Z42: 0 | AA42: 0 | AB42: 0 | AC42: 0 | AD42: 0 | AG42: =SUM(U42:AF42) -> -2202007.6 | AI42: 0 | AJ42: =SUM(U42:AE42) -> -2202007.6 | AL42: =+AC42-AI42 -> 0 | AO42: 2017891
A43: =A42+1 -> 40 | B43: KOHINOOR UPTOWN AVENUE | C43: Tower 7-1802 | D43: Tower 7 | E43: 1802 | F43: 2BHK | G43: 1114 | H43: 683.3 | I43: 795.57 | J43: Mr. | K43: 2002340 | L43: AKHILESH JITENDRA OJHA | M43: AISPD7368N | N43: 1876/2024 | O43: 45434 | P43: 6337489 | Q43: SOLD | R43: 0 | S43: 0 | T43: -1847003.5 | U43: =SUM(R43:T43) -> -1847003.5 | V43: 0 | W43: 0 | X43: 0 | Y43: 0 | Z43: 0 | AA43: 0 | AB43: 0 | AC43: -54245 | AD43: 0 | AG43: =SUM(U43:AF43) -> -1901248.5 | AI43: 54245 | AJ43: =SUM(U43:AE43) -> -1901248.5 | AL43: =+AC43+AI43 -> 0 | AO43: 2002340
A44: =A43+1 -> 41 | B44: KOHINOOR UPTOWN AVENUE | C44: Tower 6-407 | D44: Tower 6 | E44: 407 | F44: 2BHK | G44: 1114 | H44: 683.3 | I44: 795.57 | J44: Mr. | K44: 2018246 | L44: AKOSKAR S P | M44: AAWPA4618E | N44: 3161/2024 | O44: 45496 | P44: 6758857 | Q44: SOLD | R44: 0 | S44: 0 | T44: -2027654.1 | U44: =SUM(R44:T44) -> -2027654.1 | V44: 0 | W44: 0 | X44: 0 | Y44: 0 | Z44: 0 | AA44: 0 | AB44: 0 | AC44: 0 | AD44: 0 | AG44: =SUM(U44:AF44) -> -2027654.1 | AI44: 0 | AJ44: =SUM(U44:AE44) -> -2027654.1 | AL44: =+AC44-AI44 -> 0 | AO44: 2018246
A45: =A44+1 -> 42 | B45: KOHINOOR UPTOWN AVENUE | C45: Tower 6-301 | D45: Tower 6 | E45: 301 | F45: 2BHK | G45: 1012 | H45: 653.59 | I45: 723.02 | J45: Mrs. | K45: 2017685 | L45: AKSHADA SUNIL KADAM | M45: GNFPK6654C | N45: 2649/2024 | O45: 45462 | P45: 5741048 | Q45: SOLD | R45: 0 | S45: 0 | T45: -1729725.3 | U45: =SUM(R45:T45) -> -1729725.3 | V45: 0 | W45: 0 | X45: 0 | Y45: 0 | Z45: 0 | AA45: 0 | AB45: 0 | AC45: 0 | AD45: 0 | AG45: =SUM(U45:AF45) -> -1729725.3 | AI45: 0 | AJ45: =SUM(U45:AE45) -> -1729725.3 | AL45: =+AC45-AI45 -> 0 | AO45: 2017685
A46: =A45+1 -> 43 | B46: KOHINOOR UPTOWN AVENUE | C46: Tower 8-2102 | D46: Tower 8 | E46: 2102 | F46: 2BHK | G46: 1114 | H46: 683.3 | I46: 795.57 | J46: Mr. | K46: 2002480 | L46: AKSHAY ADINATH NILAPWAR | M46: AXEPN3198D | N46: 2024//2024 | O46: 45437 | P46: 6248385 | Q46: SOLD | R46: 0 | S46: 0 | T46: -1849515.1 | U46: =SUM(R46:T46) -> -1849515.1 | V46: -25000 | W46: 0 | X46: 0 | Y46: 0 | Z46: 0 | AA46: 0 | AB46: 0 | AC46: 0 | AD46: 0 | AG46: =SUM(U46:AF46) -> -1874515.1 | AI46: 0 | AJ46: =SUM(U46:AE46) -> -1874515.1 | AL46: =+AC46-AI46 -> 0 | AO46: 2002480
A47: =A46+1 -> 44 | B47: KOHINOOR UPTOWN AVENUE | C47: Tower 7-1407 | D47: Tower 7 | E47: 1407 | F47: 2BHK | G47: 1114 | H47: 683.3 | I47: 795.57 | J47: Mr. | K47: 2002317 | L47: AKSHAY BHIM AMBETKAR | M47: BWHPA4249K | N47: 2352/2024 | O47: 45448 | P47: 6320782 | Q47: SOLD | R47: 0 | S47: 0 | T47: -1746234.3 | U47: =SUM(R47:T47) -> -1746234.3 | V47: -150000 | W47: 0 | X47: 0 | Y47: 0 | Z47: 0 | AA47: 0 | AB47: 0 | AC47: 0 | AD47: 0 | AG47: =SUM(U47:AF47) -> -1896234.3 | AI47: 0 | AJ47: =SUM(U47:AE47) -> -1896234.3 | AL47: =+AC47-AI47 -> 0 | AO47: 2002317
A48: =A47+1 -> 45 | B48: KOHINOOR UPTOWN AVENUE | C48: Tower 6-2108 | D48: Tower 6 | E48: 2108 | F48: 2BHK | G48: 1012 | H48: 653.59 | I48: 723.02 | J48: Mr. | K48: 2017695 | L48: AKSHAY SANJAY JOGDAND | M48: AQZPJ0259P | N48: 2732/2024 | O48: 45464 | P48: 5776762 | Q48: SOLD | R48: 0 | S48: 0 | T48: -1733001.6 | U48: =SUM(R48:T48) -> -1733001.6 | V48: 0 | W48: 0 | X48: 0 | Y48: 0 | Z48: 0 | AA48: 0 | AB48: 0 | AC48: 0 | AD48: 0 | AG48: =SUM(U48:AF48) -> -1733001.6 | AI48: 0 | AJ48: =SUM(U48:AE48) -> -1733001.6 | AL48: =+AC48-AI48 -> 0 | AO48: 2017695
A49: =A48+1 -> 46 | B49: KOHINOOR UPTOWN AVENUE | C49: Tower 8-1305 | D49: Tower 8 | E49: 1305 | F49: 2.5BHK | G49: 1265 | H49: 813.33 | I49: 903.31 | J49: Mr. | K49: 2002431 | L49: AKSHAY SHRIRANG VYAS | M49: ARGPV8615H | N49: 2175/2024 | O49: 45441 | P49: 7294572 | Q49: SOLD | R49: 0 | S49: 0 | T49: -2188372.4 | U49: =SUM(R49:T49) -> -2188372.4 | V49: -72945.72 | W49: 0 | X49: 0 | Y49: 0 | Z49: 0 | AA49: 0 | AB49: 0 | AC49: 0 | AD49: 0 | AG49: =SUM(U49:AF49) -> -2261318.1 | AI49: 0 | AJ49: =SUM(U49:AE49) -> -2261318.1 | AL49: =+AC49-AI49 -> 0 | AO49: 2002431
A50: =A49+1 -> 47 | B50: KOHINOOR UPTOWN AVENUE | C50: Tower 2-1702 | D50: Tower 2 | E50: 1702 | F50: 2BHK | G50: 1114 | H50: 683.3 | I50: 795.57 | J50: Mr. | K50: 2020799 | L50: AKSHAY SUDHAKAR DOD | M50: DGGPD8361C | P50: 6736571 | Q50: SOLD | R50: 0 | S50: 0 | T50: -813802 | U50: =SUM(R50:T50) -> -813802 | V50: 0 | W50: 0 | X50: 0 | Y50: 0 | Z50: 0 | AA50: 0 | AB50: 0 | AC50: 0 | AD50: 0 | AG50: =SUM(U50:AF50) -> -813802 | AI50: 0 | AJ50: =SUM(U50:AE50) -> -813802 | AL50: =+AC50-AI50 -> 0 | AO50: 2020799
A51: =A50+1 -> 48 | B51: KOHINOOR UPTOWN AVENUE | C51: Tower 3-1307 | D51: Tower 3 | E51: 1307 | F51: 2BHK | G51: 1114 | H51: 683.3 | I51: 795.57 | J51: Mr. | K51: 2001888 | L51: AMAR ANANDRAO VANJARI | M51: ALALK6454T | N51: 2011/2024 | O51: 45434 | P51: 6320782 | Q51: SOLD | R51: 0 | S51: 0 | T51: -1893852.3 | U51: =SUM(R51:T51) -> -1893852.3 | V51: 0 | W51: 0 | X51: 0 | Y51: 0 | Z51: 0 | AA51: 0 | AB51: 0 | AC51: 0 | AD51: 0 | AG51: =SUM(U51:AF51) -> -1893852.3 | AI51: 0 | AJ51: =SUM(U51:AE51) -> -1893852.3 | AL51: =+AC51-AI51 -> 0 | AO51: 2001888
A52: =A51+1 -> 49 | B52: KOHINOOR UPTOWN AVENUE | C52: Tower 8-802 | D52: Tower 8 | E52: 802 | F52: 2BHK | G52: 1114 | H52: 683.3 | I52: 795.57 | J52: Mrs. | K52: 2002509 | L52: AMARJA MANOHAR HONKAR | M52: ANRPH5641Q | N52: 1703/2024 | O52: 45405 | P52: 6287368 | Q52: SOLD | R52: 0 | S52: 0 | T52: -1933516.2 | U52: =SUM(R52:T52) -> -1933516.2 | V52: 0 | W52: 0 | X52: 0 | Y52: 0 | Z52: 0 | AA52: 0 | AB52: 0 | AC52: -15568.76 | AD52: 0 | AG52: =SUM(U52:AF52) -> -1949084.9 | AI52: 15568.76 | AJ52: =SUM(U52:AE52) -> -1949084.9 | AL52: =+AC52+AI52 -> 0 | AO52: 2002509
A53: =A52+1 -> 50 | B53: KOHINOOR UPTOWN AVENUE | C53: Tower 8-1105 | D53: Tower 8 | E53: 1105 | F53: 3BHK | G53: 1498 | H53: 954.87 | I53: 1069.73 | J53: Mr. | K53: 2015493 | L53: AMEYA SUNIL DANI | M53: FAXPD2918G | N53: 3035/2024 | O53: 45483 | P53: 9169619 | Q53: SOLD | R53: 0 | S53: 0 | T53: -2842581.9 | U53: =SUM(R53:T53) -> -2842581.9 | V53: 0 | W53: 0 | X53: 0 | Y53: 0 | Z53: 0 | AA53: 0 | AB53: 0 | AC53: 0 | AD53: 0 | AG53: =SUM(U53:AF53) -> -2842581.9 | AI53: 0 | AJ53: =SUM(U53:AE53) -> -2842581.9 | AL53: =+AC53-AI53 -> 0 | AO53: 2015493
A54: =A53+1 -> 51 | B54: KOHINOOR UPTOWN AVENUE | C54: Tower 8-1604 | D54: Tower 8 | E54: 1604 | F54: 3BHK | G54: 1498 | H54: 954.87 | I54: 1069.73 | J54: Mr. | K54: 2002450 | L54: AMIT ARUN LONDHE | M54: AHGPL7524H | N54: 2647/2024 | O54: 45462 | P54: 8603809 | Q54: SOLD | R54: 0 | S54: 0 | T54: -2598897.9 | U54: =SUM(R54:T54) -> -2598897.9 | V54: 0 | W54: 0 | X54: 0 | Y54: 0 | Z54: 0 | AA54: 0 | AB54: 0 | AC54: -8055 | AD54: 0 | AG54: =SUM(U54:AF54) -> -2606952.9 | AI54: 8055 | AJ54: =SUM(U54:AE54) -> -2606952.9 | AL54: =+AC54+AI54 -> 0 | AO54: 2002450
A55: =A54+1 -> 52 | B55: KOHINOOR UPTOWN AVENUE | C55: Tower 7-1701 | D55: Tower 7 | E55: 1701 | F55: 2BHK | G55: 1012 | H55: 653.59 | I55: 723.02 | J55: Mr. | K55: 2002333 | L55: AMIT KUMAR GUPTA | M55: AZKPG3199H | N55: 2114/2024 | O55: 45440 | P55: 5729194 | Q55: SOLD | R55: 0 | S55: 0 | T55: -1676050 | U55: =SUM(R55:T55) -> -1676050 | V55: 0 | W55: 0 | X55: 0 | Y55: 0 | Z55: 0 | AA55: 0 | AB55: 0 | AC55: 0 | AD55: 0 | AG55: =SUM(U55:AF55) -> -1676050 | AI55: 0 | AJ55: =SUM(U55:AE55) -> -1676050 | AL55: =+AC55-AI55 -> 0 | AO55: 2002333
A56: =A55+1 -> 53 | B56: KOHINOOR UPTOWN AVENUE | C56: Tower 7-301 | D56: Tower 7 | E56: 301 | F56: 2BHK | G56: 1012 | H56: 653.59 | I56: 723.02 | J56: Mr. | K56: 2002370 | L56: AMIT SUBHASH GADADE | M56: ASVFD1245G | N56: 3488/2024 | O56: 45520 | P56: 5668460 | Q56: SOLD | R56: 0 | S56: 0 | T56: -1598107.1 | U56: =SUM(R56:T56) -> -1598107.1 | V56: 0 | W56: 0 | X56: 0 | Y56: 0 | Z56: 0 | AA56: 0 | AB56: 0 | AC56: -2428.96 | AD56: 0 | AG56: =SUM(U56:AF56) -> -1600536.1 | AI56: 2428.96 | AJ56: =SUM(U56:AE56) -> -1600536.1 | AL56: =+AC56+AI56 -> 8.1854523e-12 | AO56: 2002370
A57: =A56+1 -> 54 | B57: KOHINOOR UPTOWN AVENUE | C57: Tower 4-303 | D57: Tower 4 | E57: 303 | F57: 3BHK | G57: 1787 | H57: 1138.51 | I57: 1276.29 | J57: Mr. | K57: 2002241 | L57: AMIT TUKARAM MANE | M57: AMAPM4498C | N57: 1990/2024 | O57: 45435 | P57: 11088896 | Q57: SOLD | R57: 0 | S57: 0 | T57: -3312381.6 | U57: =SUM(R57:T57) -> -3312381.6 | V57: 0 | W57: 0 | X57: 0 | Y57: 0 | Z57: 0 | AA57: 0 | AB57: 0 | AC57: -14286 | AD57: 0 | AG57: =SUM(U57:AF57) -> -3326667.6 | AI57: 14286 | AJ57: =SUM(U57:AE57) -> -3326667.6 | AL57: =+AC57+AI57 -> 0 | AO57: 2002241
A58: =A57+1 -> 55 | B58: KOHINOOR UPTOWN AVENUE | C58: Tower 7-603 | D58: Tower 7 | E58: 603 | F58: 3BHK | G58: 1375 | H58: 876.73 | I58: 982.22 | J58: Mr. | K58: 2002387 | L58: AMIT VERMA | M58: ANLPV3155F | N58: 2046/2024 | O58: 45436 | P58: 7741819 | Q58: SOLD | R58: 0 | S58: 0 | T58: -2307518.7 | U58: =SUM(R58:T58) -> -2307518.7 | V58: 0 | W58: 0 | X58: 0 | Y58: 0 | Z58: 0 | AA58: 0 | AB58: 0 | AC58: -15026.59 | AD58: 0 | AG58: =SUM(U58:AF58) -> -2322545.3 | AI58: 15027.08 | AJ58: =SUM(U58:AE58) -> -2322545.3 | AL58: =+AC58+AI58 -> 0.49 | AO58: 2002387
A59: =A58+1 -> 56 | B59: KOHINOOR UPTOWN AVENUE | C59: Tower 6-1902 | D59: Tower 6 | E59: 1902 | F59: 2BHK | G59: 1114 | H59: 683.3 | I59: 795.57 | J59: Mr. | K59: 2015487 | L59: AMITKUMAR GOTE | M59: ALVPG8085H | N59: 2499/2024 | O59: 45455 | P59: 6428571 | Q59: SOLD | R59: 0 | S59: 0 | T59: -1928570.4 | U59: =SUM(R59:T59) -> -1928570.4 | V59: 0 | W59: 0 | X59: 0 | Y59: 0 | Z59: 0 | AA59: 0 | AB59: 0 | AC59: 0 | AD59: 0 | AG59: =SUM(U59:AF59) -> -1928570.4 | AI59: 0 | AJ59: =SUM(U59:AE59) -> -1928570.4 | AL59: =+AC59-AI59 -> 0 | AO59: 2015487
A60: =A59+1 -> 57 | B60: KOHINOOR UPTOWN AVENUE | C60: Tower 8-1904 | D60: Tower 8 | E60: 1904 | F60: 3BHK | G60: 1498 | H60: 954.87 | I60: 1069.73 | J60: Mrs. | K60: 2015500 | L60: AMOL MUKUNDRAO AKOLKAR | M60: ANRPA7916P | P60: 8946381 | Q60: CANCELLED | R60: 0 | S60: 0 | T60: 0 | U60: =SUM(R60:T60) -> 0 | V60: 0 | W60: 0 | X60: 0 | Y60: 0 | Z60: 0 | AA60: 0 | AB60: 0 | AC60: 0 | AD60: 0 | AG60: =SUM(U60:AF60) -> 0 | AI60: 0 | AJ60: =SUM(U60:AE60) -> 0 | AL60: =+AC60-AI60 -> 0 | AO60: 2015500
A61: =A60+1 -> 58 | B61: KOHINOOR UPTOWN AVENUE | C61: Tower 7-501 | D61: Tower 7 | E61: 501 | F61: 2BHK | G61: 1012 | H61: 653.59 | I61: 723.02 | J61: Mr. | K61: 2002380 | L61: AMOL VASANTRAO PATIL | M61: AUMPP3757D | N61: 4004/2024 | O61: 45548 | P61: 5642857 | Q61: SOLD | R61: 0 | S61: 0 | T61: -1692858.1 | U61: =SUM(R61:T61) -> -1692858.1 | V61: 0 | W61: 0 | X61: 0 | Y61: 0 | Z61: 0 | AA61: 0 | AB61: 0 | AC61: 0 | AD61: 0 | AG61: =SUM(U61:AF61) -> -1692858.1 | AI61: 0 | AJ61: =SUM(U61:AE61) -> -1692858.1 | AL61: =+AC61-AI61 -> 0 | AO61: 2002380
A62: =A61+1 -> 59 | B62: KOHINOOR UPTOWN AVENUE | C62: Tower 7-401 | D62: Tower 7 | E62: 401 | F62: 2BHK | G62: 1012 | H62: 653.59 | I62: 723.02 | J62: Mrs. | K62: 2002376 | L62: AMRUTA PRASAD NIKAM | M62: BJVPN2088L | N62: 1979/2024 | O62: 45435 | P62: 5668460 | Q62: SOLD | R62: 0 | S62: 0 | T62: -1699899.4 | U62: =SUM(R62:T62) -> -1699899.4 | V62: -51000 | W62: 0 | X62: 0 | Y62: 0 | Z62: 0 | AA62: 0 | AB62: 0 | AC62: -6122 | AD62: 0 | AG62: =SUM(U62:AF62) -> -1757021.4 | AI62: 6122 | AJ62: =SUM(U62:AE62) -> -1757021.4 | AL62: =+AC62+AI62 -> 0 | AO62: 2002376
A63: =A62+1 -> 60 | B63: KOHINOOR UPTOWN AVENUE | C63: Tower 8-103 | D63: Tower 8 | E63: 103 | F63: 3BHK | G63: 1375 | H63: 876.73 | I63: 982.21 | J63: Mrs. | K63: 2017841 | L63: AMRUTA PRATIK LADE | M63: BUGPR4706M | N63: 2005/2024 | O63: 45434 | P63: 8544571 | Q63: SOLD | R63: 0 | S63: 0 | T63: -2563368.4 | U63: =SUM(R63:T63) -> -2563368.4 | V63: 0 | W63: 0 | X63: 0 | Y63: 0 | Z63: 0 | AA63: 0 | AB63: 0 | AC63: 0 | AD63: 0 | AG63: =SUM(U63:AF63) -> -2563368.4 | AI63: 0 | AJ63: =SUM(U63:AE63) -> -2563368.4 | AL63: =+AC63-AI63 -> 0 | AO63: 2017841
A64: =A63+1 -> 61 | B64: KOHINOOR UPTOWN AVENUE | C64: Tower 6-202 | D64: Tower 6 | E64: 202 | F64: 2BHK | G64: 1114 | H64: 683.3 | I64: 795.57 | J64: Mrs. | K64: 2017834 | L64: ANAGHA A PHATAK | M64: CWMPP1011N | N64: 2496/2024 | O64: 45455 | P64: 6330286 | Q64: SOLD | R64: 0 | S64: 0 | T64: -1899085.7 | U64: =SUM(R64:T64) -> -1899085.7 | V64: 0 | W64: 0 | X64: 0 | Y64: 0 | Z64: 0 | AA64: 0 | AB64: 0 | AC64: 0 | AD64: 0 | AG64: =SUM(U64:AF64) -> -1899085.7 | AI64: 0 | AJ64: =SUM(U64:AE64) -> -1899085.7 | AL64: =+AC64-AI64 -> 0 | AO64: 2017834
A65: =A64+1 -> 62 | B65: KOHINOOR UPTOWN AVENUE | C65: Tower 6-2107 | D65: Tower 6 | E65: 2107 | F65: 2BHK | G65: 1114 | H65: 683.3 | I65: 795.57 | J65: Mr. | K65: 2015782 | L65: ANAND ASANGI | M65: BAWPA9065Q | N65: 2954/2024 | O65: 45477 | P65: 6374953 | Q65: SOLD | R65: 0 | S65: 0 | T65: -1872485.7 | U65: =SUM(R65:T65) -> -1872485.7 | V65: -63749.53 | W65: 0 | X65: 0 | Y65: 0 | Z65: 0 | AA65: 0 | AB65: 0 | AC65: 0 | AD65: 0 | AG65: =SUM(U65:AF65) -> -1936235.2 | AI65: 0 | AJ65: =SUM(U65:AE65) -> -1936235.2 | AL65: =+AC65-AI65 -> 0 | AO65: 2015782
A66: =A65+1 -> 63 | B66: KOHINOOR UPTOWN AVENUE | C66: Tower 7-1205 | D66: Tower 7 | E66: 1205 | F66: 3BHK | G66: 1498 | H66: 954.87 | I66: 1069.73 | J66: Mr. | K66: 2015757 | L66: ANIKET DESHMUKH | M66: ATCPD0137A | P66: 9830286 | Q66: CANCELLED | R66: 0 | S66: 0 | T66: 0 | U66: =SUM(R66:T66) -> 0 | V66: 0 | W66: 0 | X66: 0 | Y66: 0 | Z66: 0 | AA66: 0 | AB66: 0 | AC66: 0 | AD66: 0 | AG66: =SUM(U66:AF66) -> 0 | AI66: 0 | AJ66: =SUM(U66:AE66) -> 0 | AL66: =+AC66-AI66 -> 0 | AO66: 2015757
A67: =A66+1 -> 64 | B67: KOHINOOR UPTOWN AVENUE | C67: Tower 6-1507 | D67: Tower 6 | E67: 1507 | F67: 2BHK | G67: 1114 | H67: 683.3 | I67: 795.57 | J67: Mr. | K67: 2017964 | L67: ANIKET RAMESH PAWAR | M67: DENPP3213L | N67: 2432/2024 | O67: 45454 | P67: 6535714 | Q67: SOLD | R67: 0 | S67: 0 | T67: -2026071.4 | U67: =SUM(R67:T67) -> -2026071.4 | V67: 2058750 | W67: 0 | X67: 0 | Y67: 0 | Z67: 0 | AA67: 0 | AB67: 0 | AC67: -98035.72 | AD67: 0 | AG67: =SUM(U67:AF67) -> -65357.14 | AI67: 98035.72 | AJ67: =SUM(U67:AE67) -> -65357.14 | AL67: =+AC67+AI67 -> 0 | AO67: 2017964
A68: =A67+1 -> 65 | B68: KOHINOOR UPTOWN AVENUE | C68: Tower 3-1305 | D68: Tower 3 | E68: 1305 | F68: 2.5BHK | G68: 1265 | H68: 813.33 | I68: 903.31 | J68: Mr. | K68: 2001887 | L68: ANIKET SAMPAT JONDHALE | M68: ATXPJ7267Q | N68: 2359/2024 | O68: 45449 | P68: 7202130 | Q68: SOLD | R68: 0 | S68: 0 | T68: -2128040 | U68: =SUM(R68:T68) -> -2128040 | V68: -49000 | W68: 0 | X68: 0 | Y68: 0 | Z68: 0 | AA68: 0 | AB68: 0 | AC68: -2428 | AD68: 0 | AG68: =SUM(U68:AF68) -> -2179468 | AI68: 2428 | AJ68: =SUM(U68:AE68) -> -2179468 | AL68: =+AC68+AI68 -> 0 | AO68: 2001887
A69: =A68+1 -> 66 | B69: KOHINOOR UPTOWN AVENUE | C69: Tower 1-1801 | D69: Tower 1 | E69: 1801 | F69: 2BHK | G69: 1012 | H69: 653.59 | I69: 723.02 | J69: Ms. | K69: 2018075 | L69: ANIRBAN SARKAR | M69: BHUPS9671R | P69: 6030286 | Q69: CANCELLED | R69: 0 | S69: 0 | T69: -1054989 | U69: =SUM(R69:T69) -> -1054989 | V69: 0 | W69: 0 | X69: 0 | Y69: 0 | Z69: 0 | AA69: 0 | AB69: 0 | AC69: -24361 | AD69: 1079350 | AG69: =SUM(U69:AF69) -> 0 | AI69: 24361 | AJ69: =SUM(U69:AE69) -> 0 | AL69: =+AC69+AI69 -> 0 | AO69: 2018075
A70: =A69+1 -> 67 | B70: KOHINOOR UPTOWN AVENUE | C70: Tower 8-1301 | D70: Tower 8 | E70: 1301 | F70: 2BHK | G70: 1012 | H70: 653.59 | I70: 723.02 | J70: Mr. | K70: 2002428 | L70: ANISH MANSUR NADAF | M70: AQRPN5894N | N70: 2410/2024 | O70: 45454 | P70: 5714010 | Q70: SOLD | R70: 0 | S70: 0 | T70: -1699914.8 | U70: =SUM(R70:T70) -> -1699914.8 | V70: 0 | W70: 0 | X70: 0 | Y70: 0 | Z70: 0 | AA70: 0 | AB70: 0 | AC70: -16715 | AD70: 0 | AG70: =SUM(U70:AF70) -> -1716629.8 | AI70: 16715 | AJ70: =SUM(U70:AE70) -> -1716629.8 | AL70: =+AC70+AI70 -> 0 | AO70: 2002428
A71: =A70+1 -> 68 | B71: KOHINOOR UPTOWN AVENUE | C71: Tower 2-501 | D71: Tower 2 | E71: 501 | F71: 2BHK | G71: 1012 | H71: 653.59 | I71: 723.02 | J71: Mr. | K71: 2018505 | L71: ANISH SANJIV WAGHULDE | M71: AAWPW8994M | P71: 6008857 | Q71: CANCELLED | R71: 0 | S71: 0 | T71: -600700 | U71: =SUM(R71:T71) -> -600700 | V71: 0 | W71: 0 | X71: 0 | Y71: 0 | Z71: 0 | AA71: 0 | AB71: 0 | AC71: 0 | AD71: 600700 | AG71: =SUM(U71:AF71) -> 0 | AI71: 0 | AJ71: =SUM(U71:AE71) -> 0 | AL71: =+AC71+AI71 -> 0 | AO71: 2018505
A72: =A71+1 -> 69 | B72: KOHINOOR UPTOWN AVENUE | C72: Tower 7-204 | D72: Tower 7 | E72: 204 | F72: 2.5BHK | G72: 1265 | H72: 813.33 | I72: 903.31 | J72: Mrs. | K72: 2002361 | L72: ANITA MOHAN DUTT | M72: AFIPD4303A | N72: 2096/2024 | O72: 45443 | P72: 6848191 | Q72: SOLD | R72: 0 | S72: 0 | T72: -2058866.1 | U72: =SUM(R72:T72) -> -2058866.1 | V72: 0 | W72: 0 | X72: 0 | Y72: 0 | Z72: 0 | AA72: 0 | AB72: 0 | AC72: 0 | AD72: 0 | AG72: =SUM(U72:AF72) -> -2058866.1 | AI72: 0 | AJ72: =SUM(U72:AE72) -> -2058866.1 | AL72: =+AC72-AI72 -> 0 | AO72: 2002361
A73: =A72+1 -> 70 | B73: KOHINOOR UPTOWN AVENUE | C73: Tower 3-1501 | D73: Tower 3 | E73: 1501 | F73: 2BHK | G73: 1012 | H73: 653.59 | I73: 723.02 | J73: Mrs. | K73: 2001894 | L73: ANITA VAIJINATH SOMWANSHI | M73: DNMPS5557Q | N73: 1790/2024 | O73: 45429 | P73: 5714010 | Q73: SOLD | R73: 0 | S73: 0 | T73: -1417074.8 | U73: =SUM(R73:T73) -> -1417074.8 | V73: -289986 | W73: 0 | X73: 0 | Y73: 0 | Z73: 0 | AA73: 0 | AB73: 0 | AC73: 0 | AD73: 0 | AG73: =SUM(U73:AF73) -> -1707060.8 | AI73: 0 | AJ73: =SUM(U73:AE73) -> -1707060.8 | AL73: =+AC73-AI73 -> 0 | AO73: 2001894
A74: =A73+1 -> 71 | B74: KOHINOOR UPTOWN AVENUE | C74: Tower 8-1705 | D74: Tower 8 | E74: 1705 | F74: 3BHK | G74: 1498 | H74: 954.87 | I74: 1069.73 | J74: Mr. | K74: 2002457 | L74: ANKIN KIRANBHAI SHAH | M74: CPAPS6438F | N74: 2065/2024 | O74: 45439 | P74: 8607143 | Q74: SOLD | R74: 0 | S74: 0 | T74: -2646697.3 | U74: =SUM(R74:T74) -> -2646697.3 | V74: 0 | W74: 0 | X74: 0 | Y74: 0 | Z74: 0 | AA74: 0 | AB74: 0 | AC74: -21517.8 | AD74: 0 | AG74: =SUM(U74:AF74) -> -2668215.1 | AI74: 21517.8 | AJ74: =SUM(U74:AE74) -> -2668215.1 | AL74: =+AC74+AI74 -> 0 | AO74: 2002457
A75: =A74+1 -> 72 | B75: KOHINOOR UPTOWN AVENUE | C75: Tower 7-1404 | D75: Tower 7 | E75: 1404 | F75: 3BHK | G75: 1498 | H75: 954.87 | I75: 1069.73 | J75: Mr. | K75: 2002315 | L75: ANKIT DUBEY | M75: BFMPD5677N | N75: 2274/2024 | O75: 45446 | P75: 8603809 | Q75: SOLD | R75: 0 | S75: 0 | T75: -2530141.9 | U75: =SUM(R75:T75) -> -2530141.9 | V75: -48572 | W75: 0 | X75: 0 | Y75: 0 | Z75: 0 | AA75: 0 | AB75: 0 | AC75: 0.04 | AD75: 0 | AG75: =SUM(U75:AF75) -> -2578713.8 | AI75: -0.04 | AJ75: =SUM(U75:AE75) -> -2578713.8 | AL75: =+AC75-AI75 -> 0.08 | AO75: 2002315
A76: =A75+1 -> 73 | B76: KOHINOOR UPTOWN AVENUE | C76: Tower 8-1704 | D76: Tower 8 | E76: 1704 | F76: 3BHK | G76: 1498 | H76: 954.87 | I76: 1069.73 | J76: Mr. | K76: 2002456 | L76: ANKIT HIRAMAN UJAGARE | M76: AIZPU3794Q | N76: 0 | P76: 8626273 | Q76: CANCELLED | R76: 0 | S76: 0 | T76: 0 | U76: =SUM(R76:T76) -> 0 | V76: 0 | W76: 0 | X76: 0 | Y76: 0 | Z76: 0 | AA76: 0 | AB76: 0 | AC76: -57348.4 | AD76: 0 | AG76: =SUM(U76:AF76) -> -57348.4 | AI76: 57348.4 | AJ76: =SUM(U76:AE76) -> -57348.4 | AL76: =+AC76+AI76 -> 0 | AO76: 2002456
A77: =A76+1 -> 74 | B77: KOHINOOR UPTOWN AVENUE | C77: Tower 7-1006 | D77: Tower 7 | E77: 1006 | F77: 3BHK | G77: 1375 | H77: 876.73 | I77: 982.22 | J77: Mr. | K77: 2002288 | L77: ANKIT RAVINDRAPPA KALE | M77: FHPPK3209A | N77: 2507/2024 | O77: 45455 | P77: 7741048 | Q77: SOLD | R77: 0 | S77: 0 | T77: -1815170.8 | U77: =SUM(R77:T77) -> -1815170.8 | V77: -500000 | W77: 0 | X77: 0 | Y77: 0 | Z77: 0 | AA77: 0 | AB77: 0 | AC77: 0 | AD77: 0 | AG77: =SUM(U77:AF77) -> -2315170.8 | AI77: 0 | AJ77: =SUM(U77:AE77) -> -2315170.8 | AL77: =+AC77+AI77 -> 0 | AO77: 2002288
A78: =A77+1 -> 75 | B78: KOHINOOR UPTOWN AVENUE | C78: Tower 7-502 | D78: Tower 7 | E78: 502 | F78: 2BHK | G78: 1114 | H78: 683.3 | I78: 795.57 | J78: Mr. | K78: 2002381 | L78: ANKIT SUJANTEE | M78: EFSPS2152Q | N78: 2236/2024 | O78: 45443 | P78: 6287368 | Q78: CANCELLED | R78: 0 | S78: 0 | T78: -1674595.3 | U78: =SUM(R78:T78) -> -1674595.3 | V78: 0 | W78: 0 | X78: 0 | Y78: 0 | Z78: 0 | AA78: 0 | AB78: 0 | AC78: -101452.52 | AD78: 1737469 | AG78: =SUM(U78:AF78) -> -38578.84 | AI78: 101452.52 | AJ78: =SUM(U78:AE78) -> -38578.84 | AL78: =+AC78+AI78 -> -2.6193447e-10 | AO78: 2002381
A79: =A78+1 -> 76 | B79: KOHINOOR UPTOWN AVENUE | C79: Tower 3-1003 | D79: Tower 3 | E79: 1003 | F79: 3BHK | G79: 1375 | H79: 876.73 | I79: 982.22 | J79: Mr. | K79: 2019137 | L79: ANKIT SUNIL PATIL | M79: DDVPP8923A | N79: 2648/2024 | O79: 45462 | P79: 7678571 | Q79: SOLD | R79: 0 | S79: 0 | T79: -2303571.1 | U79: =SUM(R79:T79) -> -2303571.1 | V79: 0 | W79: 0 | X79: 0 | Y79: 0 | Z79: 0 | AA79: 0 | AB79: 0 | AC79: 0 | AD79: 0 | AG79: =SUM(U79:AF79) -> -2303571.1 | AI79: 0 | AJ79: =SUM(U79:AE79) -> -2303571.1 | AL79: =+AC79-AI79 -> 0 | AO79: 2019137
A80: =A79+1 -> 77 | B80: KOHINOOR UPTOWN AVENUE | C80: Tower 8-906 | D80: Tower 8 | E80: 906 | F80: 3BHK | G80: 1375 | H80: 876.73 | I80: 982.22 | J80: Mr. | K80: 2002518 | L80: ANKUR PRAVIN KOTHAWADE | M80: JNVPK5303K | N80: 1969/2024 | O80: 45435 | P80: 7762445 | Q80: SOLD | R80: 0 | S80: 0 | T80: -2399213.3 | U80: =SUM(R80:T80) -> -2399213.3 | V80: 0 | W80: 0 | X80: 0 | Y80: 0 | Z80: 0 | AA80: 0 | AB80: 0 | AC80: -7142 | AD80: 0 | AG80: =SUM(U80:AF80) -> -2406355.3 | AI80: 7142 | AJ80: =SUM(U80:AE80) -> -2406355.3 | AL80: =+AC80+AI80 -> 0 | AO80: 2002518
A81: =A80+1 -> 78 | B81: KOHINOOR UPTOWN AVENUE | C81: Tower 2-804 | D81: Tower 2 | E81: 804 | F81: 2.5BHK | G81: 1265 | H81: 813.33 | I81: 903.31 | J81: Mr. | K81: 2020284 | L81: ANOOP TIWARI | M81: AQJPT9936D | P81: 7830286 | Q81: CANCELLED | R81: 0 | S81: 0 | T81: -100000 | U81: =SUM(R81:T81) -> -100000 | V81: 100000 | W81: 0 | X81: 0 | Y81: 0 | Z81: 0 | AA81: 0 | AB81: 0 | AC81: 0 | AD81: 0 | AG81: =SUM(U81:AF81) -> 0 | AI81: 0 | AJ81: =SUM(U81:AE81) -> 0 | AL81: =+AC81-AI81 -> 0 | AO81: 2020284
A82: =A81+1 -> 79 | B82: KOHINOOR UPTOWN AVENUE | C82: Tower 7-1004 | D82: Tower 7 | E82: 1004 | F82: 3BHK | G82: 1498 | H82: 954.87 | I82: 1069.73 | J82: Mr. | K82: 2002287 | L82: ANSHUL KUMAR MENDHIRATTA | M82: BFZPM4528J | N82: 0 | P82: 8581345 | Q82: CANCELLED | R82: 0 | S82: 0 | T82: 31678 | U82: =SUM(R82:T82) -> 31678 | V82: 0 | W82: 0 | X82: 0 | Y82: 0 | Z82: 0 | AA82: 0 | AB82: 0 | AC82: -70499 | AD82: 0 | AG82: =SUM(U82:AF82) -> -38821 | AI82: 70499 | AJ82: =SUM(U82:AE82) -> -38821 | AL82: =+AC82+AI82 -> 0 | AO82: 2002287
A83: =A82+1 -> 80 | B83: KOHINOOR UPTOWN AVENUE | C83: Tower 6-807 | D83: Tower 6 | E83: 807 | F83: 2BHK | G83: 1114 | H83: 683.3 | I83: 795.57 | J83: Mrs. | K83: 2002279 | L83: ANU RANI | M83: ASDFG2415J | N83: 2018/2024 | O83: 45436 | P83: 6357142 | Q83: SOLD | R83: 0 | S83: 0 | T83: -1907142.9 | U83: =SUM(R83:T83) -> -1907142.9 | V83: 0 | W83: 0 | X83: 0 | Y83: 0 | Z83: 0 | AA83: 0 | AB83: 0 | AC83: 0 | AD83: 0 | AG83: =SUM(U83:AF83) -> -1907142.9 | AI83: 0 | AJ83: =SUM(U83:AE83) -> -1907142.9 | AL83: =+AC83-AI83 -> 0 | AO83: 2002279
A84: =A83+1 -> 81 | B84: KOHINOOR UPTOWN AVENUE | C84: Tower 7-1707 | D84: Tower 7 | E84: 1707 | F84: 2BHK | G84: 1114 | H84: 683.3 | I84: 795.57 | J84: Mr. | K84: 2002337 | L84: ANUJ SANTOSH TUNDALWAR | M84: BKAPT8899R | N84: 1837/2024 | O84: 45429 | P84: 6491048 | Q84: SOLD | R84: 0 | S84: 0 | T84: -2012226.3 | U84: =SUM(R84:T84) -> -2012226.3 | V84: 0 | W84: 0 | X84: 0 | Y84: 0 | Z84: 0 | AA84: 0 | AB84: 0 | AC84: 0.4 | AD84: 0 | AG84: =SUM(U84:AF84) -> -2012225.9 | AI84: -0.4 | AJ84: =SUM(U84:AE84) -> -2012225.9 | AL84: =+AC84+AI84 -> 0 | AO84: 2002337
A85: =A84+1 -> 82 | B85: KOHINOOR UPTOWN AVENUE | C85: Tower 6-608 | D85: Tower 6 | E85: 608 | F85: 2BHK | G85: 1012 | H85: 653.59 | I85: 723.02 | J85: Mr. | K85: 2019061 | L85: ANUKUL SURYABHAN BANSOD | M85: BZVPB0898Q | N85: 2374/2024 | O85: 45449 | P85: 5776762 | Q85: SOLD | R85: 0 | S85: 0 | T85: -1790794.2 | U85: =SUM(R85:T85) -> -1790794.2 | V85: 0 | W85: 0 | X85: 0 | Y85: 0 | Z85: 0 | AA85: 0 | AB85: 0 | AC85: 0 | AD85: 0 | AG85: =SUM(U85:AF85) -> -1790794.2 | AI85: 0 | AJ85: =SUM(U85:AE85) -> -1790794.2 | AL85: =+AC85-AI85 -> 0 | AO85: 2019061
A86: =A85+1 -> 83 | B86: KOHINOOR UPTOWN AVENUE | C86: Tower 7-607 | D86: Tower 7 | E86: 607 | F86: 2BHK | G86: 1114 | H86: 683.3 | I86: 795.57 | J86: Mr. | K86: 2002389 | L86: ANUP DIPAK AGARWAL | M86: BRCPA1210L | N86: 2427/2024 | O86: 45454 | P86: 6287368 | Q86: SOLD | R86: 0 | S86: 0 | T86: -1785563.2 | U86: =SUM(R86:T86) -> -1785563.2 | V86: -130776 | W86: 0 | X86: 0 | Y86: 0 | Z86: 0 | AA86: 0 | AB86: 0 | AC86: 0 | AD86: 0 | AG86: =SUM(U86:AF86) -> -1916339.2 | AI86: 0 | AJ86: =SUM(U86:AE86) -> -1916339.2 | AL86: =+AC86-AI86 -> 0 | AO86: 2002389
A87: =A86+1 -> 84 | B87: KOHINOOR UPTOWN AVENUE | C87: Tower 7-203 | D87: Tower 7 | E87: 203 | F87: 3BHK | G87: 1375 | H87: 876.73 | I87: 982.22 | J87: Mr. | K87: 2002360 | L87: ANUP MADGHE | M87: JHGFD4567T | N87: 0 | P87: 7377417 | Q87: CANCELLED | R87: 0 | S87: 0 | T87: 0 | U87: =SUM(R87:T87) -> 0 | V87: 0 | W87: 0 | X87: 0 | Y87: 0 | Z87: 0 | AA87: 0 | AB87: 0 | AC87: 0 | AD87: 0 | AG87: =SUM(U87:AF87) -> 0 | AI87: 0 | AJ87: =SUM(U87:AE87) -> 0 | AL87: =+AC87-AI87 -> 0 | AO87: 2002360
A88: =A87+1 -> 85 | B88: KOHINOOR UPTOWN AVENUE | C88: Tower 3-1805 | D88: Tower 3 | E88: 1805 | F88: 2.5BHK | G88: 1265 | H88: 813.33 | I88: 903.31 | J88: Mr. | K88: 2002185 | L88: ANUP NANDAKUMAR RANAWARE | M88: ANRPR1148J | N88: 2249/2024 | O88: 45443 | P88: 7160667 | Q88: SOLD | R88: 0 | S88: 0 | T88: -2219806.7 | U88: =SUM(R88:T88) -> -2219806.7 | V88: 0 | W88: 0 | X88: 0 | Y88: 0 | Z88: 0 | AA88: 0 | AB88: 0 | AC88: 0 | AD88: 0 | AG88: =SUM(U88:AF88) -> -2219806.7 | AI88: 0 | AJ88: =SUM(U88:AE88) -> -2219806.7 | AL88: =+AC88-AI88 -> 0 | AO88: 2002185
A89: =A88+1 -> 86 | B89: KOHINOOR UPTOWN AVENUE | C89: Tower 7-801 | D89: Tower 7 | E89: 801 | F89: 2BHK | G89: 1012 | H89: 653.59 | I89: 723.02 | J89: Mrs. | K89: 2002397 | L89: ANURADHA RAHUL DONGARE | M89: BUPDH0506P | N89: 2010/2024 | O89: 45437 | P89: 5683644 | Q89: SOLD | R89: 0 | S89: 0 | T89: -1702664.3 | U89: =SUM(R89:T89) -> -1702664.3 | V89: 0 | W89: 0 | X89: 0 | Y89: 0 | Z89: 0 | AA89: 0 | AB89: 0 | AC89: -2429 | AD89: 0 | AG89: =SUM(U89:AF89) -> -1705093.3 | AI89: 2429 | AJ89: =SUM(U89:AE89) -> -1705093.3 | AL89: =+AC89+AI89 -> 0 | AO89: 2002397
A90: =A89+1 -> 87 | B90: KOHINOOR UPTOWN AVENUE | C90: Tower 4-1104 | D90: Tower 4 | E90: 1104 | F90: 3BHK | G90: 1787 | H90: 1138.51 | I90: 1276.29 | J90: Mrs. | K90: 2018927 | L90: ANURADHA RAVINDRAKUMAR SHINDE | M90: EUPPS0386L | N90: 4388/2024 | O90: 45580 | P90: 11936857 | Q90: SOLD | R90: 0 | S90: 0 | T90: -3700424.7 | U90: =SUM(R90:T90) -> -3700424.7 | V90: 0 | W90: 0 | X90: 0 | Y90: 0 | Z90: 0 | AA90: 0 | AB90: 0 | AC90: 0 | AD90: 0 | AG90: =SUM(U90:AF90) -> -3700424.7 | AI90: 0 | AJ90: =SUM(U90:AE90) -> -3700424.7 | AL90: =+AC90-AI90 -> 0 | AO90: 2018927
A91: =A90+1 -> 88 | B91: KOHINOOR UPTOWN AVENUE | C91: Tower 6-1904 | D91: Tower 6 | E91: 1904 | F91: 2BHK | G91: 1498 | H91: 954.87 | I91: 1069.73 | J91: Mr. | K91: 2018112 | L91: ANURAG DOSHI | M91: AUVPD9557A | N91: 2892/2024 | O91: 45474 | P91: 8991048 | Q91: SOLD | R91: 0 | S91: 0 | T91: -2787223.3 | U91: =SUM(R91:T91) -> -2787223.3 | V91: 0 | W91: 0 | X91: 0 | Y91: 0 | Z91: 0 | AA91: 0 | AB91: 0 | AC91: 0 | AD91: 0 | AG91: =SUM(U91:AF91) -> -2787223.3 | AI91: 0 | AJ91: =SUM(U91:AE91) -> -2787223.3 | AL91: =+AC91-AI91 -> 0 | AO91: 2018112
A92: =A91+1 -> 89 | B92: KOHINOOR UPTOWN AVENUE | C92: Tower 3-2105 | D92: Tower 3 | E92: 2105 | F92: 3BHK | G92: 1498 | H92: 954.87 | I92: 1069.73 | J92: Mr. | K92: 2002200 | L92: ANURAG MISHRA | M92: CBFPM5734D | N92: 0 | P92: 8506464 | Q92: CANCELLED | R92: 0 | S92: 0 | T92: 0 | U92: =SUM(R92:T92) -> 0 | V92: 0 | W92: 0 | X92: 0 | Y92: 0 | Z92: 0 | AA92: 0 | AB92: 0 | AC92: 0 | AD92: 0 | AG92: =SUM(U92:AF92) -> 0 | AI92: 0 | AJ92: =SUM(U92:AE92) -> 0 | AL92: =+AC92-AI92 -> 0 | AO92: 2002200
A93: =A92+1 -> 90 | B93: KOHINOOR UPTOWN AVENUE | C93: Tower 5-1503 | D93: Tower 5 | E93: 1503 | F93: 3BHK | G93: 1498 | H93: 954.87 | I93: 1069.73 | J93: Mrs. | K93: 2017316 | L93: ANUSAYA NARAYAN BHARATI | M93: BOAPB2087R | N93: 4688/2024 | O93: 45629 | P93: 8955333 | Q93: SOLD | R93: 0 | S93: 0 | T93: -2621370.5 | U93: =SUM(R93:T93) -> -2621370.5 | V93: -80000 | W93: 0 | X93: 0 | Y93: 0 | Z93: 0 | AA93: 0 | AB93: 0 | AC93: -15227.5 | AD93: 0 | AG93: =SUM(U93:AF93) -> -2716598 | AI93: 15227.5 | AJ93: =SUM(U93:AE93) -> -2716598 | AL93: =+AC93+AI93 -> 0 | AO93: 2017316
A94: =A93+1 -> 91 | B94: KOHINOOR UPTOWN AVENUE | C94: Tower 3-404 | D94: Tower 3 | E94: 404 | F94: 2.5BHK | G94: 1265 | H94: 813.33 | I94: 903.31 | J94: Ms. | K94: 2015492 | L94: APURVA A DHAWALE | M94: AXDPD2044H | N94: 3025/2024 | O94: 45483 | P94: 7116000 | Q94: SOLD | R94: 0 | S94: 0 | T94: -2205960 | U94: =SUM(R94:T94) -> -2205960 | V94: 0 | W94: 0 | X94: 0 | Y94: 0 | Z94: 0 | AA94: 0 | AB94: 0 | AC94: 0 | AD94: 0 | AG94: =SUM(U94:AF94) -> -2205960 | AI94: 0 | AJ94: =SUM(U94:AE94) -> -2205960 | AL94: =+AC94-AI94 -> 0 | AO94: 2015492
A95: =A94+1 -> 92 | B95: KOHINOOR UPTOWN AVENUE | C95: Tower 7-2001 | D95: Tower 7 | E95: 2001 | F95: 2BHK | G95: 1012 | H95: 653.59 | I95: 723.02 | J95: Mrs. | K95: 2002353 | L95: ARATI INDRAJIT GAIKWAD | M95: BFMPG3285D | N95: 1863/2024 | O95: 45435 | P95: 5705333 | Q95: SOLD | R95: 0 | S95: 0 | T95: -1561600 | U95: =SUM(R95:T95) -> -1561600 | V95: -150000 | W95: 0 | X95: 0 | Y95: 0 | Z95: 0 | AA95: 0 | AB95: 0 | AC95: 0 | AD95: 0 | AG95: =SUM(U95:AF95) -> -1711600 | AI95: 0 | AJ95: =SUM(U95:AE95) -> -1711600 | AL95: =+AC95-AI95 -> 0 | AO95: 2002353
A96: =A95+1 -> 93 | B96: KOHINOOR UPTOWN AVENUE | C96: Tower 7-304 | D96: Tower 7 | E96: 304 | F96: 2.5BHK | G96: 1265 | H96: 813.33 | I96: 903.31 | J96: Mrs. | K96: 2015601 | L96: ARCHANA SINGH | M96: CCCPS2881R | N96: 3720/2024 | O96: 45533 | P96: 6937428 | Q96: SOLD | R96: 0 | S96: 0 | T96: -2150603.6 | U96: =SUM(R96:T96) -> -2150603.6 | V96: 0 | W96: 0 | X96: 0 | Y96: 0 | Z96: 0 | AA96: 0 | AB96: 0 | AC96: 0 | AD96: 0 | AG96: =SUM(U96:AF96) -> -2150603.6 | AI96: 0 | AJ96: =SUM(U96:AE96) -> -2150603.6 | AL96: =+AC96-AI96 -> 0 | AO96: 2015601
A97: =A96+1 -> 94 | B97: KOHINOOR UPTOWN AVENUE | C97: Tower 8-1607 | D97: Tower 8 | E97: 1607 | F97: 2BHK | G97: 1114 | H97: 683.3 | I97: 795.57 | J97: Ms. | K97: 2002451 | L97: ARCHI UPADHYAY | M97: ADZPU3652N | N97: 2192/2024 | O97: 45442 | P97: 6320782 | Q97: SOLD | R97: 0 | S97: 0 | T97: -1889092.1 | U97: =SUM(R97:T97) -> -1889092.1 | V97: 0 | W97: 0 | X97: 0 | Y97: 0 | Z97: 0 | AA97: 0 | AB97: 0 | AC97: -7143 | AD97: 0 | AG97: =SUM(U97:AF97) -> -1896235.1 | AI97: 7143 | AJ97: =SUM(U97:AE97) -> -1896235.1 | AL97: =+AC97+AI97 -> 0 | AO97: 2002451
A98: =A97+1 -> 95 | B98: KOHINOOR UPTOWN AVENUE | C98: Tower 8-2004 | D98: Tower 8 | E98: 2004 | F98: 3BHK | G98: 1498 | H98: 954.87 | I98: 1069.73 | J98: Mr. | K98: 2002475 | L98: ARIF AJAMUDDIN DESAI | M98: AONPD2209P | N98: 2072/2024 | O98: 45439 | P98: 8626273 | Q98: SOLD | R98: 0 | S98: 0 | T98: -2788156.5 | U98: =SUM(R98:T98) -> -2788156.5 | V98: -150000 | W98: 0 | X98: 0 | Y98: 0 | Z98: 0 | AA98: 0 | AB98: 0 | AC98: -28846 | AD98: 0 | AG98: =SUM(U98:AF98) -> -2967002.5 | AI98: 28846 | AJ98: =SUM(U98:AE98) -> -2967002.5 | AL98: =+AC98+AI98 -> 0 | AO98: 2002475
A99: =A98+1 -> 96 | B99: KOHINOOR UPTOWN AVENUE | C99: Tower 7-1905 | D99: Tower 7 | E99: 1905 | F99: 3BHK | G99: 1498 | H99: 954.87 | I99: 1069.73 | J99: Mr. | K99: 2017783 | L99: ARIJIT BANDYOPADHYAY | M99: AAOPB4061E | N99: 2759/2024 | O99: 45467 | P99: 8633905 | Q99: SOLD | R99: 0 | S99: 0 | T99: -2590171.4 | U99: =SUM(R99:T99) -> -2590171.4 | V99: 0 | W99: 0 | X99: 0 | Y99: 0 | Z99: 0 | AA99: 0 | AB99: 0 | AC99: 0 | AD99: 0 | AG99: =SUM(U99:AF99) -> -2590171.4 | AI99: 0 | AJ99: =SUM(U99:AE99) -> -2590171.4 | AL99: =+AC99-AI99 -> 0 | AO99: 2017783
A100: =A99+1 -> 97 | B100: KOHINOOR UPTOWN AVENUE | C100: Tower 8-904 | D100: Tower 8 | E100: 904 | F100: 3BHK | G100: 1498 | H100: 954.87 | I100: 1069.73 | J100: Mr. | K100: 2021224 | L100: ARPIT JAIN | M100: AMCPJ0197R | N100: 2169/2025 | O100: 45744 | P100: 9124952 | Q100: SOLD | R100: 0 | S100: 0 | T100: -812120.72 | U100: =SUM(R100:T100) -> -812120.72 | V100: -1952740.9 | W100: 0 | X100: 0 | Y100: 0 | Z100: 0 | AA100: 0 | AB100: 0 | AC100: 0 | AD100: 0 | AG100: =SUM(U100:AF100) -> -2764861.6 | AI100: 0 | AJ100: =SUM(U100:AE100) -> -2764861.6 | AL100: =+AC100-AI100 -> 0 | AO100: 2021224
...

Sheet Customer
B2: Company Code | C2: G/L Account | D2: BS type | E2: G/L Acct Long Text | F2: Balance Carryforward | G2: Debit Blnce of Reportng Period | H2: Credit Balance Reporting Per. | I2: Accumulated Balance
B3: 1900 | C3: 10500001 | D3: Assets | E3: Domestic Customers - Basic & Infra | F3: 8.3513225e+08 | G3: 82317594 | H3: 53683313 | I3: 8.6376653e+08
B4: 1900 | C4: 10500002 | D4: Assets | E4: Domestic Customers - GST | F4: 45177027 | G4: 3583960.8 | H4: 1842689.6 | I4: 46918298
B5: 1900 | C5: 10500003 | D5: Assets | E5: Domestic Customers - SDR | F5: -22777476 | G5: 22831301 | H5: 24576201 | I5: -24522376
B6: 1900 | C6: 10500009 | D6: Assets | E6: Domestic Customers | F6: 2.611514e+08 | G6: 2.4050037e+08 | H6: 3.3088872e+08 | I6: 1.7076304e+08
B7: 1900 | C7: 10500100 | D7: Assets | E7: Customer-Others | F7: 0 | G7: 2319592.6 | H7: 2319592.6 | I7: 0
B8: 1900 | C8: 20710001 | D8: Liabilities | E8: Customer - Advance Taken | F8: -1.1499424e+09 | G8: 1.1884096e+08 | H8: 48909539 | I8: -1.080011e+09
B9: 1900 | C9: 20710003 | D9: Liabilities | E9: Customer - Tax on Advance | F9: -56136700 | G9: 8725600.4 | H9: 3068424.9 | I9: -50479525
B10: 1900 | C10: 20710011 | D10: Liabilities | E10: Customer - EOI / Token | F10: -8849234.8 | G10: 57432076 | H10: 57104448 | I10: -8521606.7
B11: 1900 | C11: 20710013 | D11: Liabilities | E11: Customer - Tax on EOI | F11: 2358044.8 | G11: 1238084.8 | H11: 2411164.9 | I11: 1184964.7
B12: 1900 | C12: 20710015 | D12: Liabilities | E12: Customer - SDR Advance | F12: 13298862 | G12: 58336400 | H12: 50087718 | I12: 21547544
B13: 1900 | C13: 20710016 | D13: Liabilities | E13: Customer - Maintenance Advance | F13: -600 | G13: 0 | H13: 0 | I13: -600
B14: 1900 | C14: 20710019 | D14: Liabilities | E14: Customer - Refund EOI & Advance | F14: 79000 | G14: 1.0977475e+08 | H14: 1.2127158e+08 | I14: -11417835
... B16: 1900 | C16: 20710101 | D16: Liabilities | E16: Customer - Due | F16: -1.2854945e+09 | G16: 1.1376662e+08 | H16: 1.1941114e+08 | I16: -1.291139e+09
F17: =SUM(F3:F16) -> -1.3653798e+09 | I17: =SUM(I3:I16) -> -1.3619116e+09
B18: 1900 | C18: 20490001 | D18: Liabilities | E18: Customer Suspense | F18: -3862156.7 | G18: 12417810 | H18: 10070752 | I18: -1515098.7
F19: =F17+F18 -> -1.369242e+09
F21: 1.369242e+09
F22: =F19+F21 -> 0

Sheet SAP Cross Check
B2: Amounts as per SAP | D2: BS PL Amounts | E2: Difference | F2: Reasons | H2: Final Difference
A4: Row Labels | B4: Sum of Accumulated Balance | F4: There are 3 branch balances in TB: - Interbranch Transaction Cr 71,20,22,472 (SAP Assets) (Our BS Liab) - Branch Ho-Liablities Cr 72,86,681 (SAP Liab) (Our BS Liab) - Branch-Ho-Assets Dr 72,56,064 (SAP Assets) (Our BS Liab) So, Difference is coming due to change in classification, SAP Assets > Our BS Liability | G4: DTA entry yet to be passed in SAP
A5: Assets | B5: 3.2045034e+09 | D5: =BS!F32 -> 2.9976385e+09 | E5: =B5-D5 -> 2.0686486e+08 | F5: =Notes!D53+Notes!D55 -> 3.6663816e+08 | G5: ='Dep & DTA DTL'!C35 -> 1909.5925 | H5: =SUM(E5:G5) -> 5.7350493e+08
A6: Expenses | B6: 2.8473134e+08 | D6: =SUM(PL!G15:G21)+PL!G37 -> 2.4584805e+08 | E6: =B6-D6 -> 38883289 | G6: =-'Dep & DTA DTL'!C35 -> -1909.5925 | H6: =SUM(E6:G6) -> 38881380
A7: Income | B7: -3265123.6 | D7: =PL!G12 -> 3.6617165e+08 | E7: =B7+D7 -> 362906530 | H7: =SUM(E7:G7) -> 362906530
A8: Liabilities | B8: -3.4859696e+09 | D8: =D5-PL!G47 -> 2.8773149e+09 | E8: =B8+D8 -> -6.0865468e+08 | F8: =-Notes!D53-Notes!D55 -> -3.6663816e+08 | H8: =SUM(E8:G8) -> -9.7529284e+08
A9: (blank) | B9: 0
A10: Grand Total | B10: 0

Sheet Raw TB_26.04.2026 (SAP Paste)
A4: Copy Paste SAP TB here under the same headings | F4: =+SUBTOTAL(9,F6:F207) -> -1.3176543e+09 | G4: =+SUBTOTAL(9,G6:G207) -> 0 | H4: =+SUBTOTAL(9,H6:H207) -> 8.0161269e+08 | I4: =+SUBTOTAL(9,I6:I207) -> 2.2711824e+08 | J4: =+SUBTOTAL(9,J6:J207) -> -7.4315988e+08 | L4: If error means Ledger Heading not present in TB (Input)
A5: CoCd | B5: G/L Acct | C5: G/L Acct Long Text | D5: Crcy | E5: BusA | F5: Balance Carryforward | G5: Balance of Prior Periods | H5: Debit Blnce of Reportng Period | I5: Credit Balance Reporting Per. | J5: Accumulated Balance | L5: Cross Check | O5: As per TB 16.05.2026 | P5: Diff | R5: As per TB 22.05.2026 | S5: Diff-2
A6: 1900 | B6: 10000070 | C6: Office Equipments | D6: INR | F6: 54811 | G6: 0 | H6: 0 | I6: 0 | J6: 54811 | L6: =IFERROR(VLOOKUP(C6,'TB_31.03.2026 (Links)'!$D:$H,5,0)-J6,"Error") -> 0 | O6: 54811 | P6: =+J6-O6 -> 0 | R6: =VLOOKUP(B6,[2]Sheet1!$B:$J,9,0) -> 54811 | S6: =J6-R6 -> 0
A7: 1900 | B7: 10001070 | C7: Accumulated Dep - Office Equipments | D7: INR | F7: -22469.87 | G7: 0 | H7: 0 | I7: 14576.15 | J7: -37046.02 | L7: =IFERROR(VLOOKUP(C7,'TB_31.03.2026 (Links)'!$D:$H,5,0)-J7,"Error") -> 0 | O7: -37046.02 | P7: =+J7-O7 -> 0 | R7: =VLOOKUP(B7,[2]Sheet1!$B:$J,9,0) -> -37046.02 | S7: =J7-R7 -> 0
A8: 1900 | B8: 10320101 | C8: FD - Investment in Fixed Deposit | D8: INR | F8: 1000000 | G8: 0 | H8: 2.0040348e+08 | I8: 1.6640348e+08 | J8: 35000000 | L8: =IFERROR(VLOOKUP(C8,'TB_31.03.2026 (Links)'!$D:$H,5,0)-J8,"Error") -> 0 | O8: 35000000 | P8: =+J8-O8 -> 0 | R8: =VLOOKUP(B8,[2]Sheet1!$B:$J,9,0) -> 35000000 | S8: =J8-R8 -> 0
A9: 1900 | B9: 10320102 | C9: FD - Investment in Fixed Deposit Receivable | D9: INR | F9: 0 | G9: 0 | H9: 1.6622784e+08 | I9: 1.6622784e+08 | J9: 0 | L9: =IFERROR(VLOOKUP(C9,'TB_31.03.2026 (Links)'!$D:$H,5,0)-J9,"Error") -> 0 | O9: 0 | P9: =+J9-O9 -> 0 | R9: =VLOOKUP(B9,[2]Sheet1!$B:$J,9,0) -> 0 | S9: =J9-R9 -> 0
A10: 1900 | B10: 10400101 | C10: Capital WIP | D10: INR | F10: 2.8127656e+09 | G10: 0 | H10: 0 | I10: 0 | J10: 2.8127656e+09 | L10: =IFERROR(VLOOKUP(C10,'TB_31.03.2026 (Links)'!$D:$H,5,0)-J10,"Error") -> 0 | O10: 2.8127656e+09 | P10: =+J10-O10 -> 0 | R10: =VLOOKUP(B10,[2]Sheet1!$B:$J,9,0) -> 2.8127656e+09 | S10: =J10-R10 -> 0
A11: 1900 | B11: 10500001 | C11: Domestic Customers - Basic & Infra | D11: INR | F11: 8.3513225e+08 | G11: 0 | H11: 82317594 | I11: 53683313 | J11: 8.6376653e+08 | L11: =IFERROR(VLOOKUP(C11,'TB_31.03.2026 (Links)'!$D:$H,5,0)-J11,"Error") -> 0 | O11: 8.6376653e+08 | P11: =+J11-O11 -> 0 | R11: =VLOOKUP(B11,[2]Sheet1!$B:$J,9,0) -> 8.5986388e+08 | S11: =J11-R11 -> 3902658
A12: 1900 | B12: 10500002 | C12: Domestic Customers - GST | D12: INR | F12: 45177027 | G12: 0 | H12: 3583960.8 | I12: 1842689.6 | J12: 46918298 | L12: =IFERROR(VLOOKUP(C12,'TB_31.03.2026 (Links)'!$D:$H,5,0)-J12,"Error") -> 0 | O12: 46918298 | P12: =+J12-O12 -> 0 | R12: =VLOOKUP(B12,[2]Sheet1!$B:$J,9,0) -> 46723165 | S12: =J12-R12 -> 195132.9
A13: 1900 | B13: 10500003 | C13: Domestic Customers - SDR | D13: INR | F13: -22777476 | G13: 0 | H13: 22831301 | I13: 24576201 | J13: -24522376 | L13: =IFERROR(VLOOKUP(C13,'TB_31.03.2026 (Links)'!$D:$H,5,0)-J13,"Error") -> 0 | O13: -24522376 | P13: =+J13-O13 -> 0 | R13: =VLOOKUP(B13,[2]Sheet1!$B:$J,9,0) -> -24522376 | S13: =J13-R13 -> 0
A14: 1900 | B14: 10500009 | C14: Domestic Customers | D14: INR | F14: 2.611514e+08 | G14: 0 | H14: 2.4050037e+08 | I14: 3.3088872e+08 | J14: 1.7076304e+08 | L14: =IFERROR(VLOOKUP(C14,'TB_31.03.2026 (Links)'!$D:$H,5,0)-J14,"Error") -> 0 | O14: 1.7076304e+08 | P14: =+J14-O14 -> 0 | R14: =VLOOKUP(B14,[2]Sheet1!$B:$J,9,0) -> 1.7076304e+08 | S14: =J14-R14 -> 0
A15: 1900 | B15: 10500100 | C15: Customer-Others | D15: INR | F15: 0 | G15: 0 | H15: 2319592.6 | I15: 2319592.6 | J15: 0 | L15: =IFERROR(VLOOKUP(C15,'TB_31.03.2026 (Links)'!$D:$H,5,0)-J15,"Error") -> 0 | O15: 0 | P15: =+J15-O15 -> 0 | R15: =VLOOKUP(B15,[2]Sheet1!$B:$J,9,0) -> 0 | S15: =J15-R15 -> 0
A16: 1900 | B16: 10900002 | C16: TDS on Sale of Residential Property 1 % Receivable | D16: INR | F16: 29382877 | G16: 0 | H16: 5080952.9 | I16: 171474.45 | J16: 34292355 | L16: =IFERROR(VLOOKUP(C16,'TB_31.03.2026 (Links)'!$D:$H,5,0)-J16,"Error") -> 0 | O16: 34292355 | P16: =+J16-O16 -> 0 | R16: =VLOOKUP(B16,[2]Sheet1!$B:$J,9,0) -> 34292355 | S16: =J16-R16 -> 0
A17: 1900 | B17: 10900102 | C17: TDS on Sale of Commercial Property 1 % Rece- 194IA | D17: INR | F17: 0 | G17: 0 | H17: 87116.7 | I17: 87116.7 | J17: 0 | L17: =IFERROR(VLOOKUP(C17,'TB_31.03.2026 (Links)'!$D:$H,5,0)-J17,"Error") -> 0 | O17: 0 | P17: =+J17-O17 -> 0 | R17: =VLOOKUP(B17,[2]Sheet1!$B:$J,9,0) -> 0 | S17: =J17-R17 -> 0
... A43: 1900 | B43: 10952672 | C43: IDBI - 0600102000013891-Expenses A/c- Outgoing | D43: INR | F43: 0 | G43: 0 | H43: 26761 | I43: 26761 | J43: 0 | L43: =IFERROR(VLOOKUP(C43,'TB_31.03.2026 (Links)'!$D:$H,5,0)-J43,"Error") -> 0 | O43: 0 | P43: =+J43-O43 -> 0 | R43: =VLOOKUP(B43,[2]Sheet1!$B:$J,9,0) -> 0 | S43: =J43-R43 -> 0
A44: 1900 | B44: 10952680 | C44: IDBI- 0600102000013907- Rera A/c- Main | D44: INR | F44: 25000 | G44: 0 | H44: 2090 | I44: 27090 | J44: =F44+H44-I44 -> 0 | L44: =IFERROR(VLOOKUP(C44,'TB_31.03.2026 (Links)'!$D:$H,5,0)-J44,"Error") -> 0 | O44: 0 | P44: =+J44-O44 -> 0 | R44: =VLOOKUP(B44,[2]Sheet1!$B:$J,9,0) -> 0 | S44: =J44-R44 -> 0
A45: 1900 | B45: 10952681 | C45: IDBI- 0600102000013907- Rera A/c- Incoming | D45: INR | F45: 0 | G45: 0 | H45: 1000 | I45: 1000 | J45: 0 | L45: =IFERROR(VLOOKUP(C45,'TB_31.03.2026 (Links)'!$D:$H,5,0)-J45,"Error") -> 0 | O45: 0 | P45: =+J45-O45 -> 0 | R45: =VLOOKUP(B45,[2]Sheet1!$B:$J,9,0) -> 0 | S45: =J45-R45 -> 0
A46: 1900 | B46: 10952682 | C46: IDBI- 0600102000013907- Rera A/c- Outgoing | D46: INR | F46: 0 | G46: 0 | H46: 27351 | I46: 27351 | J46: 0 | L46: =IFERROR(VLOOKUP(C46,'TB_31.03.2026 (Links)'!$D:$H,5,0)-J46,"Error") -> 0 | O46: 0 | P46: =+J46-O46 -> 0 | R46: =VLOOKUP(B46,[2]Sheet1!$B:$J,9,0) -> 0 | S46: =J46-R46 -> 0
A47: 1900 | B47: 10952740 | C47: HDFC- 57500001831971- Collection A/c- Main | D47: INR | F47: 0 | G47: 0 | H47: 8713418.8 | I47: 8713418.8 | J47: 0 | L47: =IFERROR(VLOOKUP(C47,'TB_31.03.2026 (Links)'!$D:$H,5,0)-J47,"Error") -> 0 | O47: 0 | P47: =+J47-O47 -> 0 | R47: =VLOOKUP(B47,[2]Sheet1!$B:$J,9,0) -> 0 | S47: =J47-R47 -> 0
A48: 1900 | B48: 10952741 | C48: HDFC- 57500001831971- Collection A/c- Incoming | D48: INR | F48: 0 | G48: 0 | H48: 12912313 | I48: 12912313 | J48: 0 | L48: =IFERROR(VLOOKUP(C48,'TB_31.03.2026 (Links)'!$D:$H,5,0)-J48,"Error") -> 0 | O48: 0 | P48: =+J48-O48 -> 0 | R48: =VLOOKUP(B48,[2]Sheet1!$B:$J,9,0) -> 0 | S48: =J48-R48 -> 0
A49: 1900 | B49: 10952742 | C49: HDFC- 57500001831971- Collection A/c- Outgoing | D49: INR | F49: 0 | G49: 0 | H49: 4514534.9 | I49: 4514534.9 | J49: 0 | L49: =IFERROR(VLOOKUP(C49,'TB_31.03.2026 (Links)'!$D:$H,5,0)-J49,"Error") -> 0 | O49: 0 | P49: =+J49-O49 -> 0 | R49: =VLOOKUP(B49,[2]Sheet1!$B:$J,9,0) -> 0 | S49: =J49-R49 -> 0
A50: 1900 | B50: 10952750 | C50: HDFC- 57500001831820- Expenses A/c- Main | D50: INR | F50: 0 | G50: 0 | H50: 1354362 | I50: 1354362 | J50: 0.06 | L50: =IFERROR(VLOOKUP(C50,'TB_31.03.2026 (Links)'!$D:$H,5,0)-J50,"Error") -> 0 | O50: 0.06 | P50: =+J50-O50 -> 0 | R50: =VLOOKUP(B50,[2]Sheet1!$B:$J,9,0) -> 0.06 | S50: =J50-R50 -> 0
A51: 1900 | B51: 10952751 | C51: HDFC- 57500001831820- Expenses A/c- Incoming | D51: INR | F51: 0 | G51: 0 | H51: 1354362 | I51: 1354362 | J51: 0 | L51: =IFERROR(VLOOKUP(C51,'TB_31.03.2026 (Links)'!$D:$H,5,0)-J51,"Error") -> 0 | O51: 0 | P51: =+J51-O51 -> 0 | R51: =VLOOKUP(B51,[2]Sheet1!$B:$J,9,0) -> 0 | S51: =J51-R51 -> 0
A52: 1900 | B52: 10952752 | C52: HDFC- 57500001831820- Expenses A/c- Outgoing | D52: INR | F52: 0 | G52: 0 | H52: 1354362 | I52: 1354362 | J52: 0 | L52: =IFERROR(VLOOKUP(C52,'TB_31.03.2026 (Links)'!$D:$H,5,0)-J52,"Error") -> 0 | O52: 0 | P52: =+J52-O52 -> 0 | R52: =VLOOKUP(B52,[2]Sheet1!$B:$J,9,0) -> 0 | S52: =J52-R52 -> 0
A53: 1900 | B53: 10952760 | C53: HDFC- 57500001831984- Rera A/c- Main | D53: INR | F53: 0 | G53: 0 | H53: 3160163.9 | I53: 0 | J53: 3160163.9 | L53: =IFERROR(VLOOKUP(C53,'TB_31.03.2026 (Links)'!$D:$H,5,0)-J53,"Error") -> 0 | O53: 3160163.9 | P53: =+J53-O53 -> 0 | R53: =VLOOKUP(B53,[2]Sheet1!$B:$J,9,0) -> 3160163.9 | S53: =J53-R53 -> 0
A54: 1900 | B54: 10952761 | C54: HDFC- 57500001831984- Rera A/c- Incoming | D54: INR | F54: 0 | G54: 0 | H54: 3160170.9 | I54: 3160170.9 | J54: 0 | L54: =IFERROR(VLOOKUP(C54,'TB_31.03.2026 (Links)'!$D:$H,5,0)-J54,"Error") -> 0 | O54: 0 | P54: =+J54-O54 -> 0 | R54: =VLOOKUP(B54,[2]Sheet1!$B:$J,9,0) -> 0 | S54: =J54-R54 -> 0
A55: 1900 | B55: 11110003 | C55: FD-Interest on Fixed Deposit Accrued but Not Due | D55: INR | F55: 55980 | G55: 0 | H55: 2901127.1 | I55: 619060.85 | J55: 2338046.2 | L55: =IFERROR(VLOOKUP(C55,'TB_31.03.2026 (Links)'!$D:$H,5,0)-J55,"Error") -> 0 | O55: 2338046.2 | P55: =+J55-O55 -> 0 | R55: =VLOOKUP(B55,[2]Sheet1!$B:$J,9,0) -> 2338046.2 | S55: =J55-R55 -> 0
A56: 1900 | B56: 11130003 | C56: Input CGST 2.5% Receivable | D56: INR | F56: 0 | G56: 0 | H56: 43.32 | I56: 43.32 | J56: 0 | L56: =IFERROR(VLOOKUP(C56,'TB_31.03.2026 (Links)'!$D:$H,5,0)-J56,"Error") -> 0 | O56: 0 | P56: =+J56-O56 -> 0 | R56: =VLOOKUP(B56,[2]Sheet1!$B:$J,9,0) -> 0 | S56: =J56-R56 -> 0
... A67: 1900 | B67: 11140001 | C67: Prepaid Insurance | D67: INR | F67: 0 | G67: 0 | H67: 391553 | I67: 0 | J67: 391553 | L67: =IFERROR(VLOOKUP(C67,'TB_31.03.2026 (Links)'!$D:$H,5,0)-J67,"Error") -> 0 | O67: 391553 | P67: =+J67-O67 -> 0 | R67: =VLOOKUP(B67,[2]Sheet1!$B:$J,9,0) -> 391553 | S67: =J67-R67 -> 0
A68: 1900 | B68: 11140150 | C68: InterBranch Transaction | D68: INR | F68: -9.1197211e+08 | G68: 0 | H68: =562956890+6566277 -> 569523167 | I68: =24172096.66+2000+15120 -> 24189217 | J68: =+F68+H68-I68 -> -3.6663816e+08 | L68: =IFERROR(VLOOKUP(C68,'TB_31.03.2026 (Links)'!$D:$H,5,0)-J68,"Error") -> 0 | O68: -3.7318732e+08 | P68: =+J68-O68 -> 6549157 | R68: =VLOOKUP(B68,[2]Sheet1!$B:$J,9,0) -> -3.7318732e+08 | S68: =J68-R68 -> 6549157
A69: 1900 | B69: 11140151 | C69: Branch-Ho-Assets | D69: INR | F69: 7256064 | G69: 0 | H69: 0 | I69: 0 | J69: 7256064 | L69: =IFERROR(VLOOKUP(C69,'TB_31.03.2026 (Links)'!$D:$H,5,0)-J69,"Error") -> 0 | O69: 7256064 | P69: =+J69-O69 -> 0 | R69: =VLOOKUP(B69,[2]Sheet1!$B:$J,9,0) -> 7256064 | S69: =J69-R69 -> 0
A70: 1900 | B70: 11140201 | C70: IC RECEIVALE CLEARING | D70: INR | F70: 0 | G70: 0 | H70: 1178428.8 | I70: 1178428.5 | J70: 0.28 | L70: =IFERROR(VLOOKUP(C70,'TB_31.03.2026 (Links)'!$D:$H,5,0)-J70,"Error") -> 0 | O70: 0.28 | P70: =+J70-O70 -> 0 | R70: =VLOOKUP(B70,[2]Sheet1!$B:$J,9,0) -> 0.28 | S70: =J70-R70 -> 0
A71: 1900 | B71: 11150011 | C71: Deferred Tax Assets | D71: INR | F71: 3585.99 | G71: 0 | H71: 1910 | I71: 0 | J71: 5495.99 | L71: =IFERROR(VLOOKUP(C71,'TB_31.03.2026 (Links)'!$D:$H,5,0)-J71,"Error") -> 0 | O71: 5495.99 | P71: =+J71-O71 -> 0 | R71: =VLOOKUP(B71,[2]Sheet1!$B:$J,9,0) -> 5495.99 | S71: =J71-R71 -> 0
A72: 1900 | B72: 20000202 | C72: Current Capital - Rajesh Goyal | D72: INR | F72: 0 | G72: 0 | H72: 30000000 | I72: 30000000 | J72: 0 | L72: =IFERROR(VLOOKUP(C72,'TB_31.03.2026 (Links)'!$D:$H,5,0)-J72,"Error") -> 0 | O72: 0 | P72: =+J72-O72 -> 0 | R72: =VLOOKUP(B72,[2]Sheet1!$B:$J,9,0) -> 0 | S72: =J72-R72 -> 0
A73: 1900 | B73: 20000203 | C73: Current Capital - Vineet Goyal | D73: INR | F73: 0 | G73: 0 | H73: 8000000 | I73: 8000000 | J73: 0 | L73: =IFERROR(VLOOKUP(C73,'TB_31.03.2026 (Links)'!$D:$H,5,0)-J73,"Error") -> 0 | O73: 0 | P73: =+J73-O73 -> 0 | R73: =VLOOKUP(B73,[2]Sheet1!$B:$J,9,0) -> 0 | S73: =J73-R73 -> 0
A74: 1900 | B74: 20000308 | C74: Branch Ho-Liablities | D74: INR | F74: -13852958 | G74: 0 | H74: 0 | I74: 0 | J74: -13852958 | L74: =IFERROR(VLOOKUP(C74,'TB_31.03.2026 (Links)'!$D:$H,5,0)-J74,"Error") -> 0 | O74: -13852958 | P74: =+J74-O74 -> 0 | R74: =VLOOKUP(B74,[2]Sheet1!$B:$J,9,0) -> -13852958 | S74: =J74-R74 -> 0
A75: 1900 | B75: 20000350 | C75: Share Capital | D75: INR | F75: -100000 | G75: 0 | H75: 0 | I75: 0 | J75: -100000 | L75: =IFERROR(VLOOKUP(C75,'TB_31.03.2026 (Links)'!$D:$H,5,0)-J75,"Error") -> 0 | O75: -100000 | P75: =+J75-O75 -> 0 | R75: =VLOOKUP(B75,[2]Sheet1!$B:$J,9,0) -> -100000 | S75: =J75-R75 -> 0
A76: 1900 | B76: 20100001 | C76: Retained Earning A/c | D76: INR | F76: 111152.72 | G76: 0 | H76: 0 | I76: 0 | J76: 111152.72 | L76: =IFERROR(VLOOKUP(C76,'TB_31.03.2026 (Links)'!$D:$H,5,0)-J76,"Error") -> 0 | O76: 111152.72 | P76: =+J76-O76 -> 0 | R76: =VLOOKUP(B76,[2]Sheet1!$B:$J,9,0) -> 111152.72 | S76: =J76-R76 -> 0
A77: 1900 | B77: 20100003 | C77: Reserves & Surplus | D77: INR | F77: 2890.55 | G77: 0 | H77: 0 | I77: 0 | J77: 2890.55 | L77: =IFERROR(VLOOKUP(C77,'TB_31.03.2026 (Links)'!$D:$H,5,0)-J77,"Error") -> 0 | O77: 2890.55 | P77: =+J77-O77 -> 0 | R77: =VLOOKUP(B77,[2]Sheet1!$B:$J,9,0) -> 2890.55 | S77: =J77-R77 -> 0
A78: 1900 | B78: 20100101 | C78: Zero Balance Clearing for PCA | D78: INR | F78: 0 | G78: 0 | H78: 1.1984773e+09 | I78: 1.1984773e+09 | J78: 0 | L78: =IFERROR(VLOOKUP(C78,'TB_31.03.2026 (Links)'!$D:$H,5,0)-J78,"Error") -> 0 | O78: 0 | P78: =+J78-O78 -> 0 | R78: =VLOOKUP(B78,[2]Sheet1!$B:$J,9,0) -> 0 | S78: =J78-R78 -> 0
A79: 1900 | B79: 20200001 | C79: Loan from Relative -Krishna kumar Goyal | D79: INR | F79: -29758000 | G79: 0 | H79: 40000000 | I79: 131600000 | J79: -121358000 | L79: =IFERROR(VLOOKUP(C79,'TB_31.03.2026 (Links)'!$D:$H,5,0)-J79,"Error") -> 0 | O79: -121358000 | P79: =+J79-O79 -> 0 | R79: =VLOOKUP(B79,[2]Sheet1!$B:$J,9,0) -> -121358000 | S79: =J79-R79 -> 0
A80: 1900 | B80: 20200002 | C80: Loan from Directors - Rajesh Goyal | D80: INR | F80: -172634520 | G80: 0 | H80: 307500000 | I80: 340500000 | J80: -205634520 | L80: =IFERROR(VLOOKUP(C80,'TB_31.03.2026 (Links)'!$D:$H,5,0)-J80,"Error") -> 0 | O80: -205634520 | P80: =+J80-O80 -> 0 | R80: =VLOOKUP(B80,[2]Sheet1!$B:$J,9,0) -> -205634520 | S80: =J80-R80 -> 0
... A93: 1900 | B93: 20412102 | C93: SGST RCM Payable | D93: INR | F93: -43663.32 | G93: 0 | H93: 147837 | I93: 113166.46 | J93: -8992.78 | L93: =IFERROR(VLOOKUP(C93,'TB_31.03.2026 (Links)'!$D:$H,5,0)-J93,"Error") -> 0 | O93: -8992.78 | P93: =+J93-O93 -> 0 | R93: =VLOOKUP(B93,[2]Sheet1!$B:$J,9,0) -> -8992.78 | S93: =J93-R93 -> 0
A94: 1900 | B94: 20415001 | C94: TDS Payable on Purchase (194Q) | D94: INR | F94: -60276.89 | G94: 0 | H94: 60278 | I94: 1.11 | J94: =+F94+H94-I94 -> 5.8197891e-13 | L94: =IFERROR(VLOOKUP(C94,'TB_31.03.2026 (Links)'!$D:$H,5,0)-J94,"Error") -> 0 | O94: 0 | P94: =+J94-O94 -> 5.8197891e-13 | R94: =VLOOKUP(B94,[2]Sheet1!$B:$J,9,0) -> 0 | S94: =J94-R94 -> 5.8197891e-13
A95: 1900 | B95: 20415002 | C95: TDS Payable on Brokerage (194H) | D95: INR | F95: 20886 | G95: 0 | H95: 303038 | I95: 349171 | J95: -25247 | L95: =IFERROR(VLOOKUP(C95,'TB_31.03.2026 (Links)'!$D:$H,5,0)-J95,"Error") -> 0 | O95: -25247 | P95: =+J95-O95 -> 0 | R95: =VLOOKUP(B95,[2]Sheet1!$B:$J,9,0) -> -25247 | S95: =J95-R95 -> 0
A96: 1900 | B96: 20415003 | C96: TDS Payable on Interest (194A) | D96: INR | F96: 0 | G96: 0 | H96: 1616152 | I96: 6024009.9 | J96: -4407857.9 | L96: =IFERROR(VLOOKUP(C96,'TB_31.03.2026 (Links)'!$D:$H,5,0)-J96,"Error") -> 0 | O96: -4407857.9 | P96: =+J96-O96 -> 0 | R96: =VLOOKUP(B96,[2]Sheet1!$B:$J,9,0) -> -4407857.9 | S96: =J96-R96 -> 0
A97: 1900 | B97: 20415004 | C97: TDS Payable on Rent (194I) | D97: INR | F97: 0 | G97: 0 | H97: 3975 | I97: 3975 | J97: 0 | L97: =IFERROR(VLOOKUP(C97,'TB_31.03.2026 (Links)'!$D:$H,5,0)-J97,"Error") -> 0 | O97: 0 | P97: =+J97-O97 -> 0 | R97: =VLOOKUP(B97,[2]Sheet1!$B:$J,9,0) -> 0 | S97: =J97-R97 -> 0
A98: 1900 | B98: 20415006 | C98: TDS Payable on Professional Fees (194J) | D98: INR | F98: -106899 | G98: 0 | H98: 1263022 | I98: 1212300 | J98: -56177 | L98: =IFERROR(VLOOKUP(C98,'TB_31.03.2026 (Links)'!$D:$H,5,0)-J98,"Error") -> 0 | O98: -56177 | P98: =+J98-O98 -> 0 | R98: =VLOOKUP(B98,[2]Sheet1!$B:$J,9,0) -> -56177 | S98: =J98-R98 -> 0
A99: 1900 | B99: 20415007 | C99: TDS Payable on Contractor (194C) | D99: INR | F99: -844881 | G99: 0 | H99: 3404785 | I99: 2569384 | J99: -9480 | L99: =IFERROR(VLOOKUP(C99,'TB_31.03.2026 (Links)'!$D:$H,5,0)-J99,"Error") -> 0 | O99: -9480 | P99: =+J99-O99 -> 0 | R99: =VLOOKUP(B99,[2]Sheet1!$B:$J,9,0) -> -9480 | S99: =J99-R99 -> 0
A100: 1900 | B100: 20415021 | C100: TDS on Salary | D100: INR | F100: 0 | G100: 0 | H100: 3133723 | I100: 3486647 | J100: -352924 | L100: =IFERROR(VLOOKUP(C100,'TB_31.03.2026 (Links)'!$D:$H,5,0)-J100,"Error") -> 0 | O100: -352924 | P100: =+J100-O100 -> 0 | R100: =VLOOKUP(B100,[2]Sheet1!$B:$J,9,0) -> -352924 | S100: =J100-R100 -> 0
A101: 1900 | B101: 20416001 | C101: EDLI Contribution Payable | D101: INR | F101: 0 | G101: 0 | H101: 54109 | I101: 60446 | J101: -6337 | L101: =IFERROR(VLOOKUP(C101,'TB_31.03.2026 (Links)'!$D:$H,5,0)-J101,"Error") -> 0 | O101: -6337 | P101: =+J101-O101 -> 0 | R101: =VLOOKUP(B101,[2]Sheet1!$B:$J,9,0) -> -6337 | S101: =J101-R101 -> 0
A102: 1900 | B102: 20416002 | C102: Employer Contribution at ESI Payable | D102: INR | F102: 0 | G102: 0 | H102: 13502 | I102: 13502 | J102: 0 | L102: =IFERROR(VLOOKUP(C102,'TB_31.03.2026 (Links)'!$D:$H,5,0)-J102,"Error") -> 0 | O102: 0 | P102: =+J102-O102 -> 0 | R102: =VLOOKUP(B102,[2]Sheet1!$B:$J,9,0) -> 0 | S102: =J102-R102 -> 0
A103: 1900 | B103: 20416003 | C103: PF Admin Charges Payable | D103: INR | F103: 0 | G103: 0 | H103: 54103 | I103: 60440 | J103: -6337 | L103: =IFERROR(VLOOKUP(C103,'TB_31.03.2026 (Links)'!$D:$H,5,0)-J103,"Error") -> 0 | O103: -6337 | P103: =+J103-O103 -> 0 | R103: =VLOOKUP(B103,[2]Sheet1!$B:$J,9,0) -> -6337 | S103: =J103-R103 -> 0
A104: 1900 | B104: 20416004 | C104: PF Employer Contribution Payable | D104: INR | F104: 0 | G104: 0 | H104: 1298488 | I104: 1450574 | J104: -152086 | L104: =IFERROR(VLOOKUP(C104,'TB_31.03.2026 (Links)'!$D:$H,5,0)-J104,"Error") -> 0 | O104: -152086 | P104: =+J104-O104 -> 0 | R104: =VLOOKUP(B104,[2]Sheet1!$B:$J,9,0) -> -152086 | S104: =J104-R104 -> 0
A105: 1900 | B105: 20420001 | C105: Salary Payable | D105: INR | F105: 0 | G105: 0 | H105: 98361817 | I105: 104036790 | J105: -5674973 | L105: =IFERROR(VLOOKUP(C105,'TB_31.03.2026 (Links)'!$D:$H,5,0)-J105,"Error") -> 0 | O105: -5674973 | P105: =+J105-O105 -> 0 | R105: =VLOOKUP(B105,[2]Sheet1!$B:$J,9,0) -> -5674973 | S105: =J105-R105 -> 0
A106: 1900 | B106: 20420003 | C106: P.F. Employee Contribution Payable | D106: INR | F106: 0 | G106: 0 | H106: 1298488 | I106: 1450574 | J106: -152086 | L106: =IFERROR(VLOOKUP(C106,'TB_31.03.2026 (Links)'!$D:$H,5,0)-J106,"Error") -> 0 | O106: -152086 | P106: =+J106-O106 -> 0 | R106: =VLOOKUP(B106,[2]Sheet1!$B:$J,9,0) -> -152086 | S106: =J106-R106 -> 0
... A142: 1900 | B142: 40100008 | C142: Site Housekeeping Expenses | D142: INR | F142: 0 | G142: 0 | H142: 1196639 | I142: 3000 | J142: 1193639 | L142: =IFERROR(VLOOKUP(C142,'TB_31.03.2026 (Links)'!$D:$H,5,0)-J142,"Error") -> 0 | O142: 1193639 | P142: =+J142-O142 -> 0 | R142: =VLOOKUP(B142,[2]Sheet1!$B:$J,9,0) -> 1193639 | S142: =J142-R142 -> 0
A143: 1900 | B143: 40200002 | C143: Development Expenses | D143: INR | F143: 0 | G143: 0 | H143: 6640637 | I143: =50360+6566277 -> 6616637 | J143: =+H143-I143 -> 24000 | L143: =IFERROR(VLOOKUP(C143,'TB_31.03.2026 (Links)'!$D:$H,5,0)-J143,"Error") -> 0 | O143: 6590277 | P143: =+J143-O143 -> -6566277 | R143: =VLOOKUP(B143,[2]Sheet1!$B:$J,9,0) -> 6590277 | S143: =J143-R143 -> -6566277
A144: 1900 | B144: 40200004 | C144: PCMC Scrutiny Fees | D144: INR | F144: 0 | G144: 0 | H144: 671500 | I144: 0 | J144: 671500 | L144: =IFERROR(VLOOKUP(C144,'TB_31.03.2026 (Links)'!$D:$H,5,0)-J144,"Error") -> 0 | O144: 671500 | P144: =+J144-O144 -> 0 | R144: =VLOOKUP(B144,[2]Sheet1!$B:$J,9,0) -> 671500 | S144: =J144-R144 -> 0
A145: 1900 | B145: 40200005 | C145: Property Tax | D145: INR | F145: 0 | G145: 0 | H145: 764422 | I145: 0 | J145: 764422 | L145: =IFERROR(VLOOKUP(C145,'TB_31.03.2026 (Links)'!$D:$H,5,0)-J145,"Error") -> 0 | O145: 764422 | P145: =+J145-O145 -> 0 | R145: =VLOOKUP(B145,[2]Sheet1!$B:$J,9,0) -> 764422 | S145: =J145-R145 -> 0
A146: 1900 | B146: 40200032 | C146: ROC Fees Paid | D146: INR | F146: 0 | G146: 0 | H146: 20106.04 | I146: 0 | J146: 20106.04 | L146: =IFERROR(VLOOKUP(C146,'TB_31.03.2026 (Links)'!$D:$H,5,0)-J146,"Error") -> 0 | O146: 20106.04 | P146: =+J146-O146 -> 0 | R146: =VLOOKUP(B146,[2]Sheet1!$B:$J,9,0) -> 20106.04 | S146: =J146-R146 -> 0
A147: 1900 | B147: 40300003 | C147: Consumption - Civil Material | D147: INR | F147: 0 | G147: 0 | H147: 3267147.7 | I147: 164262.75 | J147: 3102885 | L147: =IFERROR(VLOOKUP(C147,'TB_31.03.2026 (Links)'!$D:$H,5,0)-J147,"Error") -> 0 | O147: 3102885 | P147: =+J147-O147 -> 0 | R147: =VLOOKUP(B147,[2]Sheet1!$B:$J,9,0) -> 3102885 | S147: =J147-R147 -> 0
A148: 1900 | B148: 40300006 | C148: Consumption - Boughout items (Hardware) | D148: INR | F148: 0 | G148: 0 | H148: 29135 | I148: 29135 | J148: 0 | L148: =IFERROR(VLOOKUP(C148,'TB_31.03.2026 (Links)'!$D:$H,5,0)-J148,"Error") -> 0 | O148: 0 | P148: =+J148-O148 -> 0 | R148: =VLOOKUP(B148,[2]Sheet1!$B:$J,9,0) -> 0 | S148: =J148-R148 -> 0
A149: 1900 | B149: 40300008 | C149: Consumption - Plumbing & Sanitary | D149: INR | F149: 0 | G149: 0 | H149: 801105.77 | I149: 0 | J149: 801105.77 | L149: =IFERROR(VLOOKUP(C149,'TB_31.03.2026 (Links)'!$D:$H,5,0)-J149,"Error") -> 0 | O149: 801105.77 | P149: =+J149-O149 -> 0 | R149: =VLOOKUP(B149,[2]Sheet1!$B:$J,9,0) -> 801105.77 | S149: =J149-R149 -> 0
A150: 1900 | B150: 40300009 | C150: Consumption - Electricals | D150: INR | F150: 0 | G150: 0 | H150: 1809 | I150: 1809 | J150: 0 | L150: =IFERROR(VLOOKUP(C150,'TB_31.03.2026 (Links)'!$D:$H,5,0)-J150,"Error") -> 0 | O150: 0 | P150: =+J150-O150 -> 0 | R150: =VLOOKUP(B150,[2]Sheet1!$B:$J,9,0) -> 0 | S150: =J150-R150 -> 0
A151: 1900 | B151: 40300010 | C151: Consumption - Furniture | D151: INR | F151: 0 | G151: 0 | H151: 270626.59 | I151: 270626.59 | J151: 0 | L151: =IFERROR(VLOOKUP(C151,'TB_31.03.2026 (Links)'!$D:$H,5,0)-J151,"Error") -> 0 | O151: 0 | P151: =+J151-O151 -> 0 | R151: =VLOOKUP(B151,[2]Sheet1!$B:$J,9,0) -> 0 | S151: =J151-R151 -> 0
A152: 1900 | B152: 40400002 | C152: Subcontracting Cost - Engineering & Civil Work | D152: INR | F152: 0 | G152: 0 | H152: 3.310557e+08 | I152: 1.8989919e+08 | J152: 1.4115651e+08 | L152: =IFERROR(VLOOKUP(C152,'TB_31.03.2026 (Links)'!$D:$H,5,0)-J152,"Error") -> 0 | O152: 1.4115651e+08 | P152: =+J152-O152 -> 0 | R152: =VLOOKUP(B152,[2]Sheet1!$B:$J,9,0) -> 1.4115651e+08 | S152: =J152-R152 -> 0
A153: 1900 | B153: 40400003 | C153: Subcontracting Cost - Electrical Work | D153: INR | F153: 0 | G153: 0 | H153: 781859 | I153: 0 | J153: 781859 | L153: =IFERROR(VLOOKUP(C153,'TB_31.03.2026 (Links)'!$D:$H,5,0)-J153,"Error") -> 0 | O153: 781859 | P153: =+J153-O153 -> 0 | R153: =VLOOKUP(B153,[2]Sheet1!$B:$J,9,0) -> 781859 | S153: =J153-R153 -> 0
A154: 1900 | B154: 40400004 | C154: Subcontracting Cost - Plumbing Work | D154: INR | F154: 0 | G154: 0 | H154: 4261.12 | I154: 0 | J154: 4261.12 | L154: =IFERROR(VLOOKUP(C154,'TB_31.03.2026 (Links)'!$D:$H,5,0)-J154,"Error") -> 0 | O154: 4261.12 | P154: =+J154-O154 -> 0 | R154: =VLOOKUP(B154,[2]Sheet1!$B:$J,9,0) -> 4261.12 | S154: =J154-R154 -> 0
A155: 1900 | B155: 40500001 | C155: Consultancy & Architect Expenses | D155: INR | F155: 0 | G155: 0 | H155: 11628000 | I155: 0 | J155: 11628000 | L155: =IFERROR(VLOOKUP(C155,'TB_31.03.2026 (Links)'!$D:$H,5,0)-J155,"Error") -> 0 | O155: 11628000 | P155: =+J155-O155 -> 0 | R155: =VLOOKUP(B155,[2]Sheet1!$B:$J,9,0) -> 11628000 | S155: =J155-R155 -> 0
... A176: 1900 | B176: 45200029 | C176: Audit Fees | D176: INR | F176: 0 | G176: 0 | H176: 580000 | I176: 380000 | J176: 200000 | L176: =IFERROR(VLOOKUP(C176,'TB_31.03.2026 (Links)'!$D:$H,5,0)-J176,"Error") -> 0 | O176: 200000 | P176: =+J176-O176 -> 0 | R176: =VLOOKUP(B176,[2]Sheet1!$B:$J,9,0) -> 200000 | S176: =J176-R176 -> 0
A177: 1900 | B177: 45300001 | C177: CGST Indirect Expenses | D177: INR | F177: 0 | G177: 0 | H177: =2134629.03+360 -> 2134989 | I177: 239957.07 | J177: =+F177+H177-I177 -> 1895032 | L177: =IFERROR(VLOOKUP(C177,'TB_31.03.2026 (Links)'!$D:$H,5,0)-J177,"Error") -> 0 | O177: 1894672 | P177: =+J177-O177 -> 360 | R177: =VLOOKUP(B177,[2]Sheet1!$B:$J,9,0) -> 1894672 | S177: =J177-R177 -> 360
A178: 1900 | B178: 45300002 | C178: SGST Indirect Expenses | D178: INR | F178: 0 | G178: 0 | H178: =2134629.03+360 -> 2134989 | I178: 239957.07 | J178: =+F178+H178-I178 -> 1895032 | L178: =IFERROR(VLOOKUP(C178,'TB_31.03.2026 (Links)'!$D:$H,5,0)-J178,"Error") -> 0 | O178: 1894672 | P178: =+J178-O178 -> 360 | R178: =VLOOKUP(B178,[2]Sheet1!$B:$J,9,0) -> 1894672 | S178: =J178-R178 -> 360
A179: 1900 | B179: 45300003 | C179: IGST Indirect Expenses | D179: INR | F179: 0 | G179: 0 | H179: 64028.52 | I179: 64028.52 | J179: 0 | L179: =IFERROR(VLOOKUP(C179,'TB_31.03.2026 (Links)'!$D:$H,5,0)-J179,"Error") -> 0 | O179: 0 | P179: =+J179-O179 -> 0 | R179: =VLOOKUP(B179,[2]Sheet1!$B:$J,9,0) -> 0 | S179: =J179-R179 -> 0
A180: 1900 | B180: 45300021 | C180: Interest on Late Payment of GST | D180: INR | F180: 0 | G180: 0 | H180: 305998 | I180: 0 | J180: 305998 | L180: =IFERROR(VLOOKUP(C180,'TB_31.03.2026 (Links)'!$D:$H,5,0)-J180,"Error") -> 0 | O180: 305998 | P180: =+J180-O180 -> 0 | R180: =VLOOKUP(B180,[2]Sheet1!$B:$J,9,0) -> 305998 | S180: =J180-R180 -> 0
A181: 1900 | B181: 45400001 | C181: Brokerage & Commission | D181: INR | F181: 0 | G181: 0 | H181: 16427282 | I181: 721799 | J181: 15705483 | L181: =IFERROR(VLOOKUP(C181,'TB_31.03.2026 (Links)'!$D:$H,5,0)-J181,"Error") -> 0 | O181: 15705483 | P181: =+J181-O181 -> 0 | R181: =VLOOKUP(B181,[2]Sheet1!$B:$J,9,0) -> 15705483 | S181: =J181-R181 -> 0
A182: 1900 | B182: 45400002 | C182: Scheme Rebate | D182: INR | F182: 0 | G182: 0 | H182: 1344000 | I182: 0 | J182: 1344000 | L182: =IFERROR(VLOOKUP(C182,'TB_31.03.2026 (Links)'!$D:$H,5,0)-J182,"Error") -> 0 | O182: 1344000 | P182: =+J182-O182 -> 0 | R182: =VLOOKUP(B182,[2]Sheet1!$B:$J,9,0) -> 1344000 | S182: =J182-R182 -> 0
A183: 1900 | B183: 45400011 | C183: Digital Marketing | D183: INR | F183: 0 | G183: 0 | H183: 1886929.6 | I183: 0 | J183: 1886929.6 | L183: =IFERROR(VLOOKUP(C183,'TB_31.03.2026 (Links)'!$D:$H,5,0)-J183,"Error") -> 0 | O183: 1886929.6 | P183: =+J183-O183 -> 0 | R183: =VLOOKUP(B183,[2]Sheet1!$B:$J,9,0) -> 1886929.6 | S183: =J183-R183 -> 0
A184: 1900 | B184: 45400014 | C184: Outdoor Marketing Cost | D184: INR | F184: 0 | G184: 0 | H184: 2490972.9 | I184: 0 | J184: 2490972.9 | L184: =IFERROR(VLOOKUP(C184,'TB_31.03.2026 (Links)'!$D:$H,5,0)-J184,"Error") -> 0 | O184: 2490972.9 | P184: =+J184-O184 -> 0 | R184: =VLOOKUP(B184,[2]Sheet1!$B:$J,9,0) -> 2490972.9 | S184: =J184-R184 -> 0
A185: 1900 | B185: 45400016 | C185: Other Marketing Expenses | D185: INR | F185: 0 | G185: 0 | H185: 1080115.3 | I185: 0 | J185: 1080115.3 | L185: =IFERROR(VLOOKUP(C185,'TB_31.03.2026 (Links)'!$D:$H,5,0)-J185,"Error") -> 0 | O185: 1080115.3 | P185: =+J185-O185 -> 0 | R185: =VLOOKUP(B185,[2]Sheet1!$B:$J,9,0) -> 1080115.3 | S185: =J185-R185 -> 0
A186: 1900 | B186: 45400020 | C186: Other Sales Cost | D186: INR | F186: 0 | G186: 0 | H186: 300000 | I186: 50000 | J186: 250000 | L186: =IFERROR(VLOOKUP(C186,'TB_31.03.2026 (Links)'!$D:$H,5,0)-J186,"Error") -> 0 | O186: 250000 | P186: =+J186-O186 -> 0 | R186: =VLOOKUP(B186,[2]Sheet1!$B:$J,9,0) -> 250000 | S186: =J186-R186 -> 0
A187: 1900 | B187: 45510008 | C187: OD - Interest on OD | D187: INR | F187: 0 | G187: 0 | H187: 1993971 | I187: 0 | J187: 1993971 | L187: =IFERROR(VLOOKUP(C187,'TB_31.03.2026 (Links)'!$D:$H,5,0)-J187,"Error") -> 0 | O187: 1993971 | P187: =+J187-O187 -> 0 | R187: =VLOOKUP(B187,[2]Sheet1!$B:$J,9,0) -> 1993971 | S187: =J187-R187 -> 0
A188: 1900 | B188: 45510051 | C188: Bank Charges | D188: INR | F188: 0 | G188: 0 | H188: 1040410.7 | I188: 1005926.6 | J188: 34484.1 | L188: =IFERROR(VLOOKUP(C188,'TB_31.03.2026 (Links)'!$D:$H,5,0)-J188,"Error") -> 0 | O188: 34484.1 | P188: =+J188-O188 -> 0 | R188: =VLOOKUP(B188,[2]Sheet1!$B:$J,9,0) -> 34484.1 | S188: =J188-R188 -> 0
A189: 1900 | B189: 45520023 | C189: Registration and Filing Fees | D189: INR | F189: 0 | G189: 0 | H189: 17875 | I189: 0 | J189: 17875 | L189: =IFERROR(VLOOKUP(C189,'TB_31.03.2026 (Links)'!$D:$H,5,0)-J189,"Error") -> 0 | O189: 17875 | P189: =+J189-O189 -> 0 | R189: =VLOOKUP(B189,[2]Sheet1!$B:$J,9,0) -> 17875 | S189: =J189-R189 -> 0
A190: 1900 | B190: 45600006 | C190: Depreciation - Office Equipments | D190: INR | F190: 0 | G190: 0 | H190: 14576.15 | I190: 0 | J190: 14576.15 | L190: =IFERROR(VLOOKUP(C190,'TB_31.03.2026 (Links)'!$D:$H,5,0)-J190,"Error") -> 0 | O190: 14576.15 | P190: =+J190-O190 -> 0 | R190: =VLOOKUP(B190,[2]Sheet1!$B:$J,9,0) -> 14576.15 | S190: =J190-R190 -> 0
... A195: 1900 | B195: 90000005 | C195: Migration Account - GL | D195: INR | F195: 1.2165561e+09 | G195: 0 | H195: 0 | I195: 0 | J195: 1.2165561e+09 | L195: =IFERROR(VLOOKUP(C195,'TB_31.03.2026 (Links)'!$D:$H,5,0)-J195,"Error") -> 0 | O195: 1.2165561e+09 | P195: =+J195-O195 -> 0 | R195: =VLOOKUP(B195,[2]Sheet1!$B:$J,9,0) -> 1.2165561e+09 | S195: =J195-R195 -> 0
A196: 1900 | B196: 10910011 | C196: TDS Receivable - Aditya Birla Capital limited | D196: INR | G196: 0 | H196: 5563060.9 | I196: 713183.9 | J196: 4849877 | L196: =IFERROR(VLOOKUP(C196,'TB_31.03.2026 (Links)'!$D:$H,5,0)-J196,"Error") -> 0 | O196: 4849877 | P196: =+J196-O196 -> 0 | R196: =VLOOKUP(B196,[2]Sheet1!$B:$J,9,0) -> 4849877 | S196: =J196-R196 -> 0
A197: 1900 | B197: 10930001 | C197: Advance to Vendor | D197: INR | G197: 0 | H197: 120000 | I197: 100000 | J197: 20000 | L197: =IFERROR(VLOOKUP(C197,'TB_31.03.2026 (Links)'!$D:$H,5,0)-J197,"Error") -> 0 | O197: 20000 | P197: =+J197-O197 -> 0 | R197: =VLOOKUP(B197,[2]Sheet1!$B:$J,9,0) -> 20000 | S197: =J197-R197 -> 0
A198: 1900 | B198: 11110011 | C198: PF Excess Paid | D198: INR | G198: 0 | H198: 147 | I198: 0 | J198: 147 | L198: =IFERROR(VLOOKUP(C198,'TB_31.03.2026 (Links)'!$D:$H,5,0)-J198,"Error") -> 0 | O198: 147 | P198: =+J198-O198 -> 0 | R198: =VLOOKUP(B198,[2]Sheet1!$B:$J,9,0) -> 147 | S198: =J198-R198 -> 0
A199: 1900 | B199: 20420033 | C199: Professional Fees Payable | D199: INR | G199: 0 | H199: 0 | I199: 7500 | J199: -7500 | L199: =IFERROR(VLOOKUP(C199,'TB_31.03.2026 (Links)'!$D:$H,5,0)-J199,"Error") -> 0 | O199: -7500 | P199: =+J199-O199 -> 0 | R199: =VLOOKUP(B199,[2]Sheet1!$B:$J,9,0) -> -7500 | S199: =J199-R199 -> 0
A200: 1900 | B200: 45400018 | C200: Advertising Expenses | D200: INR | G200: 0 | H200: =15360+14400 -> 29760 | I200: 0 | J200: =+H200-I200 -> 29760 | L200: =IFERROR(VLOOKUP(C200,'TB_31.03.2026 (Links)'!$D:$H,5,0)-J200,"Error") -> 0 | O200: 15360 | P200: =+J200-O200 -> 14400 | R200: =VLOOKUP(B200,[2]Sheet1!$B:$J,9,0) -> 15360 | S200: =J200-R200 -> 14400
A201: 1900 | B201: 45510053 | C201: Penalty/Fine/Damages | D201: INR | G201: 0 | H201: 1000000 | I201: 0 | J201: 1000000 | L201: =IFERROR(VLOOKUP(C201,'TB_31.03.2026 (Links)'!$D:$H,5,0)-J201,"Error") -> 0 | O201: 1000000 | P201: =+J201-O201 -> 0 | R201: =VLOOKUP(B201,[2]Sheet1!$B:$J,9,0) -> 1000000 | S201: =J201-R201 -> 0
A202: 1900 | B202: 45520001 | C202: Interest Paid on Loan | D202: INR | G202: 0 | H202: 67296060 | I202: 6415229 | J202: 60880831 | L202: =IFERROR(VLOOKUP(C202,'TB_31.03.2026 (Links)'!$D:$H,5,0)-J202,"Error") -> 0 | O202: 60880831 | P202: =+J202-O202 -> 0 | R202: =VLOOKUP(B202,[2]Sheet1!$B:$J,9,0) -> 60880831 | S202: =J202-R202 -> 0
A203: 1900 | B203: 45520026 | C203: Deffered Tax - P&L | D203: INR | G203: 0 | H203: 0 | I203: 1910 | J203: -1910 | L203: =IFERROR(VLOOKUP(C203,'TB_31.03.2026 (Links)'!$D:$H,5,0)-J203,"Error") -> 0 | O203: -1910 | P203: =+J203-O203 -> 0 | R203: =VLOOKUP(B203,[2]Sheet1!$B:$J,9,0) -> -1910 | S203: =J203-R203 -> 0
A204: 1900 | B204: 11150001 | C204: Income Tax Refund | D204: INR | G204: 0 | H204: 0 | I204: 6530 | J204: -6530 | L204: =IFERROR(VLOOKUP(C204,'TB_31.03.2026 (Links)'!$D:$H,5,0)-J204,"Error") -> 0 | O204: -6530 | P204: =+J204-O204 -> 0 | R204: =VLOOKUP(B204,[2]Sheet1!$B:$J,9,0) -> -6530 | S204: =J204-R204 -> 0
A205: 1900 | B205: 30000072 | C205: Sale of - Land | D205: INR | G205: 0 | H205: 0 | I205: 362900000 | J205: -362900000 | L205: =IFERROR(VLOOKUP(C205,'TB_31.03.2026 (Links)'!$D:$H,5,0)-J205,"Error") -> 0 | O205: -362900000 | P205: =+J205-O205 -> 0 | R205: =VLOOKUP(B205,[2]Sheet1!$B:$J,9,0) -> -362900000 | S205: =J205-R205 -> 0
A206: 1900 | B206: 40900201 | C206: Stamp Duty & Registration Expenses - on Land Purch | D206: INR | G206: 0 | H206: 300000 | I206: 0 | J206: 300000 | L206: =IFERROR(VLOOKUP(C206,'TB_31.03.2026 (Links)'!$D:$H,5,0)-J206,"Error") -> 0 | O206: 300000 | P206: =+J206-O206 -> 0 | R206: =VLOOKUP(B206,[2]Sheet1!$B:$J,9,0) -> 300000 | S206: =J206-R206 -> 0
A207: 1900 | B207: 45520021 | C207: Interest On Late Payment of TDS | D207: INR | G207: 0 | H207: 88645 | I207: 0 | J207: 88645 | L207: =IFERROR(VLOOKUP(C207,'TB_31.03.2026 (Links)'!$D:$H,5,0)-J207,"Error") -> 0 | O207: 86645 | P207: =+J207-O207 -> 2000 | R207: =VLOOKUP(B207,[2]Sheet1!$B:$J,9,0) -> 86645 | S207: =J207-R207 -> 2000
A208: 1900 | B208: 10910012 | C208: TDS Payable (Excess Paid) | D208: INR | G208: 0 | H208: 465249.11 | I208: 442019.11 | J208: 23230
J211: 3.3866097e+08
...

Sheet TB_31.03.2026 (Links)
E3: =SUBTOTAL(9,E5:E207) -> -1.4305115e-06 | F3: =SUBTOTAL(9,F5:F207) -> 1.5934278e+10 | G3: =SUBTOTAL(9,G5:G207) -> 1.5934278e+10 | H3: =SUBTOTAL(9,H5:H207) -> -1.4305115e-06 | I3: =SUBTOTAL(9,I5:I207) -> -1.4305115e-06
A4: Company Code | B4: G/L Account | C4: BS type | D4: G/L Acct Long Text | E4: Balance Carryforward | F4: Debit Blnce of Reportng Period | G4: Credit Balance Reporting Per. | H4: Accumulated Balance | I4: Latest TB
A5: 1900 | B5: 10000070 | C5: Assets | D5: Office Equipments | E5: =VLOOKUP(D5,'Raw TB_26.04.2026 (SAP Paste)'!$C:$J,4,0) -> 54811 | F5: =VLOOKUP(D5,'Raw TB_26.04.2026 (SAP Paste)'!$C:$J,6,0) -> 0 | G5: =VLOOKUP(D5,'Raw TB_26.04.2026 (SAP Paste)'!$C:$J,7,0) -> 0 | H5: =+VLOOKUP(D5,'Raw TB_26.04.2026 (SAP Paste)'!C:J,8,0) -> 54811 | I5: =VLOOKUP(B5,TB!$B$4:$H$202,7,) -> 54811 | J5: =I5-H5 -> 0
A6: 1900 | B6: 10001070 | C6: Assets | D6: Accumulated Dep - Office Equipments | E6: =VLOOKUP(D6,'Raw TB_26.04.2026 (SAP Paste)'!$C:$J,4,0) -> -22469.87 | F6: =VLOOKUP(D6,'Raw TB_26.04.2026 (SAP Paste)'!$C:$J,6,0) -> 0 | G6: =VLOOKUP(D6,'Raw TB_26.04.2026 (SAP Paste)'!$C:$J,7,0) -> 14576.15 | H6: =+VLOOKUP(D6,'Raw TB_26.04.2026 (SAP Paste)'!C:J,8,0) -> -37046.02 | I6: =VLOOKUP(B6,TB!$B$4:$H$202,7,) -> -37046.02 | J6: =I6-H6 -> 0
A7: 1900 | B7: 10320101 | C7: Assets | D7: FD - Investment in Fixed Deposit | E7: =VLOOKUP(D7,'Raw TB_26.04.2026 (SAP Paste)'!$C:$J,4,0) -> 1000000 | F7: =VLOOKUP(D7,'Raw TB_26.04.2026 (SAP Paste)'!$C:$J,6,0) -> 2.0040348e+08 | G7: =VLOOKUP(D7,'Raw TB_26.04.2026 (SAP Paste)'!$C:$J,7,0) -> 1.6640348e+08 | H7: =+VLOOKUP(D7,'Raw TB_26.04.2026 (SAP Paste)'!C:J,8,0) -> 35000000 | I7: =VLOOKUP(B7,TB!$B$4:$H$202,7,) -> 35000000 | J7: =I7-H7 -> 0
A8: 1900 | B8: 10320102 | C8: Assets | D8: FD - Investment in Fixed Deposit Receivable | E8: =VLOOKUP(D8,'Raw TB_26.04.2026 (SAP Paste)'!$C:$J,4,0) -> 0 | F8: =VLOOKUP(D8,'Raw TB_26.04.2026 (SAP Paste)'!$C:$J,6,0) -> 1.6622784e+08 | G8: =VLOOKUP(D8,'Raw TB_26.04.2026 (SAP Paste)'!$C:$J,7,0) -> 1.6622784e+08 | H8: =+VLOOKUP(D8,'Raw TB_26.04.2026 (SAP Paste)'!C:J,8,0) -> 0 | I8: =VLOOKUP(B8,TB!$B$4:$H$202,7,) -> 0 | J8: =I8-H8 -> 0
A9: 1900 | B9: 10400101 | C9: Assets | D9: Capital WIP | E9: =VLOOKUP(D9,'Raw TB_26.04.2026 (SAP Paste)'!$C:$J,4,0) -> 2.8127656e+09 | F9: =VLOOKUP(D9,'Raw TB_26.04.2026 (SAP Paste)'!$C:$J,6,0) -> 0 | G9: =VLOOKUP(D9,'Raw TB_26.04.2026 (SAP Paste)'!$C:$J,7,0) -> 0 | H9: =+VLOOKUP(D9,'Raw TB_26.04.2026 (SAP Paste)'!C:J,8,0) -> 2.8127656e+09 | I9: =VLOOKUP(B9,TB!$B$4:$H$202,7,) -> 2.8127656e+09 | J9: =I9-H9 -> 0
A10: 1900 | B10: 10500001 | C10: Assets | D10: Domestic Customers - Basic & Infra | E10: =VLOOKUP(D10,'Raw TB_26.04.2026 (SAP Paste)'!$C:$J,4,0) -> 8.3513225e+08 | F10: =VLOOKUP(D10,'Raw TB_26.04.2026 (SAP Paste)'!$C:$J,6,0) -> 82317594 | G10: =VLOOKUP(D10,'Raw TB_26.04.2026 (SAP Paste)'!$C:$J,7,0) -> 53683313 | H10: =+VLOOKUP(D10,'Raw TB_26.04.2026 (SAP Paste)'!C:J,8,0) -> 8.6376653e+08 | I10: =VLOOKUP(B10,TB!$B$4:$H$202,7,) -> 8.6376653e+08 | J10: =I10-H10 -> 0
A11: 1900 | B11: 10500002 | C11: Assets | D11: Domestic Customers - GST | E11: =VLOOKUP(D11,'Raw TB_26.04.2026 (SAP Paste)'!$C:$J,4,0) -> 45177027 | F11: =VLOOKUP(D11,'Raw TB_26.04.2026 (SAP Paste)'!$C:$J,6,0) -> 3583960.8 | G11: =VLOOKUP(D11,'Raw TB_26.04.2026 (SAP Paste)'!$C:$J,7,0) -> 1842689.6 | H11: =+VLOOKUP(D11,'Raw TB_26.04.2026 (SAP Paste)'!C:J,8,0) -> 46918298 | I11: =VLOOKUP(B11,TB!$B$4:$H$202,7,) -> 46918298 | J11: =I11-H11 -> 0
A12: 1900 | B12: 10500003 | C12: Assets | D12: Domestic Customers - SDR | E12: =VLOOKUP(D12,'Raw TB_26.04.2026 (SAP Paste)'!$C:$J,4,0) -> -22777476 | F12: =VLOOKUP(D12,'Raw TB_26.04.2026 (SAP Paste)'!$C:$J,6,0) -> 22831301 | G12: =VLOOKUP(D12,'Raw TB_26.04.2026 (SAP Paste)'!$C:$J,7,0) -> 24576201 | H12: =+VLOOKUP(D12,'Raw TB_26.04.2026 (SAP Paste)'!C:J,8,0) -> -24522376 | I12: =VLOOKUP(B12,TB!$B$4:$H$202,7,) -> -24522376 | J12: =I12-H12 -> 0
A13: 1900 | B13: 10500009 | C13: Assets | D13: Domestic Customers | E13: =VLOOKUP(D13,'Raw TB_26.04.2026 (SAP Paste)'!$C:$J,4,0) -> 2.611514e+08 | F13: =VLOOKUP(D13,'Raw TB_26.04.2026 (SAP Paste)'!$C:$J,6,0) -> 2.4050037e+08 | G13: =VLOOKUP(D13,'Raw TB_26.04.2026 (SAP Paste)'!$C:$J,7,0) -> 3.3088872e+08 | H13: =+VLOOKUP(D13,'Raw TB_26.04.2026 (SAP Paste)'!C:J,8,0) -> 1.7076304e+08 | I13: =VLOOKUP(B13,TB!$B$4:$H$202,7,) -> 1.7076304e+08 | J13: =I13-H13 -> 0
A14: 1900 | B14: 10500100 | C14: Assets | D14: Customer-Others | E14: =VLOOKUP(D14,'Raw TB_26.04.2026 (SAP Paste)'!$C:$J,4,0) -> 0 | F14: =VLOOKUP(D14,'Raw TB_26.04.2026 (SAP Paste)'!$C:$J,6,0) -> 2319592.6 | G14: =VLOOKUP(D14,'Raw TB_26.04.2026 (SAP Paste)'!$C:$J,7,0) -> 2319592.6 | H14: =+VLOOKUP(D14,'Raw TB_26.04.2026 (SAP Paste)'!C:J,8,0) -> 0 | I14: =VLOOKUP(B14,TB!$B$4:$H$202,7,) -> 0 | J14: =I14-H14 -> 0
A15: 1900 | B15: 10900002 | C15: Assets | D15: TDS on Sale of Residential Property 1 % Receivable | E15: =VLOOKUP(D15,'Raw TB_26.04.2026 (SAP Paste)'!$C:$J,4,0) -> 29382877 | F15: =VLOOKUP(D15,'Raw TB_26.04.2026 (SAP Paste)'!$C:$J,6,0) -> 5080952.9 | G15: =VLOOKUP(D15,'Raw TB_26.04.2026 (SAP Paste)'!$C:$J,7,0) -> 171474.45 | H15: =+VLOOKUP(D15,'Raw TB_26.04.2026 (SAP Paste)'!C:J,8,0) -> 34292355 | I15: =VLOOKUP(B15,TB!$B$4:$H$202,7,) -> 34292355 | J15: =I15-H15 -> 0
A16: 1900 | B16: 10910101 | C16: Assets | D16: FD - TDS on FD Interest | E16: =VLOOKUP(D16,'Raw TB_26.04.2026 (SAP Paste)'!$C:$J,4,0) -> 6220 | F16: =VLOOKUP(D16,'Raw TB_26.04.2026 (SAP Paste)'!$C:$J,6,0) -> 286789.98 | G16: =VLOOKUP(D16,'Raw TB_26.04.2026 (SAP Paste)'!$C:$J,7,0) -> 0 | H16: =+VLOOKUP(D16,'Raw TB_26.04.2026 (SAP Paste)'!C:J,8,0) -> 293009.98 | I16: =VLOOKUP(B16,TB!$B$4:$H$202,7,) -> 293009.98 | J16: =I16-H16 -> 0
A17: 1900 | B17: 10930002 | C17: Assets | D17: Advances to Employee | E17: =VLOOKUP(D17,'Raw TB_26.04.2026 (SAP Paste)'!$C:$J,4,0) -> 41467 | F17: =VLOOKUP(D17,'Raw TB_26.04.2026 (SAP Paste)'!$C:$J,6,0) -> 1008248 | G17: =VLOOKUP(D17,'Raw TB_26.04.2026 (SAP Paste)'!$C:$J,7,0) -> 851633 | H17: =+VLOOKUP(D17,'Raw TB_26.04.2026 (SAP Paste)'!C:J,8,0) -> 198082 | I17: =VLOOKUP(B17,TB!$B$4:$H$202,7,) -> 198082 | J17: =I17-H17 -> 0 | K17: Manoj Kumar Verma
A18: 1900 | B18: 10940001 | C18: Assets | D18: Cash | E18: =VLOOKUP(D18,'Raw TB_26.04.2026 (SAP Paste)'!$C:$J,4,0) -> 8605 | F18: =VLOOKUP(D18,'Raw TB_26.04.2026 (SAP Paste)'!$C:$J,6,0) -> 0 | G18: =VLOOKUP(D18,'Raw TB_26.04.2026 (SAP Paste)'!$C:$J,7,0) -> 500 | H18: =+VLOOKUP(D18,'Raw TB_26.04.2026 (SAP Paste)'!C:J,8,0) -> 8105 | I18: =VLOOKUP(B18,TB!$B$4:$H$202,7,) -> 8105 | J18: =I18-H18 -> 0
A19: 1900 | B19: 10951220 | C19: Assets | D19: IDBI- 0600102000012582- Collection A/c- Main | E19: =VLOOKUP(D19,'Raw TB_26.04.2026 (SAP Paste)'!$C:$J,4,0) -> 10000 | F19: =VLOOKUP(D19,'Raw TB_26.04.2026 (SAP Paste)'!$C:$J,6,0) -> 51819394 | G19: =VLOOKUP(D19,'Raw TB_26.04.2026 (SAP Paste)'!$C:$J,7,0) -> 51829394 | H19: =+VLOOKUP(D19,'Raw TB_26.04.2026 (SAP Paste)'!C:J,8,0) -> -0.01 | I19: =VLOOKUP(B19,TB!$B$4:$H$202,7,) -> -0.01 | J19: =I19-H19 -> 0
A20: 1900 | B20: 10951221 | C20: Assets | D20: IDBI- 0600102000012582- Collection A/c- Incoming | E20: =VLOOKUP(D20,'Raw TB_26.04.2026 (SAP Paste)'!$C:$J,4,0) -> 0 | F20: =VLOOKUP(D20,'Raw TB_26.04.2026 (SAP Paste)'!$C:$J,6,0) -> 59674302 | G20: =VLOOKUP(D20,'Raw TB_26.04.2026 (SAP Paste)'!$C:$J,7,0) -> 59674302 | H20: =+VLOOKUP(D20,'Raw TB_26.04.2026 (SAP Paste)'!C:J,8,0) -> 0 | I20: =VLOOKUP(B20,TB!$B$4:$H$202,7,) -> 0 | J20: =I20-H20 -> 0
A21: 1900 | B21: 10951222 | C21: Assets | D21: IDBI- 0600102000012582- Collection A/c- Outgoing | E21: =VLOOKUP(D21,'Raw TB_26.04.2026 (SAP Paste)'!$C:$J,4,0) -> 0 | F21: =VLOOKUP(D21,'Raw TB_26.04.2026 (SAP Paste)'!$C:$J,6,0) -> 50299509 | G21: =VLOOKUP(D21,'Raw TB_26.04.2026 (SAP Paste)'!$C:$J,7,0) -> 50299509 | H21: =+VLOOKUP(D21,'Raw TB_26.04.2026 (SAP Paste)'!C:J,8,0) -> 0 | I21: =VLOOKUP(B21,TB!$B$4:$H$202,7,) -> 0 | J21: =I21-H21 -> 0
A22: 1900 | B22: 10951230 | C22: Assets | D22: IDBI- 0600102000012591- RERA A/c- Main | E22: =VLOOKUP(D22,'Raw TB_26.04.2026 (SAP Paste)'!$C:$J,4,0) -> 1017434.2 | F22: =VLOOKUP(D22,'Raw TB_26.04.2026 (SAP Paste)'!$C:$J,6,0) -> 39480082 | G22: =VLOOKUP(D22,'Raw TB_26.04.2026 (SAP Paste)'!$C:$J,7,0) -> 40497516 | H22: =+VLOOKUP(D22,'Raw TB_26.04.2026 (SAP Paste)'!C:J,8,0) -> 0 | I22: =VLOOKUP(B22,TB!$B$4:$H$202,7,) -> 0 | J22: =I22-H22 -> 0
A23: 1900 | B23: 10951231 | C23: Assets | D23: IDBI- 0600102000012591- RERA A/c- Incoming | E23: =VLOOKUP(D23,'Raw TB_26.04.2026 (SAP Paste)'!$C:$J,4,0) -> 0 | F23: =VLOOKUP(D23,'Raw TB_26.04.2026 (SAP Paste)'!$C:$J,6,0) -> 34862417 | G23: =VLOOKUP(D23,'Raw TB_26.04.2026 (SAP Paste)'!$C:$J,7,0) -> 34862417 | H23: =+VLOOKUP(D23,'Raw TB_26.04.2026 (SAP Paste)'!C:J,8,0) -> 0 | I23: =VLOOKUP(B23,TB!$B$4:$H$202,7,) -> 0 | J23: =I23-H23 -> 0
A24: 1900 | B24: 10951232 | C24: Assets | D24: IDBI- 0600102000012591- RERA A/c- Outgoing | E24: =VLOOKUP(D24,'Raw TB_26.04.2026 (SAP Paste)'!$C:$J,4,0) -> 0 | F24: =VLOOKUP(D24,'Raw TB_26.04.2026 (SAP Paste)'!$C:$J,6,0) -> 46540189 | G24: =VLOOKUP(D24,'Raw TB_26.04.2026 (SAP Paste)'!$C:$J,7,0) -> 46540189 | H24: =+VLOOKUP(D24,'Raw TB_26.04.2026 (SAP Paste)'!C:J,8,0) -> 0 | I24: =VLOOKUP(B24,TB!$B$4:$H$202,7,) -> 0 | J24: =I24-H24 -> 0
A25: 1900 | B25: 10951240 | C25: Assets | D25: IDBI- 0600102000012607- Expenses A/c- Main | E25: =VLOOKUP(D25,'Raw TB_26.04.2026 (SAP Paste)'!$C:$J,4,0) -> 6119366.9 | F25: =VLOOKUP(D25,'Raw TB_26.04.2026 (SAP Paste)'!$C:$J,6,0) -> 9.6431089e+08 | G25: =VLOOKUP(D25,'Raw TB_26.04.2026 (SAP Paste)'!$C:$J,7,0) -> 9.6886082e+08 | H25: =+VLOOKUP(D25,'Raw TB_26.04.2026 (SAP Paste)'!C:J,8,0) -> 1569438.1 | I25: =VLOOKUP(B25,TB!$B$4:$H$202,7,) -> 1569438.1 | J25: =I25-H25 -> 0
A26: 1900 | B26: 10951241 | C26: Assets | D26: IDBI- 0600102000012607- Expenses A/c- Incoming | E26: =VLOOKUP(D26,'Raw TB_26.04.2026 (SAP Paste)'!$C:$J,4,0) -> 0 | F26: =VLOOKUP(D26,'Raw TB_26.04.2026 (SAP Paste)'!$C:$J,6,0) -> 1.1648538e+09 | G26: =VLOOKUP(D26,'Raw TB_26.04.2026 (SAP Paste)'!$C:$J,7,0) -> 1.1630593e+09 | H26: =+VLOOKUP(D26,'Raw TB_26.04.2026 (SAP Paste)'!C:J,8,0) -> 1794521 | I26: =VLOOKUP(B26,TB!$B$4:$H$202,7,) -> 1794521 | J26: =I26-H26 -> 0
A27: 1900 | B27: 10951242 | C27: Assets | D27: IDBI- 0600102000012607- Expenses A/c- Outgoing | E27: =VLOOKUP(D27,'Raw TB_26.04.2026 (SAP Paste)'!$C:$J,4,0) -> -5789326.8 | F27: =VLOOKUP(D27,'Raw TB_26.04.2026 (SAP Paste)'!$C:$J,6,0) -> 1.2204223e+09 | G27: =VLOOKUP(D27,'Raw TB_26.04.2026 (SAP Paste)'!$C:$J,7,0) -> 1.2147387e+09 | H27: =+VLOOKUP(D27,'Raw TB_26.04.2026 (SAP Paste)'!C:J,8,0) -> -105721 | I27: =VLOOKUP(B27,TB!$B$4:$H$202,7,) -> -105721 | J27: =I27-H27 -> 0
A28: 1900 | B28: 10951250 | C28: Assets | D28: IDBI- 0600102000012616- E-Tax A/c- Main | E28: =VLOOKUP(D28,'Raw TB_26.04.2026 (SAP Paste)'!$C:$J,4,0) -> 614400 | F28: =VLOOKUP(D28,'Raw TB_26.04.2026 (SAP Paste)'!$C:$J,6,0) -> 21508838 | G28: =VLOOKUP(D28,'Raw TB_26.04.2026 (SAP Paste)'!$C:$J,7,0) -> 22048853 | H28: =+VLOOKUP(D28,'Raw TB_26.04.2026 (SAP Paste)'!C:J,8,0) -> 74385.22 | I28: =VLOOKUP(B28,TB!$B$4:$H$202,7,) -> 74385.22 | J28: =I28-H28 -> 0
A29: 1900 | B29: 10951251 | C29: Assets | D29: IDBI- 0600102000012616- E-Tax A/c- Incoming | E29: =VLOOKUP(D29,'Raw TB_26.04.2026 (SAP Paste)'!$C:$J,4,0) -> 0 | F29: =VLOOKUP(D29,'Raw TB_26.04.2026 (SAP Paste)'!$C:$J,6,0) -> 27981803 | G29: =VLOOKUP(D29,'Raw TB_26.04.2026 (SAP Paste)'!$C:$J,7,0) -> 27981803 | H29: =+VLOOKUP(D29,'Raw TB_26.04.2026 (SAP Paste)'!C:J,8,0) -> 0 | I29: =VLOOKUP(B29,TB!$B$4:$H$202,7,) -> 0 | J29: =I29-H29 -> 0
... A137: 1900 | B137: 40500001 | C137: Expenses | D137: Consultancy & Architect Expenses | E137: =VLOOKUP(D137,'Raw TB_26.04.2026 (SAP Paste)'!$C:$J,4,0) -> 0 | F137: =VLOOKUP(D137,'Raw TB_26.04.2026 (SAP Paste)'!$C:$J,6,0) -> 11628000 | G137: =VLOOKUP(D137,'Raw TB_26.04.2026 (SAP Paste)'!$C:$J,7,0) -> 0 | H137: =+VLOOKUP(D137,'Raw TB_26.04.2026 (SAP Paste)'!C:J,8,0) -> 11628000 | I137: =VLOOKUP(B137,TB!$B$4:$H$202,7,) -> 11628000 | J137: =I137-H137 -> 0
A138: 1900 | B138: 40800052 | C138: Expenses | D138: Labour Charges -Security Guard | E138: =VLOOKUP(D138,'Raw TB_26.04.2026 (SAP Paste)'!$C:$J,4,0) -> 0 | F138: =VLOOKUP(D138,'Raw TB_26.04.2026 (SAP Paste)'!$C:$J,6,0) -> 904090.32 | G138: =VLOOKUP(D138,'Raw TB_26.04.2026 (SAP Paste)'!$C:$J,7,0) -> 156780 | H138: =+VLOOKUP(D138,'Raw TB_26.04.2026 (SAP Paste)'!C:J,8,0) -> 747310.32 | I138: =VLOOKUP(B138,TB!$B$4:$H$202,7,) -> 747310.32 | J138: =I138-H138 -> 0 | K138: Direct | L138: Indirect | M138: Total | N138: As per TB | O138: Difference
A139: 1900 | B139: 45100001 | C139: Expenses | D139: Salary A/c | E139: =VLOOKUP(D139,'Raw TB_26.04.2026 (SAP Paste)'!$C:$J,4,0) -> 0 | F139: =VLOOKUP(D139,'Raw TB_26.04.2026 (SAP Paste)'!$C:$J,6,0) -> 58040948 | G139: =VLOOKUP(D139,'Raw TB_26.04.2026 (SAP Paste)'!$C:$J,7,0) -> 34210 | H139: =+VLOOKUP(D139,'Raw TB_26.04.2026 (SAP Paste)'!C:J,8,0) -> 58006738 | I139: =VLOOKUP(B139,TB!$B$4:$H$202,7,) -> 58006738 | J139: =I139-H139 -> 0 | K139: ='WIP Final'!G272 -> 47912268 | L139: ='WIP Final'!G273 -> 10477308 | M139: =K139+L139 -> 58389576 | N139: =H139+H140 -> 58389576 | O139: =M139-N139 -> 0
A140: 1900 | B140: 45100005 | C140: Expenses | D140: Employee Bonus | E140: =VLOOKUP(D140,'Raw TB_26.04.2026 (SAP Paste)'!$C:$J,4,0) -> 0 | F140: =VLOOKUP(D140,'Raw TB_26.04.2026 (SAP Paste)'!$C:$J,6,0) -> 402674 | G140: =VLOOKUP(D140,'Raw TB_26.04.2026 (SAP Paste)'!$C:$J,7,0) -> 19836 | H140: =+VLOOKUP(D140,'Raw TB_26.04.2026 (SAP Paste)'!C:J,8,0) -> 382838 | I140: =VLOOKUP(B140,TB!$B$4:$H$202,7,) -> 382838 | J140: =I140-H140 -> 0
A141: 1900 | B141: 45100021 | C141: Expenses | D141: Conveyance Expenses | E141: =VLOOKUP(D141,'Raw TB_26.04.2026 (SAP Paste)'!$C:$J,4,0) -> 0 | F141: =VLOOKUP(D141,'Raw TB_26.04.2026 (SAP Paste)'!$C:$J,6,0) -> 1510470 | G141: =VLOOKUP(D141,'Raw TB_26.04.2026 (SAP Paste)'!$C:$J,7,0) -> 0 | H141: =+VLOOKUP(D141,'Raw TB_26.04.2026 (SAP Paste)'!C:J,8,0) -> 1510470 | I141: =VLOOKUP(B141,TB!$B$4:$H$202,7,) -> 1510470 | J141: =I141-H141 -> 0
A142: 1900 | B142: 45100052 | C142: Expenses | D142: PF Employer Contribution | E142: =VLOOKUP(D142,'Raw TB_26.04.2026 (SAP Paste)'!$C:$J,4,0) -> 0 | F142: =VLOOKUP(D142,'Raw TB_26.04.2026 (SAP Paste)'!$C:$J,6,0) -> 1450574 | G142: =VLOOKUP(D142,'Raw TB_26.04.2026 (SAP Paste)'!$C:$J,7,0) -> 0 | H142: =+VLOOKUP(D142,'Raw TB_26.04.2026 (SAP Paste)'!C:J,8,0) -> 1450574 | I142: =VLOOKUP(B142,TB!$B$4:$H$202,7,) -> 1450574 | J142: =I142-H142 -> 0
A143: 1900 | B143: 45100053 | C143: Expenses | D143: EDLI Contribution | E143: =VLOOKUP(D143,'Raw TB_26.04.2026 (SAP Paste)'!$C:$J,4,0) -> 0 | F143: =VLOOKUP(D143,'Raw TB_26.04.2026 (SAP Paste)'!$C:$J,6,0) -> 60446 | G143: =VLOOKUP(D143,'Raw TB_26.04.2026 (SAP Paste)'!$C:$J,7,0) -> 0 | H143: =+VLOOKUP(D143,'Raw TB_26.04.2026 (SAP Paste)'!C:J,8,0) -> 60446 | I143: =VLOOKUP(B143,TB!$B$4:$H$202,7,) -> 60446 | J143: =I143-H143 -> 0
A144: 1900 | B144: 45100054 | C144: Expenses | D144: PF Admin Charges | E144: =VLOOKUP(D144,'Raw TB_26.04.2026 (SAP Paste)'!$C:$J,4,0) -> 0 | F144: =VLOOKUP(D144,'Raw TB_26.04.2026 (SAP Paste)'!$C:$J,6,0) -> 60440 | G144: =VLOOKUP(D144,'Raw TB_26.04.2026 (SAP Paste)'!$C:$J,7,0) -> 0 | H144: =+VLOOKUP(D144,'Raw TB_26.04.2026 (SAP Paste)'!C:J,8,0) -> 60440 | I144: =VLOOKUP(B144,TB!$B$4:$H$202,7,) -> 60440 | J144: =I144-H144 -> 0
A145: 1900 | B145: 45100055 | C145: Expenses | D145: Other Deduction related to Personnel Cost | E145: =VLOOKUP(D145,'Raw TB_26.04.2026 (SAP Paste)'!$C:$J,4,0) -> 0 | F145: =VLOOKUP(D145,'Raw TB_26.04.2026 (SAP Paste)'!$C:$J,6,0) -> 23678 | G145: =VLOOKUP(D145,'Raw TB_26.04.2026 (SAP Paste)'!$C:$J,7,0) -> 23678 | H145: =+VLOOKUP(D145,'Raw TB_26.04.2026 (SAP Paste)'!C:J,8,0) -> 0 | I145: =VLOOKUP(B145,TB!$B$4:$H$202,7,) -> 0 | J145: =I145-H145 -> 0
A146: 1900 | B146: 45100056 | C146: Expenses | D146: Employer Contribution at ESIC | E146: =VLOOKUP(D146,'Raw TB_26.04.2026 (SAP Paste)'!$C:$J,4,0) -> 0 | F146: =VLOOKUP(D146,'Raw TB_26.04.2026 (SAP Paste)'!$C:$J,6,0) -> 13502 | G146: =VLOOKUP(D146,'Raw TB_26.04.2026 (SAP Paste)'!$C:$J,7,0) -> 13502 | H146: =+VLOOKUP(D146,'Raw TB_26.04.2026 (SAP Paste)'!C:J,8,0) -> 0 | I146: =VLOOKUP(B146,TB!$B$4:$H$202,7,) -> 0 | J146: =I146-H146 -> 0
A147: 1900 | B147: 45100059 | C147: Expenses | D147: MLWF Employer Contribution | E147: =VLOOKUP(D147,'Raw TB_26.04.2026 (SAP Paste)'!$C:$J,4,0) -> 0 | F147: =VLOOKUP(D147,'Raw TB_26.04.2026 (SAP Paste)'!$C:$J,6,0) -> 12525 | G147: =VLOOKUP(D147,'Raw TB_26.04.2026 (SAP Paste)'!$C:$J,7,0) -> 0 | H147: =+VLOOKUP(D147,'Raw TB_26.04.2026 (SAP Paste)'!C:J,8,0) -> 12525 | I147: =VLOOKUP(B147,TB!$B$4:$H$202,7,) -> 12525 | J147: =I147-H147 -> 0
A148: 1900 | B148: 45200003 | C148: Expenses | D148: Printing & Stationery | E148: =VLOOKUP(D148,'Raw TB_26.04.2026 (SAP Paste)'!$C:$J,4,0) -> 0 | F148: =VLOOKUP(D148,'Raw TB_26.04.2026 (SAP Paste)'!$C:$J,6,0) -> 64593.2 | G148: =VLOOKUP(D148,'Raw TB_26.04.2026 (SAP Paste)'!$C:$J,7,0) -> 14451 | H148: =+VLOOKUP(D148,'Raw TB_26.04.2026 (SAP Paste)'!C:J,8,0) -> 50142.2 | I148: =VLOOKUP(B148,TB!$B$4:$H$202,7,) -> 50142.2 | J148: =I148-H148 -> 0
A149: 1900 | B149: 45200004 | C149: Expenses | D149: Professional Fees | E149: =VLOOKUP(D149,'Raw TB_26.04.2026 (SAP Paste)'!$C:$J,4,0) -> 0 | F149: =VLOOKUP(D149,'Raw TB_26.04.2026 (SAP Paste)'!$C:$J,6,0) -> 765000 | G149: =VLOOKUP(D149,'Raw TB_26.04.2026 (SAP Paste)'!$C:$J,7,0) -> 380000 | H149: =+VLOOKUP(D149,'Raw TB_26.04.2026 (SAP Paste)'!C:J,8,0) -> 385000 | I149: =VLOOKUP(B149,TB!$B$4:$H$202,7,) -> 385000 | J149: =I149-H149 -> 0
A150: 1900 | B150: 45200005 | C150: Expenses | D150: Repair & Maintenance | E150: =VLOOKUP(D150,'Raw TB_26.04.2026 (SAP Paste)'!$C:$J,4,0) -> 0 | F150: =VLOOKUP(D150,'Raw TB_26.04.2026 (SAP Paste)'!$C:$J,6,0) -> 451548.28 | G150: =VLOOKUP(D150,'Raw TB_26.04.2026 (SAP Paste)'!$C:$J,7,0) -> 50974.99 | H150: =+VLOOKUP(D150,'Raw TB_26.04.2026 (SAP Paste)'!C:J,8,0) -> 400573.29 | I150: =VLOOKUP(B150,TB!$B$4:$H$202,7,) -> 400573.29 | J150: =I150-H150 -> 0
A151: 1900 | B151: 45200006 | C151: Expenses | D151: Round Off Expense | E151: =VLOOKUP(D151,'Raw TB_26.04.2026 (SAP Paste)'!$C:$J,4,0) -> 0 | F151: =VLOOKUP(D151,'Raw TB_26.04.2026 (SAP Paste)'!$C:$J,6,0) -> 34.36 | G151: =VLOOKUP(D151,'Raw TB_26.04.2026 (SAP Paste)'!$C:$J,7,0) -> 13.04 | H151: =+VLOOKUP(D151,'Raw TB_26.04.2026 (SAP Paste)'!C:J,8,0) -> 21.32 | I151: =VLOOKUP(B151,TB!$B$4:$H$202,7,) -> 21.32 | J151: =I151-H151 -> 0
... A166: 1900 | B166: 10910011 | C166: Assets | D166: TDS Receivable - Aditya Birla Capital limited | E166: =VLOOKUP(D166,'Raw TB_26.04.2026 (SAP Paste)'!$C:$J,4,0) -> 0 | F166: =VLOOKUP(D166,'Raw TB_26.04.2026 (SAP Paste)'!$C:$J,6,0) -> 5563060.9 | G166: =VLOOKUP(D166,'Raw TB_26.04.2026 (SAP Paste)'!$C:$J,7,0) -> 713183.9 | H166: =+VLOOKUP(D166,'Raw TB_26.04.2026 (SAP Paste)'!C:J,8,0) -> 4849877 | I166: =VLOOKUP(B166,TB!$B$4:$H$202,7,) -> 4849877 | J166: =I166-H166 -> 0
A167: 1900 | B167: 10930001 | C167: Assets | D167: Advance to Vendor | E167: =VLOOKUP(D167,'Raw TB_26.04.2026 (SAP Paste)'!$C:$J,4,0) -> 0 | F167: =VLOOKUP(D167,'Raw TB_26.04.2026 (SAP Paste)'!$C:$J,6,0) -> 120000 | G167: =VLOOKUP(D167,'Raw TB_26.04.2026 (SAP Paste)'!$C:$J,7,0) -> 100000 | H167: =+VLOOKUP(D167,'Raw TB_26.04.2026 (SAP Paste)'!C:J,8,0) -> 20000 | I167: =VLOOKUP(B167,TB!$B$4:$H$202,7,) -> 20000 | J167: =I167-H167 -> 0 | K167: BHANDARI SAAJ & ASSOCIATES
A168: 1900 | B168: 10951262 | C168: Assets | D168: IDBI- 0600102000012625- Maintenance A/c- Outgoing | E168: =VLOOKUP(D168,'Raw TB_26.04.2026 (SAP Paste)'!$C:$J,4,0) -> 0 | F168: =VLOOKUP(D168,'Raw TB_26.04.2026 (SAP Paste)'!$C:$J,6,0) -> 1.47 | G168: =VLOOKUP(D168,'Raw TB_26.04.2026 (SAP Paste)'!$C:$J,7,0) -> 1.47 | H168: =+VLOOKUP(D168,'Raw TB_26.04.2026 (SAP Paste)'!C:J,8,0) -> 0 | I168: =VLOOKUP(B168,TB!$B$4:$H$202,7,) -> 0 | J168: =I168-H168 -> 0
A169: 1900 | B169: 10952662 | C169: Assets | D169: IDBI- 0600102000013916- Rera A/c- Outgoing | E169: =VLOOKUP(D169,'Raw TB_26.04.2026 (SAP Paste)'!$C:$J,4,0) -> 0 | F169: =VLOOKUP(D169,'Raw TB_26.04.2026 (SAP Paste)'!$C:$J,6,0) -> 25000 | G169: =VLOOKUP(D169,'Raw TB_26.04.2026 (SAP Paste)'!$C:$J,7,0) -> 25000 | H169: =+VLOOKUP(D169,'Raw TB_26.04.2026 (SAP Paste)'!C:J,8,0) -> 0 | I169: =VLOOKUP(B169,TB!$B$4:$H$202,7,) -> 0 | J169: =I169-H169 -> 0
A170: 1900 | B170: 10952671 | C170: Assets | D170: IDBI- 0600102000013891- Expenses A/c- Incoming | E170: =VLOOKUP(D170,'Raw TB_26.04.2026 (SAP Paste)'!$C:$J,4,0) -> 0 | F170: =VLOOKUP(D170,'Raw TB_26.04.2026 (SAP Paste)'!$C:$J,6,0) -> 1500 | G170: =VLOOKUP(D170,'Raw TB_26.04.2026 (SAP Paste)'!$C:$J,7,0) -> 1500 | H170: =+VLOOKUP(D170,'Raw TB_26.04.2026 (SAP Paste)'!C:J,8,0) -> 0 | I170: =VLOOKUP(B170,TB!$B$4:$H$202,7,) -> 0 | J170: =I170-H170 -> 0
A171: 1900 | B171: 10952672 | C171: Assets | D171: IDBI - 0600102000013891-Expenses A/c- Outgoing | E171: =VLOOKUP(D171,'Raw TB_26.04.2026 (SAP Paste)'!$C:$J,4,0) -> 0 | F171: =VLOOKUP(D171,'Raw TB_26.04.2026 (SAP Paste)'!$C:$J,6,0) -> 26761 | G171: =VLOOKUP(D171,'Raw TB_26.04.2026 (SAP Paste)'!$C:$J,7,0) -> 26761 | H171: =+VLOOKUP(D171,'Raw TB_26.04.2026 (SAP Paste)'!C:J,8,0) -> 0 | I171: =VLOOKUP(B171,TB!$B$4:$H$202,7,) -> 0 | J171: =I171-H171 -> 0
A172: 1900 | B172: 10952681 | C172: Assets | D172: IDBI- 0600102000013907- Rera A/c- Incoming | E172: =VLOOKUP(D172,'Raw TB_26.04.2026 (SAP Paste)'!$C:$J,4,0) -> 0 | F172: =VLOOKUP(D172,'Raw TB_26.04.2026 (SAP Paste)'!$C:$J,6,0) -> 1000 | G172: =VLOOKUP(D172,'Raw TB_26.04.2026 (SAP Paste)'!$C:$J,7,0) -> 1000 | H172: =+VLOOKUP(D172,'Raw TB_26.04.2026 (SAP Paste)'!C:J,8,0) -> 0 | I172: =VLOOKUP(B172,TB!$B$4:$H$202,7,) -> 0 | J172: =I172-H172 -> 0
A173: 1900 | B173: 10952682 | C173: Assets | D173: IDBI- 0600102000013907- Rera A/c- Outgoing | E173: =VLOOKUP(D173,'Raw TB_26.04.2026 (SAP Paste)'!$C:$J,4,0) -> 0 | F173: =VLOOKUP(D173,'Raw TB_26.04.2026 (SAP Paste)'!$C:$J,6,0) -> 27351 | G173: =VLOOKUP(D173,'Raw TB_26.04.2026 (SAP Paste)'!$C:$J,7,0) -> 27351 | H173: =+VLOOKUP(D173,'Raw TB_26.04.2026 (SAP Paste)'!C:J,8,0) -> 0 | I173: =VLOOKUP(B173,TB!$B$4:$H$202,7,) -> 0 | J173: =I173-H173 -> 0
A174: 1900 | B174: 11140001 | C174: Assets | D174: Prepaid Insurance | E174: =VLOOKUP(D174,'Raw TB_26.04.2026 (SAP Paste)'!$C:$J,4,0) -> 0 | F174: =VLOOKUP(D174,'Raw TB_26.04.2026 (SAP Paste)'!$C:$J,6,0) -> 391553 | G174: =VLOOKUP(D174,'Raw TB_26.04.2026 (SAP Paste)'!$C:$J,7,0) -> 0 | H174: =+VLOOKUP(D174,'Raw TB_26.04.2026 (SAP Paste)'!C:J,8,0) -> 391553 | I174: =VLOOKUP(B174,TB!$B$4:$H$202,7,) -> 391553 | J174: =I174-H174 -> 0
A175: 1900 | B175: 20000203 | C175: Liabilities | D175: Current Capital - Vineet Goyal | E175: =VLOOKUP(D175,'Raw TB_26.04.2026 (SAP Paste)'!$C:$J,4,0) -> 0 | F175: =VLOOKUP(D175,'Raw TB_26.04.2026 (SAP Paste)'!$C:$J,6,0) -> 8000000 | G175: =VLOOKUP(D175,'Raw TB_26.04.2026 (SAP Paste)'!$C:$J,7,0) -> 8000000 | H175: =+VLOOKUP(D175,'Raw TB_26.04.2026 (SAP Paste)'!C:J,8,0) -> 0 | I175: =VLOOKUP(B175,TB!$B$4:$H$202,7,) -> 0 | J175: =I175-H175 -> 0
A176: 1900 | B176: 20412002 | C176: Liabilities | D176: Output SGST 0.5% Payable | E176: =VLOOKUP(D176,'Raw TB_26.04.2026 (SAP Paste)'!$C:$J,4,0) -> 0 | F176: =VLOOKUP(D176,'Raw TB_26.04.2026 (SAP Paste)'!$C:$J,6,0) -> 180481 | G176: =VLOOKUP(D176,'Raw TB_26.04.2026 (SAP Paste)'!$C:$J,7,0) -> 180481 | H176: =+VLOOKUP(D176,'Raw TB_26.04.2026 (SAP Paste)'!C:J,8,0) -> 0 | I176: =VLOOKUP(B176,TB!$B$4:$H$202,7,) -> 0 | J176: =I176-H176 -> 0
A177: 1900 | B177: 20415003 | C177: Liabilities | D177: TDS Payable on Interest (194A) | E177: =VLOOKUP(D177,'Raw TB_26.04.2026 (SAP Paste)'!$C:$J,4,0) -> 0 | F177: =VLOOKUP(D177,'Raw TB_26.04.2026 (SAP Paste)'!$C:$J,6,0) -> 1616152 | G177: =VLOOKUP(D177,'Raw TB_26.04.2026 (SAP Paste)'!$C:$J,7,0) -> 6024009.9 | H177: =+VLOOKUP(D177,'Raw TB_26.04.2026 (SAP Paste)'!C:J,8,0) -> -4407857.9 | I177: =VLOOKUP(B177,TB!$B$4:$H$202,7,) -> -4407857.9 | J177: =I177-H177 -> 0
A178: 1900 | B178: 20420009 | C178: Liabilities | D178: PTEC Payable | E178: =VLOOKUP(D178,'Raw TB_26.04.2026 (SAP Paste)'!$C:$J,4,0) -> 0 | F178: =VLOOKUP(D178,'Raw TB_26.04.2026 (SAP Paste)'!$C:$J,6,0) -> 2500 | G178: =VLOOKUP(D178,'Raw TB_26.04.2026 (SAP Paste)'!$C:$J,7,0) -> 5000 | H178: =+VLOOKUP(D178,'Raw TB_26.04.2026 (SAP Paste)'!C:J,8,0) -> -2500 | I178: =VLOOKUP(B178,TB!$B$4:$H$202,7,) -> -2500 | J178: =I178-H178 -> 0
A179: 1900 | B179: 40100005 | C179: Expenses | D179: Site Engineering Expenses | E179: =VLOOKUP(D179,'Raw TB_26.04.2026 (SAP Paste)'!$C:$J,4,0) -> 0 | F179: =VLOOKUP(D179,'Raw TB_26.04.2026 (SAP Paste)'!$C:$J,6,0) -> 147188 | G179: =VLOOKUP(D179,'Raw TB_26.04.2026 (SAP Paste)'!$C:$J,7,0) -> 0 | H179: =+VLOOKUP(D179,'Raw TB_26.04.2026 (SAP Paste)'!C:J,8,0) -> 147188 | I179: =VLOOKUP(B179,TB!$B$4:$H$202,7,) -> 147188 | J179: =I179-H179 -> 0
... A191: 1900 | B191: 45300002 | C191: Expenses | D191: SGST Indirect Expenses | E191: =VLOOKUP(D191,'Raw TB_26.04.2026 (SAP Paste)'!$C:$J,4,0) -> 0 | F191: =VLOOKUP(D191,'Raw TB_26.04.2026 (SAP Paste)'!$C:$J,6,0) -> 2134989 | G191: =VLOOKUP(D191,'Raw TB_26.04.2026 (SAP Paste)'!$C:$J,7,0) -> 239957.07 | H191: =+VLOOKUP(D191,'Raw TB_26.04.2026 (SAP Paste)'!C:J,8,0) -> 1895032 | I191: =VLOOKUP(B191,TB!$B$4:$H$202,7,) -> 1894672 | J191: =I191-H191 -> -360
A192: 1900 | B192: 45300003 | C192: Expenses | D192: IGST Indirect Expenses | E192: =VLOOKUP(D192,'Raw TB_26.04.2026 (SAP Paste)'!$C:$J,4,0) -> 0 | F192: =VLOOKUP(D192,'Raw TB_26.04.2026 (SAP Paste)'!$C:$J,6,0) -> 64028.52 | G192: =VLOOKUP(D192,'Raw TB_26.04.2026 (SAP Paste)'!$C:$J,7,0) -> 64028.52 | H192: =+VLOOKUP(D192,'Raw TB_26.04.2026 (SAP Paste)'!C:J,8,0) -> 0 | I192: =VLOOKUP(B192,TB!$B$4:$H$202,7,) -> 0 | J192: =I192-H192 -> 0 | M192: 15 Days ABFL Interest Payable | N192: Other interest | P192: Unsecured loan interest | Q192: ABFL Loan Interest
A193: 1900 | B193: 45520001 | C193: Expenses | D193: Interest Paid on Loan | E193: =VLOOKUP(D193,'Raw TB_26.04.2026 (SAP Paste)'!$C:$J,4,0) -> 0 | F193: =VLOOKUP(D193,'Raw TB_26.04.2026 (SAP Paste)'!$C:$J,6,0) -> 67296060 | G193: =VLOOKUP(D193,'Raw TB_26.04.2026 (SAP Paste)'!$C:$J,7,0) -> 6415229 | H193: =+VLOOKUP(D193,'Raw TB_26.04.2026 (SAP Paste)'!C:J,8,0) -> 60880831 | I193: =VLOOKUP(B193,TB!$B$4:$H$202,7,) -> 60880831 | J193: =I193-H193 -> 0 | M193: 1551002 | N193: ='Raw TB_26.04.2026 (SAP Paste)'!J202-M193 -> 59329829 | P193: 12382060 | Q193: ='Raw TB_26.04.2026 (SAP Paste)'!J202-P193 -> 48498771
A194: 1900 | B194: 90000001 | D194: Migration Account - Assets | E194: =VLOOKUP(D194,'Raw TB_26.04.2026 (SAP Paste)'!$C:$J,4,0) -> -8605 | F194: =VLOOKUP(D194,'Raw TB_26.04.2026 (SAP Paste)'!$C:$J,6,0) -> 0 | G194: =VLOOKUP(D194,'Raw TB_26.04.2026 (SAP Paste)'!$C:$J,7,0) -> 0 | H194: =+VLOOKUP(D194,'Raw TB_26.04.2026 (SAP Paste)'!C:J,8,0) -> -8605 | I194: 0 | J194: 0
A195: 1900 | B195: 90000002 | D195: Migration Account - Inventory | E195: =VLOOKUP(D195,'Raw TB_26.04.2026 (SAP Paste)'!$C:$J,4,0) -> -1.888422e+09 | F195: =VLOOKUP(D195,'Raw TB_26.04.2026 (SAP Paste)'!$C:$J,6,0) -> 0 | G195: =VLOOKUP(D195,'Raw TB_26.04.2026 (SAP Paste)'!$C:$J,7,0) -> 0 | H195: =+VLOOKUP(D195,'Raw TB_26.04.2026 (SAP Paste)'!C:J,8,0) -> -1.888422e+09 | I195: 0 | J195: 0
A196: 1900 | B196: 90000003 | D196: Migration Account - Customers | E196: =VLOOKUP(D196,'Raw TB_26.04.2026 (SAP Paste)'!$C:$J,4,0) -> 1.3295484e+08 | F196: =VLOOKUP(D196,'Raw TB_26.04.2026 (SAP Paste)'!$C:$J,6,0) -> 21662823 | G196: =VLOOKUP(D196,'Raw TB_26.04.2026 (SAP Paste)'!$C:$J,7,0) -> 21662823 | H196: =+VLOOKUP(D196,'Raw TB_26.04.2026 (SAP Paste)'!C:J,8,0) -> 1.3295484e+08 | I196: 0 | J196: 0
A197: 1900 | B197: 90000004 | D197: Migration Account - Vendor | E197: =VLOOKUP(D197,'Raw TB_26.04.2026 (SAP Paste)'!$C:$J,4,0) -> 538919625 | F197: =VLOOKUP(D197,'Raw TB_26.04.2026 (SAP Paste)'!$C:$J,6,0) -> 0 | G197: =VLOOKUP(D197,'Raw TB_26.04.2026 (SAP Paste)'!$C:$J,7,0) -> 0 | H197: =+VLOOKUP(D197,'Raw TB_26.04.2026 (SAP Paste)'!C:J,8,0) -> 538919625 | I197: 0 | J197: 0
A198: 1900 | B198: 90000005 | D198: Migration Account - GL | E198: =VLOOKUP(D198,'Raw TB_26.04.2026 (SAP Paste)'!$C:$J,4,0) -> 1.2165561e+09 | F198: =VLOOKUP(D198,'Raw TB_26.04.2026 (SAP Paste)'!$C:$J,6,0) -> 0 | G198: =VLOOKUP(D198,'Raw TB_26.04.2026 (SAP Paste)'!$C:$J,7,0) -> 0 | H198: =+VLOOKUP(D198,'Raw TB_26.04.2026 (SAP Paste)'!C:J,8,0) -> 1.2165561e+09 | I198: 0 | J198: 0
A199: 1900 | B199: 11110011 | C199: Assets | D199: PF Excess Paid | E199: =VLOOKUP(D199,'Raw TB_26.04.2026 (SAP Paste)'!$C:$J,4,0) -> 0 | F199: =VLOOKUP(D199,'Raw TB_26.04.2026 (SAP Paste)'!$C:$J,6,0) -> 147 | G199: =VLOOKUP(D199,'Raw TB_26.04.2026 (SAP Paste)'!$C:$J,7,0) -> 0 | H199: =+VLOOKUP(D199,'Raw TB_26.04.2026 (SAP Paste)'!C:J,8,0) -> 147 | I199: =VLOOKUP(B199,TB!$B$4:$H$202,7,) -> 147 | J199: =I199-H199 -> 0
A200: 1900 | B200: 45400018 | C200: Expenses | D200: Advertising Expenses | E200: =VLOOKUP(D200,'Raw TB_26.04.2026 (SAP Paste)'!$C:$J,4,0) -> 0 | F200: =VLOOKUP(D200,'Raw TB_26.04.2026 (SAP Paste)'!$C:$J,6,0) -> 29760 | G200: =VLOOKUP(D200,'Raw TB_26.04.2026 (SAP Paste)'!$C:$J,7,0) -> 0 | H200: =+VLOOKUP(D200,'Raw TB_26.04.2026 (SAP Paste)'!C:J,8,0) -> 29760 | I200: =VLOOKUP(B200,TB!$B$4:$H$202,7,) -> 15360 | J200: =I200-H200 -> -14400
A201: 1900 | B201: 45510053 | C201: Expenses | D201: Penalty/Fine/Damages | E201: =VLOOKUP(D201,'Raw TB_26.04.2026 (SAP Paste)'!$C:$J,4,0) -> 0 | F201: =VLOOKUP(D201,'Raw TB_26.04.2026 (SAP Paste)'!$C:$J,6,0) -> 1000000 | G201: =VLOOKUP(D201,'Raw TB_26.04.2026 (SAP Paste)'!$C:$J,7,0) -> 0 | H201: =+VLOOKUP(D201,'Raw TB_26.04.2026 (SAP Paste)'!C:J,8,0) -> 1000000 | I201: =VLOOKUP(B201,TB!$B$4:$H$202,7,) -> 1000000 | J201: =I201-H201 -> 0
A202: 1900 | B202: 45520026 | C202: Expenses | D202: Deffered Tax - P&L | E202: =VLOOKUP(D202,'Raw TB_26.04.2026 (SAP Paste)'!$C:$J,4,0) -> 0 | F202: =VLOOKUP(D202,'Raw TB_26.04.2026 (SAP Paste)'!$C:$J,6,0) -> 0 | G202: =VLOOKUP(D202,'Raw TB_26.04.2026 (SAP Paste)'!$C:$J,7,0) -> 1910 | H202: =+VLOOKUP(D202,'Raw TB_26.04.2026 (SAP Paste)'!C:J,8,0) -> -1910 | I202: =VLOOKUP(B202,TB!$B$4:$H$202,7,) -> -1910 | J202: =I202-H202 -> 0
A203: 1900 | B203: 11150001 | C203: Assets | D203: Income Tax Refund | E203: =VLOOKUP(D203,'Raw TB_26.04.2026 (SAP Paste)'!$C:$J,4,0) -> 0 | F203: =VLOOKUP(D203,'Raw TB_26.04.2026 (SAP Paste)'!$C:$J,6,0) -> 0 | G203: 6530 | H203: -6530 | I203: =VLOOKUP(B203,TB!$B$4:$H$202,7,) -> -6530 | J203: =I203-H203 -> 0
A204: 1900 | B204: 30000072 | C204: Income | D204: Sale of - Land | E204: =VLOOKUP(D204,'Raw TB_26.04.2026 (SAP Paste)'!$C:$J,4,0) -> 0 | F204: =VLOOKUP(D204,'Raw TB_26.04.2026 (SAP Paste)'!$C:$J,6,0) -> 0 | G204: 362900000 | H204: -362900000 | I204: =VLOOKUP(B204,TB!$B$4:$H$202,7,) -> -362900000 | J204: =I204-H204 -> 0
A205: 1900 | B205: 40900201 | C205: Expenses | D205: Stamp Duty & Registration Expenses - on Land Purch | E205: =VLOOKUP(D205,'Raw TB_26.04.2026 (SAP Paste)'!$C:$J,4,0) -> 0 | F205: 300000 | G205: 0 | H205: 300000 | I205: =VLOOKUP(B205,TB!$B$4:$H$202,7,) -> 300000 | J205: =I205-H205 -> 0
A206: 1900 | B206: 45520021 | C206: Expenses | D206: Interest On Late Payment of TDS | E206: =VLOOKUP(D206,'Raw TB_26.04.2026 (SAP Paste)'!$C:$J,4,0) -> 0 | F206: 88645 | G206: 0 | H206: 88645 | I206: =VLOOKUP(B206,TB!$B$4:$H$202,7,) -> 86645 | J206: =I206-H206 -> -2000
A207: 1900 | B207: 10910012 | C207: Assets | D207: TDS Payable (Excess Paid) | E207: =VLOOKUP(D207,'Raw TB_26.04.2026 (SAP Paste)'!$C:$J,4,0) -> 0 | F207: 465249.11 | G207: 442019.11 | H207: 23230 | I207: =VLOOKUP(B207,TB!$B$4:$H$202,7,) -> 23230 | J207: =I207-H207 -> 0

Sheet TB
D2: 0 | E2: - | F2: 15921197678 | G2: 15921197678 | H2: 0
A3: Company Code | B3: G/L Account | C3: G/L Acct Long Text | D3: Balance Carryforward | E3: Balance of Prior Periods | F3: Debit Blnce of Reportng Period | G3: Credit Balance Reporting Per. | H3: Accumulated Balance
A4: 1900 | B4: 10000070 | C4: Office Equipments | D4: 54811 | E4: 0 | F4: 0 | G4: 0 | H4: 54811
A5: 1900 | B5: 10001070 | C5: Accumulated Dep - Office Equipments | D5: -22469.87 | E5: 0 | F5: 0 | G5: 14576.15 | H5: -37046.02
A6: 1900 | B6: 10320101 | C6: FD - Investment in Fixed Deposit | D6: 1000000 | E6: 0 | F6: 2.0040348e+08 | G6: 1.6640348e+08 | H6: 35000000
A7: 1900 | B7: 10320102 | C7: FD - Investment in Fixed Deposit Receivable | D7: 0 | E7: 0 | F7: 1.6622784e+08 | G7: 1.6622784e+08 | H7: 0
A8: 1900 | B8: 10400101 | C8: Capital WIP | D8: 2.8127656e+09 | E8: 0 | F8: 0 | G8: 0 | H8: 2.8127656e+09
A9: 1900 | B9: 10500001 | C9: Domestic Customers - Basic & Infra | D9: 8.3513225e+08 | E9: 0 | F9: 86220252 | G9: 57585971 | H9: 8.6376653e+08
A10: 1900 | B10: 10500002 | C10: Domestic Customers - GST | D10: 45177027 | E10: 0 | F10: 3779093.7 | G10: 2037822.5 | H10: 46918298
A11: 1900 | B11: 10500003 | C11: Domestic Customers - SDR | D11: -22777476 | E11: 0 | F11: 22831301 | G11: 24576201 | H11: -24522376
A12: 1900 | B12: 10500009 | C12: Domestic Customers | D12: 2.611514e+08 | E12: 0 | F12: 2.4050037e+08 | G12: 3.3088872e+08 | H12: 1.7076304e+08
A13: 1900 | B13: 10500100 | C13: Customer-Others | D13: 0 | E13: 0 | F13: 2319592.6 | G13: 2319592.6 | H13: 0
A14: 1900 | B14: 10900002 | C14: TDS on Sale of Residential Property 1 % Receivable | D14: 29382877 | E14: 0 | F14: 5080952.9 | G14: 171474.45 | H14: 34292355
A15: 1900 | B15: 10900102 | C15: TDS on Sale of Commercial Property 1 % Rece- 194IA | D15: 0 | E15: 0 | F15: 87116.7 | G15: 87116.7 | H15: 0
... A202: 1900 | B202: 45600006 | C202: Depreciation - Office Equipments | D202: 0 | E202: 0 | F202: 14576.15 | G202: 0 | H202: 14576.15
